Workbook

Sheet _README
A1: BONITE BOTTLERS LIMITED
A2: SFA — SAP Integration & Compliance Module
A4: Purpose of This Workbook
A5: A working model that demonstrates the complete logic of the SAP Integration & Compliance module.
A6: Used to validate design before development begins; will serve as the developer reference and UAT data set.
A8: Sheet Index
A9: Sheet | B9: Type | C9: Purpose
A10: _README | B10: Info | C10: This page
A11: M_Depot | B11: Master | C11: Depot Master — codes, default outlets, SAP warehouse
A12: M_SKU | B12: Master | C12: SKU Master — code, name, category, pack size, retail price
A13: M_DepotPrice | B13: Master | C13: Depot-wise default price for shortage postings
A14: M_User | B14: Master | C14: User Master — salesman, SAP code, depot, reporting manager
A15: M_Config | B15: Master | C15: System parameters — SLA, aging threshold, etc.
A16: T_Load | B16: Transaction | C16: Every SAP-pushed load. Status: Pending / Confirmed / Force-Pushed
A17: T_Sales | B17: Transaction | C17: Every sale recorded on mobile
A18: T_Unload | B18: Transaction | C18: Every unload event (derived from Load − Sales)
A19: T_ROP | B19: Transaction | C19: ROP verification — Expected vs Actual, Variance, Action
A20: T_DefaultOutletPosting | B20: Transaction | C20: Auto-postings to Default Outlet for shortages
... A25: R_AgingView | B25: Report | C25: Open loads aged by days outstanding
A27: How to Read This Workbook
A28: • Sheets starting with M_ are MASTER data (configured once).
A29: • Sheets starting with T_ are TRANSACTIONAL data (daily activity).
A30: • Sheets starting with R_ are REPORTS or VIEWS (auto-calculated from M_ and T_ sheets).
A31: • Sheets starting with _ are workbook-level helpers (README, scenario control).

Sheet M_Depot
A1: Depot Master
A2: Source of truth for depot codes, default outlets, and SAP warehouse references.
A3: NOTE: In the live SFA system, Default Outlet is maintained in Outlet Master (with "Default Outlet" flag checked).
A4: Repeated here purely for Excel-model convenience.
A6: Depot Name | B6: Depot Code | C6: Default Outlet Code | D6: Default Outlet Name | E6: SAP Warehouse | F6: Status
A7: Mwanza | B7: MWZ | C7: MWZ1000001 | D7: Mwanza Ambush | E7: MWZFWH | F7: Active
A8: Dodoma | B8: DOD | C8: DOD1000001 | D8: Dodoma Ambush | E8: DODFWH | F8: Active
A9: Mbeya | B9: MBY | C9: MBY1000001 | D9: Mbeya Ambush | E9: MBYFWH | F9: Active
A10: Dar Es Salaam | B10: DAR | C10: DAR1000001 | D10: Dar Es Salaam Ambush | E10: DARFWH | F10: Active
A11: Same | B11: SAM | C11: SAM1000001 | D11: Same Ambush | E11: SAMFWH | F11: Active
A12: Mererani | B12: MER | C12: MER1000001 | D12: Mererani Ambush | E12: MERFWH | F12: Active
A13: Tarakea | B13: TRK | C13: TRK1000001 | D13: Tarakea Ambush | E13: TRKFWH | F13: Active
A14: Tanga | B14: TAN | C14: TAN1000001 | D14: Tanga Ambush | E14: TANFWH | F14: Active
A15: Nzega | B15: NZG | C15: NZG1000001 | D15: Nzega Ambush | E15: NZGFWH | F15: Active
A16: Terrat | B16: TER | C16: TER1000001 | D16: Terrat Ambush | E16: TERFWH | F16: Active
A17: Kiteto | B17: KIT | C17: KIT1000001 | D17: Kiteto Ambush | E17: KITFWH | F17: Active
... A24: MOSHI | B24: MOS | C24: MOS1000001 | D24: MOSHI Ambush | E24: MOSFWH | F24: Active
A26: Total Active Depots: | B26: =COUNTIF(F7:F24,"Active") -> 18

Sheet M_SKU
A1: SKU (Product) Master
A2: Product attributes only. Pricing is maintained in M_DepotPrice (single source of truth for pricing).
A4: Code Prefix Legend
A5: FG - Finished Goods — RGB CSD (Returnable Glass Bottles, Carbonated Soda)
A6: KD - KNMW — Kilimanjaro Natural Mineral Water (PET and Bulk)
A7: PH - PET 500ml CSD
A8: PO - PET 300ml CSD (small-format)
A9: PT - PET 1250ml CSD (large-format / tall)
A11: Unit / Sub-Unit Rule
A12: • When Unit = Sub-Unit (Conversion = 1): product sells in whole Units only.
A13: • When Unit ≠ Sub-Unit (Conversion > 1): product can be sold in whole Units OR loose Sub-Units. Salesman toggles view on mobile.
A14: • Loads are always in whole Units. Unloads and sales may include decimals for sub-unit-capable SKUs.
A15: Example: 12 Crates + 16 Bottles of a 24/Crate SKU is stored as 12.6667 Crates internally.
A17: Product Name | B17: Code | C17: Category | D17: Sub-Category | E17: Brand | F17: Unit | G17: Sub Unit | H17: Conversion Rate | I17: Is Active | J17: Sells in Sub-Unit?
A18: Coke RGB 350ml | B18: FG001 | C18: Carbonated Soda Drink (CSD) | D18: RETURNABLE GLASS BOTTLES (RGB) | E18: COKE | F18: Crates | G18: Bottles | H18: 24 | I18: Y | J18: =IF(F18=G18,"No","Yes") -> Yes
A19: Fanta Orange RGB 350ml | B19: FG002 | C19: Carbonated Soda Drink (CSD) | D19: RETURNABLE GLASS BOTTLES (RGB) | E19: FANTA | F19: Crates | G19: Bottles | H19: 24 | I19: Y | J19: =IF(F19=G19,"No","Yes") -> Yes
A20: Fanta Passion RGB 350ml | B20: FG003 | C20: Carbonated Soda Drink (CSD) | D20: RETURNABLE GLASS BOTTLES (RGB) | E20: FANTA | F20: Crates | G20: Bottles | H20: 24 | I20: Y | J20: =IF(F20=G20,"No","Yes") -> Yes
A21: Fanta Pineapple RGB 350ml | B21: FG004 | C21: Carbonated Soda Drink (CSD) | D21: RETURNABLE GLASS BOTTLES (RGB) | E21: FANTA | F21: Crates | G21: Bottles | H21: 24 | I21: Y | J21: =IF(F21=G21,"No","Yes") -> Yes
A22: Fanta Fruit Blast RGB 350 ml | B22: FG005 | C22: Carbonated Soda Drink (CSD) | D22: RETURNABLE GLASS BOTTLES (RGB) | E22: FANTA | F22: Crates | G22: Bottles | H22: 24 | I22: Y | J22: =IF(F22=G22,"No","Yes") -> Yes
A23: Sprite 350ml | B23: FG006 | C23: Carbonated Soda Drink (CSD) | D23: RETURNABLE GLASS BOTTLES (RGB) | E23: SPRITE | F23: Crates | G23: Bottles | H23: 24 | I23: Y | J23: =IF(F23=G23,"No","Yes") -> Yes
A24: Stoney Tangawizi RGB 350ml | B24: FG007 | C24: Carbonated Soda Drink (CSD) | D24: RETURNABLE GLASS BOTTLES (RGB) | E24: STONEY | F24: Crates | G24: Bottles | H24: 24 | I24: Y | J24: =IF(F24=G24,"No","Yes") -> Yes
A25: Sparletta Pinenut RGB 350ml | B25: FG008 | C25: Carbonated Soda Drink (CSD) | D25: RETURNABLE GLASS BOTTLES (RGB) | E25: SPARLETTA | F25: Crates | G25: Bottles | H25: 24 | I25: Y | J25: =IF(F25=G25,"No","Yes") -> Yes
A26: Krest Bitter Lemon RGB 300ml | B26: FG009 | C26: Carbonated Soda Drink (CSD) | D26: RETURNABLE GLASS BOTTLES (RGB) | E26: KREST | F26: Crates | G26: Bottles | H26: 24 | I26: Y | J26: =IF(F26=G26,"No","Yes") -> Yes
A27: Krest Club Soda RGB 300ml | B27: FG010 | C27: Carbonated Soda Drink (CSD) | D27: RETURNABLE GLASS BOTTLES (RGB) | E27: KREST | F27: Crates | G27: Bottles | H27: 24 | I27: Y | J27: =IF(F27=G27,"No","Yes") -> Yes
A28: Krest Tonic Water RGB 300ml | B28: FG011 | C28: Carbonated Soda Drink (CSD) | D28: RETURNABLE GLASS BOTTLES (RGB) | E28: KREST | F28: Crates | G28: Bottles | H28: 24 | I28: Y | J28: =IF(F28=G28,"No","Yes") -> Yes
A29: Krest Ginger Ale RGB 300ml | B29: FG012 | C29: Carbonated Soda Drink (CSD) | D29: RETURNABLE GLASS BOTTLES (RGB) | E29: KREST | F29: Crates | G29: Bottles | H29: 24 | I29: Y | J29: =IF(F29=G29,"No","Yes") -> Yes
... A57: Fanta Orange Pet 1250 ML | B57: PT007 | C57: Carbonated Soda Drink (CSD) | D57: PET CSD | E57: FANTA | F57: Cases | G57: Cases | H57: 1 | I57: Y | J57: =IF(F57=G57,"No","Yes") -> No
A59: Total Active SKUs: | B59: =COUNTIF(I18:I57,"Y") -> 40
A60: SKUs Sold in Sub-Units: | B60: =COUNTIF(J18:J57,"Yes") -> 15
A61: SKUs Sold Only in Whole Units: | B61: =COUNTIF(J18:J57,"No") -> 25

Sheet M_DepotPrice
A1: Depot-wise Price Master
A2: Single source of truth for pricing. Used for shortage postings to Default Outlet and all sales reporting in this model.
A4: Lookup Cascade (Shortage Posting Logic)
A5: 1. First look for a row where Price Type = "Special" AND Code = X AND Depot Applicable = Y.
A6: 2. If found → use that special price.
A7: 3. If not found → fall back to the row where Price Type = "Default" AND Code = X AND Depot Applicable = "All".
A9: Code | B9: SKU Name | C9: Unit Price | D9: Conversion Rate | E9: Sub-Unit Price | F9: Tax % | G9: Price Type | H9: Depot Applicable
A10: FG001 | B10: =M_SKU!A18 -> Coke RGB 350ml | C10: 11780 | D10: =M_SKU!H18 -> 24 | E10: =IF(D10=1,"",ROUND(C10/D10,2)) -> 490.83 | F10: 0.18 | G10: Default | H10: All
A11: FG002 | B11: =M_SKU!A19 -> Fanta Orange RGB 350ml | C11: 11780 | D11: =M_SKU!H19 -> 24 | E11: =IF(D11=1,"",ROUND(C11/D11,2)) -> 490.83 | F11: 0.18 | G11: Default | H11: All
A12: FG003 | B12: =M_SKU!A20 -> Fanta Passion RGB 350ml | C12: 11780 | D12: =M_SKU!H20 -> 24 | E12: =IF(D12=1,"",ROUND(C12/D12,2)) -> 490.83 | F12: 0.18 | G12: Default | H12: All
A13: FG004 | B13: =M_SKU!A21 -> Fanta Pineapple RGB 350ml | C13: 11780 | D13: =M_SKU!H21 -> 24 | E13: =IF(D13=1,"",ROUND(C13/D13,2)) -> 490.83 | F13: 0.18 | G13: Default | H13: All
A14: FG005 | B14: =M_SKU!A22 -> Fanta Fruit Blast RGB 350 ml | C14: 11780 | D14: =M_SKU!H22 -> 24 | E14: =IF(D14=1,"",ROUND(C14/D14,2)) -> 490.83 | F14: 0.18 | G14: Default | H14: All
A15: FG006 | B15: =M_SKU!A23 -> Sprite 350ml | C15: 11780 | D15: =M_SKU!H23 -> 24 | E15: =IF(D15=1,"",ROUND(C15/D15,2)) -> 490.83 | F15: 0.18 | G15: Default | H15: All
A16: FG007 | B16: =M_SKU!A24 -> Stoney Tangawizi RGB 350ml | C16: 11780 | D16: =M_SKU!H24 -> 24 | E16: =IF(D16=1,"",ROUND(C16/D16,2)) -> 490.83 | F16: 0.18 | G16: Default | H16: All
A17: FG008 | B17: =M_SKU!A25 -> Sparletta Pinenut RGB 350ml | C17: 11780 | D17: =M_SKU!H25 -> 24 | E17: =IF(D17=1,"",ROUND(C17/D17,2)) -> 490.83 | F17: 0.18 | G17: Default | H17: All
A18: FG009 | B18: =M_SKU!A26 -> Krest Bitter Lemon RGB 300ml | C18: 11780 | D18: =M_SKU!H26 -> 24 | E18: =IF(D18=1,"",ROUND(C18/D18,2)) -> 490.83 | F18: 0.18 | G18: Default | H18: All
A19: FG010 | B19: =M_SKU!A27 -> Krest Club Soda RGB 300ml | C19: 11780 | D19: =M_SKU!H27 -> 24 | E19: =IF(D19=1,"",ROUND(C19/D19,2)) -> 490.83 | F19: 0.18 | G19: Default | H19: All
A20: FG011 | B20: =M_SKU!A28 -> Krest Tonic Water RGB 300ml | C20: 11780 | D20: =M_SKU!H28 -> 24 | E20: =IF(D20=1,"",ROUND(C20/D20,2)) -> 490.83 | F20: 0.18 | G20: Default | H20: All
A21: FG012 | B21: =M_SKU!A29 -> Krest Ginger Ale RGB 300ml | C21: 11780 | D21: =M_SKU!H29 -> 24 | E21: =IF(D21=1,"",ROUND(C21/D21,2)) -> 490.83 | F21: 0.18 | G21: Default | H21: All
... A49: PT007 | B49: =M_SKU!A57 -> Fanta Orange Pet 1250 ML | C49: 8305 | D49: =M_SKU!H57 -> 1 | E49: =IF(D49=1,"",ROUND(C49/D49,2)) | F49: 0.18 | G49: Default | H49: All
A50: — Special Prices —
A51: KD003 | B51: =M_SKU!A34 -> KNMW 1500ml | C51: 3559 | D51: =M_SKU!H34 -> 1 | E51: =IF(D51=1,"",ROUND(C51/D51,2)) | F51: 0.18 | G51: Special | H51: Dar Es Salaam
A52: KD007 | B52: =M_SKU!A38 -> KNMW 1000ml(6 Pack) | C52: 2119 | D52: =M_SKU!H38 -> 1 | E52: =IF(D52=1,"",ROUND(C52/D52,2)) | F52: 0.18 | G52: Special | H52: Dar Es Salaam
A54: Default Price Rows: | C54: =COUNTIF(G10:G52,"Default") -> 40
A55: Special Price Rows: | C55: =COUNTIF(G10:G52,"Special") -> 2
A57: Price Lookup Demo
A58: Demonstrates the cascade: enter SKU + Depot below to see the resolved price.
A60: SKU Code: | C60: KD007
A61: Depot: | C61: Dar Es Salaam
A62: Resolved Price: | C62: {=IFERROR(INDEX(C10:C52,MATCH(1,(A10:A52=C60)*(H10:H52=C61)*(G10:G52="Special"),0)),INDEX(C10:C52,MATCH(1,(A10:A52=C60)*(G10:G52="Default"),0)))} -> 2119 | D62: {=_xlfn.LET(_xlpm.Special,_xlfn._xlws.FILTER($C$10:$C$52,($A$10:$A$52=C60)*($G$10:$G$52="Special")*($H$10:$H$52=C61),""),_xlpm.Default,_xlfn._xlws.FILTER($C$10:$C$52,($A$10:$A$52=C60)*($G$10:$G$52="Default"),""),IF(_xlpm.Special<>"",_xlpm.Special,_xlpm.Default))} -> 2119
A63: Source: | B63: =IFERROR(IF(INDEX(G10:G52,MATCH(1,(A10:A52=C60)*(H10:H52=C61)*(G10:G52="Special"),0))="Special","Special (depot override)","Default"),"Default") -> Default
A65: Note: Formulas above use INDEX/MATCH with multiple conditions; works in Excel 365 / 2021+. For older Excel, use as array formula (Ctrl+Shift+Enter).

Sheet M_User
A1: User Master
A2: All users in scope for the SAP Integration & Compliance model: Salesmen, Sales Supervisors, and Clerks.
A4: Notes
A5: • Salesmen: SAP-pushed loads map to these users via SAP Code. They appear on mobile, sell, and unload.
A6: • Sales Supervisors: receive variance reports for salesmen reporting to them (parallel 24h SLA logging).
A7: • Clerks: confirm SAP-pushed invoices in the Integration page; verify Actual ROP at end of day.
A8: • Rows highlighted yellow = Sales Supervisors. Rows highlighted green = Clerks. Plain rows = Salesmen.
A9: • "BBL_SUP_***" and "BBL_CLK_***" Emp Codes are placeholders to be replaced with real codes before go-live.
A11: User ID | B11: Emp Code | C11: User Name | D11: SAP Code | E11: Depot Code | F11: Role | G11: Reporting Manager | H11: Reporting Mgr User ID | I11: Reporting Manager Email | J11: Is Active
A12: 89 | B12: BBL2211 | C12: Omary O. Seif | D12: DSM300140 | E12: DAR | F12: Salesman | G12: Rose Meshack Kambey | H12: 86 | I12: Rose.Meshack@bbl.co.tz | J12: Y
A13: 88 | B13: BBL2446 | C13: Doglas E. Shirima | D13: ARS000069 | E13: ARS | F13: Salesman | G13: Kelvin V. Kuwese | H13: 79 | I13: Kelvin.Kuwese@bbl.co.tz | J13: Y
A14: 76 | B14: BBL2769 | C14: Gloria Florence Temba | D14: MOS100535 | E14: MOS | F14: Salesman | G14: Rachel Emanuel Kissota | H14: 57 | I14: Rachel.Kissota@bbl.co.tz | J14: Y
A15: 75 | B15: BBL2916 | C15: Nickson Zakaria Soingei | D15: MOS100658 | E15: MOS | F15: Salesman | G15: Rachel Emanuel Kissota | H15: 57 | I15: Rachel.Kissota@bbl.co.tz | J15: Y
A16: 74 | B16: MSL960 | C16: Ritha Nemes Sambaya | D16: MOS100639 | E16: MOS | F16: Salesman | G16: Rachel Emanuel Kissota | H16: 57 | I16: Rachel.Kissota@bbl.co.tz | J16: Y
A17: 73 | B17: BBL1959 | C17: George Gibson Mmary | D17: MOS100200 | E17: MOS | F17: Salesman | G17: Rachel Emanuel Kissota | H17: 57 | I17: Rachel.Kissota@bbl.co.tz | J17: Y
A18: 72 | B18: BBL1183 | C18: Erick K. Mkama | D18: MOS100209 | E18: MOS | F18: Salesman | G18: Rachel Emanuel Kissota | H18: 57 | I18: Rachel.Kissota@bbl.co.tz | J18: Y
A19: 71 | B19: BBL1723 | C19: Frank Samwel Kahewanga | D19: MOS100215 | E19: MOS | F19: Salesman | G19: Rachel Emanuel Kissota | H19: 57 | I19: Rachel.Kissota@bbl.co.tz | J19: Y
A20: 70 | B20: BBL1759 | C20: Seleman Abdalah Mshana | D20: MOS100171 | E20: MOS | F20: Salesman | G20: Moses Titus Shija | H20: 56 | I20: Moses.Shija@bbl.co.tz | J20: Y
A21: 69 | B21: MSL1118 | C21: Samson Felix Ngowi | D21: MOS100842 | E21: MOS | F21: Salesman | G21: Moses Titus Shija | H21: 56 | I21: Moses.Shija@bbl.co.tz | J21: Y
A22: 68 | B22: BBL2732 | C22: Emmanueli Steven John | D22: MOS100633 | E22: MOS | F22: Salesman | G22: Maria M. Mchagi | H22: 55 | I22: Maria.Mchagi@bbl.co.tz | J22: Y
A23: 67 | B23: BBL1963 | C23: Priscus J Justine | D23: MOS100022 | E23: MOS | F23: Salesman | G23: Moses Titus Shija | H23: 56 | I23: Moses.Shija@bbl.co.tz | J23: Y
... A44: 29 | B44: BBL2285 | C44: Piniel Julius Singo | D44: MOS100654 | E44: MOS | F44: Salesman | G44: Steven Olais Kivuyo | H44: 28 | I44: stephen.kivuyo@bbl.co.tz | J44: Y
A45: 28 | B45: BBL_SUP_028 | C45: Steven Olais Kivuyo | E45: MOS | F45: Sales Supervisor | I45: stephen.kivuyo@bbl.co.tz | J45: Y
A46: 46 | B46: BBL_SUP_046 | C46: Beatrice Urio | E46: MOS | F46: Sales Supervisor | I46: Beatrice.Urio@bbl.co.tz | J46: Y
A47: 47 | B47: BBL_SUP_047 | C47: Stephen F. Njama | E47: MOS | F47: Sales Supervisor | I47: Stephen.Njama@bbl.co.tz | J47: Y
A48: 55 | B48: BBL_SUP_055 | C48: Maria M. Mchagi | E48: MOS | F48: Sales Supervisor | I48: Maria.Mchagi@bbl.co.tz | J48: Y
A49: 56 | B49: BBL_SUP_056 | C49: Moses Titus Shija | E49: MOS | F49: Sales Supervisor | I49: Moses.Shija@bbl.co.tz | J49: Y
A50: 57 | B50: BBL_SUP_057 | C50: Rachel Emanuel Kissota | E50: MOS | F50: Sales Supervisor | I50: Rachel.Kissota@bbl.co.tz | J50: Y
A51: 79 | B51: BBL_SUP_079 | C51: Kelvin V. Kuwese | E51: ARS | F51: Sales Supervisor | I51: Kelvin.Kuwese@bbl.co.tz | J51: Y
A52: 86 | B52: BBL_SUP_086 | C52: Rose Meshack Kambey | E52: DAR | F52: Sales Supervisor | I52: Rose.Meshack@bbl.co.tz | J52: Y
A53: C001 | B53: BBL_CLK_001 | C53: Clerk — Dar Es Salaam | E53: DAR | F53: Clerk | J53: Y
A54: C002 | B54: BBL_CLK_002 | C54: Clerk — Arusha | E54: ARS | F54: Clerk | J54: Y
A55: C003 | B55: BBL_CLK_003 | C55: Clerk — Moshi | E55: MOS | F55: Clerk | J55: Y
A57: Total Users: | C57: =COUNTA(A12:A55) -> 44
A58: - Salesmen: | C58: =COUNTIF(F12:F55,"Salesman") -> 33
A59: - Sales Supervisors: | C59: =COUNTIF(F12:F55,"Sales Supervisor") -> 8
A60: - Clerks: | C60: =COUNTIF(F12:F55,"Clerk") -> 3
A62: Active Users: | C62: =COUNTIF(J12:J55,"Y") -> 44
A64: Data Integrity Checks
A65: Duplicate SAP Codes: | C65: =SUMPRODUCT((D12:D55<>"")*(COUNTIF(D12:D55,D12:D55)>1)) -> 0
A66: Duplicate User IDs: | C66: =SUMPRODUCT((A12:A55<>"")*(COUNTIF(A12:A55,A12:A55)>1)) -> 0
A67: Salesmen with no SAP Code: | C67: =SUMPRODUCT((F12:F55="Salesman")*(D12:D55="")) -> 0
A69: (All three values above should be 0 for clean data)

Sheet M_Config
A1: System Configuration
A2: Global parameters used throughout the model. Editable inputs are highlighted in pale yellow.
A3: Live system equivalent: System Settings page in SFA Web, accessible to authorised admin only.
A5: SAP Integration & Compliance Parameters
A6: Parameter | B6: Value | C6: Unit | D6: Notes
A7: Reason Logging SLA | B7: 24 | C7: Hours | D7: Supervisor must log variance reason within this window; aged variances flagged for management.
A8: Aging Alert Threshold | B8: 7 | C8: Days | D8: Open loads outstanding beyond this threshold appear in the Aging View as stale loads.
A9: Force-Push Approval Required | B9: No | D9: Clerk authority is sufficient to force-push an unmapped SAP invoice. Controlled via Roles & Permissions.
A10: Geo-Fence Radius | B10: 100 | C10: Metres | D10: Reference value from main pilot. Used for delivery and outlet visit validation; not used directly here.
A11: Variance Tolerance | B11: 0 | C11: Units | D11: Zero tolerance: any non-zero variance between Expected ROP and Actual ROP triggers a variance report.
A12: Default Outlet Price Source | B12: Depot Default Price | D12: Pricing source for shortage postings. Looked up via the M_DepotPrice cascade.
A13: Pricing Cascade Order | B13: Special → Default | D13: For shortage postings: try Special price first (Depot+SKU), then fall back to Default (SKU, All depots).
A14: Model Currency | B14: TZS | D14: Tanzanian Shilling. Used for all monetary displays in this model.
A16: Color Coding
A17: Pale Yellow + Blue Bold | B17: Editable input parameter

Sheet T_Load
A1: T_Load — SAP Integration Page (Inbound)
A2: Every SAP-pushed invoice (van load) lands here. Each row = one SKU+Batch line. Rows with the same Load ID belong to the same SAP document.
A3: Clerk reviews each Load ID and either Confirms (auto-mapped) or Force-Pushes (if SAP Code does not resolve in User Master).
A4: Once Confirmed, the load flows into Van Load (the salesman sees stock on his mobile).
A6: Column Groups: | B6: Identification | D6: From SAP | F6: Resolved by SFA | H6: State | J6: Exception Handling | L6: Derived Key
A8: Load ID | B8: SAP Doc Number | C8: Posting/Load Date | D8: SAP Code | E8: SAP Dest Name | F8: Mapped User ID | G8: Mapped Salesman Name | H8: Mapped Depot | I8: SAP Warehouse Code | J8: SKU Code | K8: SKU Name | L8: Batch Number | M8: Production Date | N8: Expiry Date | O8: Quantity (Units) | P8: Status | Q8: Confirmed By | R8: Confirmed On | S8: Force-Push Reason | T8: Remarks | U8: Stock Key
A9: L-0001 | B9: 166147 | C9: 46179 | D9: MOS100802 | E9: Joyline J Lyimo | F9: =IFERROR(INDEX(M_User!$A$12:$J$67,MATCH(D9,M_User!$D$12:$D$67,0),1),"UNMAPPED") -> 45 | G9: =IFERROR(INDEX(M_User!$A$12:$J$67,MATCH(D9,M_User!$D$12:$D$67,0),3),"UNMAPPED") -> Joyline J Lyimo | H9: =IFERROR(INDEX(M_User!$A$12:$J$67,MATCH(D9,M_User!$D$12:$D$67,0),5),"UNMAPPED") -> MOS | I9: MOSFWH | J9: PH001 | K9: =IFERROR(INDEX(M_SKU!$A$18:$J$57,MATCH(J9,M_SKU!$B$18:$B$57,0),1),"UNKNOWN SKU") -> Coke Pet 500ML ( x12) | L9: CK6-33411 | M9: 46177 | N9: 46288 | O9: 70 | P9: Pending Confirmation | U9: =D9 & "|" & J9 & "|" & L9 -> MOS100802|PH001|CK6-33411
A10: L-0001 | B10: 166147 | C10: 46179 | D10: MOS100802 | E10: Joyline J Lyimo | F10: =IFERROR(INDEX(M_User!$A$12:$J$67,MATCH(D10,M_User!$D$12:$D$67,0),1),"UNMAPPED") -> 45 | G10: =IFERROR(INDEX(M_User!$A$12:$J$67,MATCH(D10,M_User!$D$12:$D$67,0),3),"UNMAPPED") -> Joyline J Lyimo | H10: =IFERROR(INDEX(M_User!$A$12:$J$67,MATCH(D10,M_User!$D$12:$D$67,0),5),"UNMAPPED") -> MOS | I10: MOSFWH | J10: PH002 | K10: =IFERROR(INDEX(M_SKU!$A$18:$J$57,MATCH(J10,M_SKU!$B$18:$B$57,0),1),"UNKNOWN SKU") -> Sprite Pet 500ML (x 12) | L10: CK6-33362 | M10: 46158 | N10: 46269 | O10: 15 | P10: Pending Confirmation | U10: =D10 & "|" & J10 & "|" & L10 -> MOS100802|PH002|CK6-33362
A11: L-0001 | B11: 166147 | C11: 46179 | D11: MOS100802 | E11: Joyline J Lyimo | F11: =IFERROR(INDEX(M_User!$A$12:$J$67,MATCH(D11,M_User!$D$12:$D$67,0),1),"UNMAPPED") -> 45 | G11: =IFERROR(INDEX(M_User!$A$12:$J$67,MATCH(D11,M_User!$D$12:$D$67,0),3),"UNMAPPED") -> Joyline J Lyimo | H11: =IFERROR(INDEX(M_User!$A$12:$J$67,MATCH(D11,M_User!$D$12:$D$67,0),5),"UNMAPPED") -> MOS | I11: MOSFWH | J11: PH003 | K11: =IFERROR(INDEX(M_SKU!$A$18:$J$57,MATCH(J11,M_SKU!$B$18:$B$57,0),1),"UNKNOWN SKU") -> Fanta Orange Pet 500ML ( x 12) | L11: CK6-33405 | M11: 46172 | N11: 46283 | O11: 40 | P11: Pending Confirmation | U11: =D11 & "|" & J11 & "|" & L11 -> MOS100802|PH003|CK6-33405
A12: L-0001 | B12: 166147 | C12: 46179 | D12: MOS100802 | E12: Joyline J Lyimo | F12: =IFERROR(INDEX(M_User!$A$12:$J$67,MATCH(D12,M_User!$D$12:$D$67,0),1),"UNMAPPED") -> 45 | G12: =IFERROR(INDEX(M_User!$A$12:$J$67,MATCH(D12,M_User!$D$12:$D$67,0),3),"UNMAPPED") -> Joyline J Lyimo | H12: =IFERROR(INDEX(M_User!$A$12:$J$67,MATCH(D12,M_User!$D$12:$D$67,0),5),"UNMAPPED") -> MOS | I12: MOSFWH | J12: PH004 | K12: =IFERROR(INDEX(M_SKU!$A$18:$J$57,MATCH(J12,M_SKU!$B$18:$B$57,0),1),"UNKNOWN SKU") -> Fanta Passion Pet 500ML ( x12) | L12: CK5-33334 | M12: 46151 | N12: 46262 | O12: 15 | P12: Pending Confirmation | U12: =D12 & "|" & J12 & "|" & L12 -> MOS100802|PH004|CK5-33334
A13: L-0001 | B13: 166147 | C13: 46179 | D13: MOS100802 | E13: Joyline J Lyimo | F13: =IFERROR(INDEX(M_User!$A$12:$J$67,MATCH(D13,M_User!$D$12:$D$67,0),1),"UNMAPPED") -> 45 | G13: =IFERROR(INDEX(M_User!$A$12:$J$67,MATCH(D13,M_User!$D$12:$D$67,0),3),"UNMAPPED") -> Joyline J Lyimo | H13: =IFERROR(INDEX(M_User!$A$12:$J$67,MATCH(D13,M_User!$D$12:$D$67,0),5),"UNMAPPED") -> MOS | I13: MOSFWH | J13: PH007 | K13: =IFERROR(INDEX(M_SKU!$A$18:$J$57,MATCH(J13,M_SKU!$B$18:$B$57,0),1),"UNKNOWN SKU") -> Stoney Tangawizi Pet 500 ml ( x12) | L13: CK6-33375 | M13: 46161 | N13: 46272 | O13: 5 | P13: Pending Confirmation | U13: =D13 & "|" & J13 & "|" & L13 -> MOS100802|PH007|CK6-33375
A14: L-0001 | B14: 166147 | C14: 46179 | D14: MOS100802 | E14: Joyline J Lyimo | F14: =IFERROR(INDEX(M_User!$A$12:$J$67,MATCH(D14,M_User!$D$12:$D$67,0),1),"UNMAPPED") -> 45 | G14: =IFERROR(INDEX(M_User!$A$12:$J$67,MATCH(D14,M_User!$D$12:$D$67,0),3),"UNMAPPED") -> Joyline J Lyimo | H14: =IFERROR(INDEX(M_User!$A$12:$J$67,MATCH(D14,M_User!$D$12:$D$67,0),5),"UNMAPPED") -> MOS | I14: MOSFWH | J14: PH008 | K14: =IFERROR(INDEX(M_SKU!$A$18:$J$57,MATCH(J14,M_SKU!$B$18:$B$57,0),1),"UNKNOWN SKU") -> Sparletta Pinenut Pet 500 ml ( x12) | L14: CK5-33370 | M14: 46161 | N14: 46272 | O14: 5 | P14: Pending Confirmation | U14: =D14 & "|" & J14 & "|" & L14 -> MOS100802|PH008|CK5-33370
A15: L-0002 | B15: 166148 | C15: 46179 | D15: MOS100645 | E15: Riziki Rajabu | F15: =IFERROR(INDEX(M_User!$A$12:$J$67,MATCH(D15,M_User!$D$12:$D$67,0),1),"UNMAPPED") -> 50 | G15: =IFERROR(INDEX(M_User!$A$12:$J$67,MATCH(D15,M_User!$D$12:$D$67,0),3),"UNMAPPED") -> Riziki Rajabu Mghamba | H15: =IFERROR(INDEX(M_User!$A$12:$J$67,MATCH(D15,M_User!$D$12:$D$67,0),5),"UNMAPPED") -> MOS | I15: MOSFWH | J15: FG001 | K15: =IFERROR(INDEX(M_SKU!$A$18:$J$57,MATCH(J15,M_SKU!$B$18:$B$57,0),1),"UNKNOWN SKU") -> Coke RGB 350ml | L15: CK3-33408 | M15: 46175 | N15: 46539 | O15: 15.58 | P15: Pending Confirmation | U15: =D15 & "|" & J15 & "|" & L15 -> MOS100645|FG001|CK3-33408
A16: L-0002 | B16: 166148 | C16: 46179 | D16: MOS100645 | E16: Riziki Rajabu | F16: =IFERROR(INDEX(M_User!$A$12:$J$67,MATCH(D16,M_User!$D$12:$D$67,0),1),"UNMAPPED") -> 50 | G16: =IFERROR(INDEX(M_User!$A$12:$J$67,MATCH(D16,M_User!$D$12:$D$67,0),3),"UNMAPPED") -> Riziki Rajabu Mghamba | H16: =IFERROR(INDEX(M_User!$A$12:$J$67,MATCH(D16,M_User!$D$12:$D$67,0),5),"UNMAPPED") -> MOS | I16: MOSFWH | J16: FG001 | K16: =IFERROR(INDEX(M_SKU!$A$18:$J$57,MATCH(J16,M_SKU!$B$18:$B$57,0),1),"UNKNOWN SKU") -> Coke RGB 350ml | L16: CK3-33409 | M16: 46175 | N16: 46539 | O16: 64.42 | P16: Pending Confirmation | U16: =D16 & "|" & J16 & "|" & L16 -> MOS100645|FG001|CK3-33409
A17: L-0002 | B17: 166148 | C17: 46179 | D17: MOS100645 | E17: Riziki Rajabu | F17: =IFERROR(INDEX(M_User!$A$12:$J$67,MATCH(D17,M_User!$D$12:$D$67,0),1),"UNMAPPED") -> 50 | G17: =IFERROR(INDEX(M_User!$A$12:$J$67,MATCH(D17,M_User!$D$12:$D$67,0),3),"UNMAPPED") -> Riziki Rajabu Mghamba | H17: =IFERROR(INDEX(M_User!$A$12:$J$67,MATCH(D17,M_User!$D$12:$D$67,0),5),"UNMAPPED") -> MOS | I17: MOSFWH | J17: FG002 | K17: =IFERROR(INDEX(M_SKU!$A$18:$J$57,MATCH(J17,M_SKU!$B$18:$B$57,0),1),"UNKNOWN SKU") -> Fanta Orange RGB 350ml | L17: CK3-33407 | M17: 46174 | N17: 46538 | O17: 30 | P17: Pending Confirmation | U17: =D17 & "|" & J17 & "|" & L17 -> MOS100645|FG002|CK3-33407
A18: L-0002 | B18: 166148 | C18: 46179 | D18: MOS100645 | E18: Riziki Rajabu | F18: =IFERROR(INDEX(M_User!$A$12:$J$67,MATCH(D18,M_User!$D$12:$D$67,0),1),"UNMAPPED") -> 50 | G18: =IFERROR(INDEX(M_User!$A$12:$J$67,MATCH(D18,M_User!$D$12:$D$67,0),3),"UNMAPPED") -> Riziki Rajabu Mghamba | H18: =IFERROR(INDEX(M_User!$A$12:$J$67,MATCH(D18,M_User!$D$12:$D$67,0),5),"UNMAPPED") -> MOS | I18: MOSFWH | J18: FG003 | K18: =IFERROR(INDEX(M_SKU!$A$18:$J$57,MATCH(J18,M_SKU!$B$18:$B$57,0),1),"UNKNOWN SKU") -> Fanta Passion RGB 350ml | L18: CK3-33387 | M18: 46164 | N18: 46528 | O18: 15 | P18: Pending Confirmation | U18: =D18 & "|" & J18 & "|" & L18 -> MOS100645|FG003|CK3-33387
A19: L-0002 | B19: 166148 | C19: 46179 | D19: MOS100645 | E19: Riziki Rajabu | F19: =IFERROR(INDEX(M_User!$A$12:$J$67,MATCH(D19,M_User!$D$12:$D$67,0),1),"UNMAPPED") -> 50 | G19: =IFERROR(INDEX(M_User!$A$12:$J$67,MATCH(D19,M_User!$D$12:$D$67,0),3),"UNMAPPED") -> Riziki Rajabu Mghamba | H19: =IFERROR(INDEX(M_User!$A$12:$J$67,MATCH(D19,M_User!$D$12:$D$67,0),5),"UNMAPPED") -> MOS | I19: MOSFWH | J19: FG004 | K19: =IFERROR(INDEX(M_SKU!$A$18:$J$57,MATCH(J19,M_SKU!$B$18:$B$57,0),1),"UNKNOWN SKU") -> Fanta Pineapple RGB 350ml | L19: CK3-33385 | M19: 46163 | N19: 46527 | O19: 15 | P19: Pending Confirmation | U19: =D19 & "|" & J19 & "|" & L19 -> MOS100645|FG004|CK3-33385
A20: L-0002 | B20: 166148 | C20: 46179 | D20: MOS100645 | E20: Riziki Rajabu | F20: =IFERROR(INDEX(M_User!$A$12:$J$67,MATCH(D20,M_User!$D$12:$D$67,0),1),"UNMAPPED") -> 50 | G20: =IFERROR(INDEX(M_User!$A$12:$J$67,MATCH(D20,M_User!$D$12:$D$67,0),3),"UNMAPPED") -> Riziki Rajabu Mghamba | H20: =IFERROR(INDEX(M_User!$A$12:$J$67,MATCH(D20,M_User!$D$12:$D$67,0),5),"UNMAPPED") -> MOS | I20: MOSFWH | J20: FG005 | K20: =IFERROR(INDEX(M_SKU!$A$18:$J$57,MATCH(J20,M_SKU!$B$18:$B$57,0),1),"UNKNOWN SKU") -> Fanta Fruit Blast RGB 350 ml | L20: CK3-33402 | M20: 46171 | N20: 46535 | O20: 12 | P20: Pending Confirmation | U20: =D20 & "|" & J20 & "|" & L20 -> MOS100645|FG005|CK3-33402
... A439: L-0020 | B439: 4078166 | C439: 46179 | D439: DSM300140 | E439: Omary seif | F439: =IFERROR(INDEX(M_User!$A$12:$J$67,MATCH(D439,M_User!$D$12:$D$67,0),1),"UNMAPPED") -> 89 | G439: =IFERROR(INDEX(M_User!$A$12:$J$67,MATCH(D439,M_User!$D$12:$D$67,0),3),"UNMAPPED") -> Omary O. Seif | H439: =IFERROR(INDEX(M_User!$A$12:$J$67,MATCH(D439,M_User!$D$12:$D$67,0),5),"UNMAPPED") -> DAR | I439: DSMFWH | J439: KD007 | K439: =IFERROR(INDEX(M_SKU!$A$18:$J$57,MATCH(J439,M_SKU!$B$18:$B$57,0),1),"UNKNOWN SKU") -> KNMW 1000ml(6 Pack) | L439: CK4-833 | M439: 46167 | N439: 46531 | O439: 300 | P439: Pending Confirmation | U439: =D439 & "|" & J439 & "|" & L439 -> DSM300140|KD007|CK4-833
A442: SUMMARY
A443: Total Load Rows: | B443: =COUNTA(A9:A439) -> 431
A444: Unique Invoices: | B444: =SUMPRODUCT(1/COUNTIF(B9:B439,B9:B439)) -> 20
A445: Unique Salesmen (SAP): | B445: =SUMPRODUCT(1/COUNTIF(D9:D439,D9:D439)) -> 18
A446: Unmapped Rows (Force-Push needed): | B446: =COUNTIF(F9:F439,"UNMAPPED") -> 24
A448: Status Breakdown:
A449: Pending Confirmation: | B449: =COUNTIF(P9:P439,"Pending Confirmation") -> 431
A450: Confirmed: | B450: =COUNTIF(P9:P439,"Confirmed") -> 0
A451: Force-Pushed: | B451: =COUNTIF(P9:P439,"Force-Pushed") -> 0
A452: Rejected: | B452: =COUNTIF(P9:P439,"Rejected") -> 0
A454: Data Integrity Checks
A455: Unique Stock Keys (rows): | B455: =SUMPRODUCT(1/COUNTIF(U9:U439,U9:U439)) -> 424
A456: Rows with UNKNOWN SKU: | B456: =COUNTIF(K9:K439,"UNKNOWN SKU") -> 0
A457: Total Quantity Across All Loads: | B457: =SUM(O9:O439) -> 8286

Sheet T_Sales
A1: T_Sales — Mobile Sales Recorded by Salesmen
A2: Every sale recorded on a salesman's mobile app. Each row = one outlet visit + one SKU+Batch line.
A3: IMPORTANT: Sales records are IMMUTABLE. They cannot be modified after entry. Variance resolution flows around this constraint.
A4: Used downstream to compute Expected ROP = Load − Sales (per Salesman × SKU × Batch).
A6: Column Groups: | B6: Identification | D6: Mobile-Entered | F6: Resolved by SFA | H6: Pricing (Cascade) | J6: Derived Key
A8: Sale ID | B8: Load ID | C8: Sale Date | D8: Salesman SAP Code | E8: Salesman Name | F8: Salesman Depot | G8: Outlet Code | H8: Outlet Name | I8: SKU Code | J8: SKU Name | K8: Batch Number | L8: Quantity (Units) | M8: Unit Price (TZS) | N8: Sale Value (TZS) | O8: Stock Key
A9: S-00084 | B9: L-0019 | C9: 46179 | D9: ARS000069 | E9: =IFERROR(INDEX(M_User!$A$12:$J$67,MATCH(D9,M_User!$D$12:$D$67,0),3),"UNMAPPED") -> Doglas E. Shirima | F9: =IFERROR(INDEX(M_User!$A$12:$J$67,MATCH(D9,M_User!$D$12:$D$67,0),5),"UNMAPPED") -> ARS | G9: OUT-ARS-001 | H9: Sokoine Road Stores | I9: FG001 | J9: =IFERROR(INDEX(M_SKU!$A$18:$J$57,MATCH(I9,M_SKU!$B$18:$B$57,0),1),"UNKNOWN SKU") -> Coke RGB 350ml | K9: CK3-33379 | L9: 4.4610496 | M9: {=IFERROR(INDEX(M_DepotPrice!$C$10:$C$52,MATCH(1,(M_DepotPrice!$A$10:$A$52=I9)*(M_DepotPrice!$H$10:$H$52=IFERROR(INDEX(M_Depot!$A$7:$A$24,MATCH(F9,M_Depot!$B$7:$B$24,0)),""))*(M_DepotPrice!$G$10:$G$52="Special"),0)),INDEX(M_DepotPrice!$C$10:$C$52,MATCH(1,(M_DepotPrice!$A$10:$A$52=I9)*(M_DepotPrice!$G$10:$G$52="Default"),0)))} -> 11780 | N9: =(L9*M9)*1.18 -> 62010.374 | O9: =D9 & "|" & I9 & "|" & K9 -> ARS000069|FG001|CK3-33379 | P9: =ROUND(M9*1.18*L9,0) -> 62010
A10: S-00013 | B10: L-0019 | C10: 46179 | D10: ARS000069 | E10: =IFERROR(INDEX(M_User!$A$12:$J$67,MATCH(D10,M_User!$D$12:$D$67,0),3),"UNMAPPED") -> Doglas E. Shirima | F10: =IFERROR(INDEX(M_User!$A$12:$J$67,MATCH(D10,M_User!$D$12:$D$67,0),5),"UNMAPPED") -> ARS | G10: OUT-ARS-001 | H10: Sokoine Road Stores | I10: FG003 | J10: =IFERROR(INDEX(M_SKU!$A$18:$J$57,MATCH(I10,M_SKU!$B$18:$B$57,0),1),"UNKNOWN SKU") -> Fanta Passion RGB 350ml | K10: CK3-33290 | L10: 0.61213082 | M10: {=IFERROR(INDEX(M_DepotPrice!$C$10:$C$52,MATCH(1,(M_DepotPrice!$A$10:$A$52=I10)*(M_DepotPrice!$H$10:$H$52=IFERROR(INDEX(M_Depot!$A$7:$A$24,MATCH(F10,M_Depot!$B$7:$B$24,0)),""))*(M_DepotPrice!$G$10:$G$52="Special"),0)),INDEX(M_DepotPrice!$C$10:$C$52,MATCH(1,(M_DepotPrice!$A$10:$A$52=I10)*(M_DepotPrice!$G$10:$G$52="Default"),0)))} -> 11780 | N10: =(L10*M10)*1.18 -> 8508.8632 | O10: =D10 & "|" & I10 & "|" & K10 -> ARS000069|FG003|CK3-33290
A11: S-00015 | B11: L-0019 | C11: 46179 | D11: ARS000069 | E11: =IFERROR(INDEX(M_User!$A$12:$J$67,MATCH(D11,M_User!$D$12:$D$67,0),3),"UNMAPPED") -> Doglas E. Shirima | F11: =IFERROR(INDEX(M_User!$A$12:$J$67,MATCH(D11,M_User!$D$12:$D$67,0),5),"UNMAPPED") -> ARS | G11: OUT-ARS-001 | H11: Sokoine Road Stores | I11: FG004 | J11: =IFERROR(INDEX(M_SKU!$A$18:$J$57,MATCH(I11,M_SKU!$B$18:$B$57,0),1),"UNKNOWN SKU") -> Fanta Pineapple RGB 350ml | K11: CK5-33354 | L11: 0.46663565 | M11: {=IFERROR(INDEX(M_DepotPrice!$C$10:$C$52,MATCH(1,(M_DepotPrice!$A$10:$A$52=I11)*(M_DepotPrice!$H$10:$H$52=IFERROR(INDEX(M_Depot!$A$7:$A$24,MATCH(F11,M_Depot!$B$7:$B$24,0)),""))*(M_DepotPrice!$G$10:$G$52="Special"),0)),INDEX(M_DepotPrice!$C$10:$C$52,MATCH(1,(M_DepotPrice!$A$10:$A$52=I11)*(M_DepotPrice!$G$10:$G$52="Default"),0)))} -> 11780 | N11: =(L11*M11)*1.18 -> 6486.4222 | O11: =D11 & "|" & I11 & "|" & K11 -> ARS000069|FG004|CK5-33354
A12: S-00016 | B12: L-0019 | C12: 46179 | D12: ARS000069 | E12: =IFERROR(INDEX(M_User!$A$12:$J$67,MATCH(D12,M_User!$D$12:$D$67,0),3),"UNMAPPED") -> Doglas E. Shirima | F12: =IFERROR(INDEX(M_User!$A$12:$J$67,MATCH(D12,M_User!$D$12:$D$67,0),5),"UNMAPPED") -> ARS | G12: OUT-ARS-001 | H12: Sokoine Road Stores | I12: FG006 | J12: =IFERROR(INDEX(M_SKU!$A$18:$J$57,MATCH(I12,M_SKU!$B$18:$B$57,0),1),"UNKNOWN SKU") -> Sprite 350ml | K12: CK3-33306 | L12: 0.2439 | M12: {=IFERROR(INDEX(M_DepotPrice!$C$10:$C$52,MATCH(1,(M_DepotPrice!$A$10:$A$52=I12)*(M_DepotPrice!$H$10:$H$52=IFERROR(INDEX(M_Depot!$A$7:$A$24,MATCH(F12,M_Depot!$B$7:$B$24,0)),""))*(M_DepotPrice!$G$10:$G$52="Special"),0)),INDEX(M_DepotPrice!$C$10:$C$52,MATCH(1,(M_DepotPrice!$A$10:$A$52=I12)*(M_DepotPrice!$G$10:$G$52="Default"),0)))} -> 11780 | N12: =(L12*M12)*1.18 -> 3390.3076 | O12: =D12 & "|" & I12 & "|" & K12 -> ARS000069|FG006|CK3-33306
A13: S-00022 | B13: L-0019 | C13: 46179 | D13: ARS000069 | E13: =IFERROR(INDEX(M_User!$A$12:$J$67,MATCH(D13,M_User!$D$12:$D$67,0),3),"UNMAPPED") -> Doglas E. Shirima | F13: =IFERROR(INDEX(M_User!$A$12:$J$67,MATCH(D13,M_User!$D$12:$D$67,0),5),"UNMAPPED") -> ARS | G13: OUT-ARS-001 | H13: Sokoine Road Stores | I13: FG009 | J13: =IFERROR(INDEX(M_SKU!$A$18:$J$57,MATCH(I13,M_SKU!$B$18:$B$57,0),1),"UNKNOWN SKU") -> Krest Bitter Lemon RGB 300ml | K13: CK3-33348 | L13: 1.2692724 | M13: {=IFERROR(INDEX(M_DepotPrice!$C$10:$C$52,MATCH(1,(M_DepotPrice!$A$10:$A$52=I13)*(M_DepotPrice!$H$10:$H$52=IFERROR(INDEX(M_Depot!$A$7:$A$24,MATCH(F13,M_Depot!$B$7:$B$24,0)),""))*(M_DepotPrice!$G$10:$G$52="Special"),0)),INDEX(M_DepotPrice!$C$10:$C$52,MATCH(1,(M_DepotPrice!$A$10:$A$52=I13)*(M_DepotPrice!$G$10:$G$52="Default"),0)))} -> 11780 | N13: =(L13*M13)*1.18 -> 17643.394 | O13: =D13 & "|" & I13 & "|" & K13 -> ARS000069|FG009|CK3-33348
A14: S-00026 | B14: L-0019 | C14: 46179 | D14: ARS000069 | E14: =IFERROR(INDEX(M_User!$A$12:$J$67,MATCH(D14,M_User!$D$12:$D$67,0),3),"UNMAPPED") -> Doglas E. Shirima | F14: =IFERROR(INDEX(M_User!$A$12:$J$67,MATCH(D14,M_User!$D$12:$D$67,0),5),"UNMAPPED") -> ARS | G14: OUT-ARS-001 | H14: Sokoine Road Stores | I14: FG010 | J14: =IFERROR(INDEX(M_SKU!$A$18:$J$57,MATCH(I14,M_SKU!$B$18:$B$57,0),1),"UNKNOWN SKU") -> Krest Club Soda RGB 300ml | K14: CK3-33301 | L14: 0.92523012 | M14: {=IFERROR(INDEX(M_DepotPrice!$C$10:$C$52,MATCH(1,(M_DepotPrice!$A$10:$A$52=I14)*(M_DepotPrice!$H$10:$H$52=IFERROR(INDEX(M_Depot!$A$7:$A$24,MATCH(F14,M_Depot!$B$7:$B$24,0)),""))*(M_DepotPrice!$G$10:$G$52="Special"),0)),INDEX(M_DepotPrice!$C$10:$C$52,MATCH(1,(M_DepotPrice!$A$10:$A$52=I14)*(M_DepotPrice!$G$10:$G$52="Default"),0)))} -> 11780 | N14: =(L14*M14)*1.18 -> 12861.069 | O14: =D14 & "|" & I14 & "|" & K14 -> ARS000069|FG010|CK3-33301
A15: S-00029 | B15: L-0019 | C15: 46179 | D15: ARS000069 | E15: =IFERROR(INDEX(M_User!$A$12:$J$67,MATCH(D15,M_User!$D$12:$D$67,0),3),"UNMAPPED") -> Doglas E. Shirima | F15: =IFERROR(INDEX(M_User!$A$12:$J$67,MATCH(D15,M_User!$D$12:$D$67,0),5),"UNMAPPED") -> ARS | G15: OUT-ARS-001 | H15: Sokoine Road Stores | I15: FG011 | J15: =IFERROR(INDEX(M_SKU!$A$18:$J$57,MATCH(I15,M_SKU!$B$18:$B$57,0),1),"UNKNOWN SKU") -> Krest Tonic Water RGB 300ml | K15: CK3-33237 | L15: 0.6615 | M15: {=IFERROR(INDEX(M_DepotPrice!$C$10:$C$52,MATCH(1,(M_DepotPrice!$A$10:$A$52=I15)*(M_DepotPrice!$H$10:$H$52=IFERROR(INDEX(M_Depot!$A$7:$A$24,MATCH(F15,M_Depot!$B$7:$B$24,0)),""))*(M_DepotPrice!$G$10:$G$52="Special"),0)),INDEX(M_DepotPrice!$C$10:$C$52,MATCH(1,(M_DepotPrice!$A$10:$A$52=I15)*(M_DepotPrice!$G$10:$G$52="Default"),0)))} -> 11780 | N15: =(L15*M15)*1.18 -> 9195.1146 | O15: =D15 & "|" & I15 & "|" & K15 -> ARS000069|FG011|CK3-33237
A16: S-00032 | B16: L-0019 | C16: 46179 | D16: ARS000069 | E16: =IFERROR(INDEX(M_User!$A$12:$J$67,MATCH(D16,M_User!$D$12:$D$67,0),3),"UNMAPPED") -> Doglas E. Shirima | F16: =IFERROR(INDEX(M_User!$A$12:$J$67,MATCH(D16,M_User!$D$12:$D$67,0),5),"UNMAPPED") -> ARS | G16: OUT-ARS-001 | H16: Sokoine Road Stores | I16: FG012 | J16: =IFERROR(INDEX(M_SKU!$A$18:$J$57,MATCH(I16,M_SKU!$B$18:$B$57,0),1),"UNKNOWN SKU") -> Krest Ginger Ale RGB 300ml | K16: CK3-33126 | L16: 0.2456 | M16: {=IFERROR(INDEX(M_DepotPrice!$C$10:$C$52,MATCH(1,(M_DepotPrice!$A$10:$A$52=I16)*(M_DepotPrice!$H$10:$H$52=IFERROR(INDEX(M_Depot!$A$7:$A$24,MATCH(F16,M_Depot!$B$7:$B$24,0)),""))*(M_DepotPrice!$G$10:$G$52="Special"),0)),INDEX(M_DepotPrice!$C$10:$C$52,MATCH(1,(M_DepotPrice!$A$10:$A$52=I16)*(M_DepotPrice!$G$10:$G$52="Default"),0)))} -> 11780 | N16: =(L16*M16)*1.18 -> 3413.9382 | O16: =D16 & "|" & I16 & "|" & K16 -> ARS000069|FG012|CK3-33126
A17: S-00035 | B17: L-0019 | C17: 46179 | D17: ARS000069 | E17: =IFERROR(INDEX(M_User!$A$12:$J$67,MATCH(D17,M_User!$D$12:$D$67,0),3),"UNMAPPED") -> Doglas E. Shirima | F17: =IFERROR(INDEX(M_User!$A$12:$J$67,MATCH(D17,M_User!$D$12:$D$67,0),5),"UNMAPPED") -> ARS | G17: OUT-ARS-001 | H17: Sokoine Road Stores | I17: KD001 | J17: =IFERROR(INDEX(M_SKU!$A$18:$J$57,MATCH(I17,M_SKU!$B$18:$B$57,0),1),"UNKNOWN SKU") -> KNMW 500ml | K17: CK4-836 | L17: 65 | M17: {=IFERROR(INDEX(M_DepotPrice!$C$10:$C$52,MATCH(1,(M_DepotPrice!$A$10:$A$52=I17)*(M_DepotPrice!$H$10:$H$52=IFERROR(INDEX(M_Depot!$A$7:$A$24,MATCH(F17,M_Depot!$B$7:$B$24,0)),""))*(M_DepotPrice!$G$10:$G$52="Special"),0)),INDEX(M_DepotPrice!$C$10:$C$52,MATCH(1,(M_DepotPrice!$A$10:$A$52=I17)*(M_DepotPrice!$G$10:$G$52="Default"),0)))} -> 3559 | N17: =(L17*M17)*1.18 -> 272975.3 | O17: =D17 & "|" & I17 & "|" & K17 -> ARS000069|KD001|CK4-836
A18: S-00036 | B18: L-0019 | C18: 46179 | D18: ARS000069 | E18: =IFERROR(INDEX(M_User!$A$12:$J$67,MATCH(D18,M_User!$D$12:$D$67,0),3),"UNMAPPED") -> Doglas E. Shirima | F18: =IFERROR(INDEX(M_User!$A$12:$J$67,MATCH(D18,M_User!$D$12:$D$67,0),5),"UNMAPPED") -> ARS | G18: OUT-ARS-001 | H18: Sokoine Road Stores | I18: KD001 | J18: =IFERROR(INDEX(M_SKU!$A$18:$J$57,MATCH(I18,M_SKU!$B$18:$B$57,0),1),"UNKNOWN SKU") -> KNMW 500ml | K18: CK6-983 | L18: 1 | M18: {=IFERROR(INDEX(M_DepotPrice!$C$10:$C$52,MATCH(1,(M_DepotPrice!$A$10:$A$52=I18)*(M_DepotPrice!$H$10:$H$52=IFERROR(INDEX(M_Depot!$A$7:$A$24,MATCH(F18,M_Depot!$B$7:$B$24,0)),""))*(M_DepotPrice!$G$10:$G$52="Special"),0)),INDEX(M_DepotPrice!$C$10:$C$52,MATCH(1,(M_DepotPrice!$A$10:$A$52=I18)*(M_DepotPrice!$G$10:$G$52="Default"),0)))} -> 3559 | N18: =(L18*M18)*1.18 -> 4199.62 | O18: =D18 & "|" & I18 & "|" & K18 -> ARS000069|KD001|CK6-983
A19: S-00053 | B19: L-0019 | C19: 46179 | D19: ARS000069 | E19: =IFERROR(INDEX(M_User!$A$12:$J$67,MATCH(D19,M_User!$D$12:$D$67,0),3),"UNMAPPED") -> Doglas E. Shirima | F19: =IFERROR(INDEX(M_User!$A$12:$J$67,MATCH(D19,M_User!$D$12:$D$67,0),5),"UNMAPPED") -> ARS | G19: OUT-ARS-001 | H19: Sokoine Road Stores | I19: KD004 | J19: =IFERROR(INDEX(M_SKU!$A$18:$J$57,MATCH(I19,M_SKU!$B$18:$B$57,0),1),"UNKNOWN SKU") -> Kilimanjaro Drinking Water 6000 ML | K19: CK7-895 | L19: 5 | M19: {=IFERROR(INDEX(M_DepotPrice!$C$10:$C$52,MATCH(1,(M_DepotPrice!$A$10:$A$52=I19)*(M_DepotPrice!$H$10:$H$52=IFERROR(INDEX(M_Depot!$A$7:$A$24,MATCH(F19,M_Depot!$B$7:$B$24,0)),""))*(M_DepotPrice!$G$10:$G$52="Special"),0)),INDEX(M_DepotPrice!$C$10:$C$52,MATCH(1,(M_DepotPrice!$A$10:$A$52=I19)*(M_DepotPrice!$G$10:$G$52="Default"),0)))} -> 2119 | N19: =(L19*M19)*1.18 -> 12502.1 | O19: =D19 & "|" & I19 & "|" & K19 -> ARS000069|KD004|CK7-895
A20: S-00058 | B20: L-0019 | C20: 46179 | D20: ARS000069 | E20: =IFERROR(INDEX(M_User!$A$12:$J$67,MATCH(D20,M_User!$D$12:$D$67,0),3),"UNMAPPED") -> Doglas E. Shirima | F20: =IFERROR(INDEX(M_User!$A$12:$J$67,MATCH(D20,M_User!$D$12:$D$67,0),5),"UNMAPPED") -> ARS | G20: OUT-ARS-001 | H20: Sokoine Road Stores | I20: KD005 | J20: =IFERROR(INDEX(M_SKU!$A$18:$J$57,MATCH(I20,M_SKU!$B$18:$B$57,0),1),"UNKNOWN SKU") -> Kilimanjaro Drinking Water 12000 ML | K20: CK7-909 | L20: 1 | M20: {=IFERROR(INDEX(M_DepotPrice!$C$10:$C$52,MATCH(1,(M_DepotPrice!$A$10:$A$52=I20)*(M_DepotPrice!$H$10:$H$52=IFERROR(INDEX(M_Depot!$A$7:$A$24,MATCH(F20,M_Depot!$B$7:$B$24,0)),""))*(M_DepotPrice!$G$10:$G$52="Special"),0)),INDEX(M_DepotPrice!$C$10:$C$52,MATCH(1,(M_DepotPrice!$A$10:$A$52=I20)*(M_DepotPrice!$G$10:$G$52="Default"),0)))} -> 3559 | N20: =(L20*M20)*1.18 -> 4199.62 | O20: =D20 & "|" & I20 & "|" & K20 -> ARS000069|KD005|CK7-909
A21: S-00063 | B21: L-0019 | C21: 46179 | D21: ARS000069 | E21: =IFERROR(INDEX(M_User!$A$12:$J$67,MATCH(D21,M_User!$D$12:$D$67,0),3),"UNMAPPED") -> Doglas E. Shirima | F21: =IFERROR(INDEX(M_User!$A$12:$J$67,MATCH(D21,M_User!$D$12:$D$67,0),5),"UNMAPPED") -> ARS | G21: OUT-ARS-001 | H21: Sokoine Road Stores | I21: KD006 | J21: =IFERROR(INDEX(M_SKU!$A$18:$J$57,MATCH(I21,M_SKU!$B$18:$B$57,0),1),"UNKNOWN SKU") -> Kilimanjaro Drinking Water 18900 ML | K21: CK7-914 | L21: 1 | M21: {=IFERROR(INDEX(M_DepotPrice!$C$10:$C$52,MATCH(1,(M_DepotPrice!$A$10:$A$52=I21)*(M_DepotPrice!$H$10:$H$52=IFERROR(INDEX(M_Depot!$A$7:$A$24,MATCH(F21,M_Depot!$B$7:$B$24,0)),""))*(M_DepotPrice!$G$10:$G$52="Special"),0)),INDEX(M_DepotPrice!$C$10:$C$52,MATCH(1,(M_DepotPrice!$A$10:$A$52=I21)*(M_DepotPrice!$G$10:$G$52="Default"),0)))} -> 5932 | N21: =(L21*M21)*1.18 -> 6999.76 | O21: =D21 & "|" & I21 & "|" & K21 -> ARS000069|KD006|CK7-914
... A1164: S-00092 | B1164: L-0020 | C1164: 46183 | D1164: DSM300140 | E1164: =IFERROR(INDEX(M_User!$A$12:$J$67,MATCH(D1164,M_User!$D$12:$D$67,0),3),"UNMAPPED") -> Omary O. Seif | F1164: =IFERROR(INDEX(M_User!$A$12:$J$67,MATCH(D1164,M_User!$D$12:$D$67,0),5),"UNMAPPED") -> DAR | G1164: OUT-DAR-007 | H1164: Mwananyamala Beverages | I1164: KD003 | J1164: =IFERROR(INDEX(M_SKU!$A$18:$J$57,MATCH(I1164,M_SKU!$B$18:$B$57,0),1),"UNKNOWN SKU") -> KNMW 1500ml | K1164: CK4-823 | L1164: 19 | M1164: {=IFERROR(INDEX(M_DepotPrice!$C$10:$C$52,MATCH(1,(M_DepotPrice!$A$10:$A$52=I1164)*(M_DepotPrice!$H$10:$H$52=IFERROR(INDEX(M_Depot!$A$7:$A$24,MATCH(F1164,M_Depot!$B$7:$B$24,0)),""))*(M_DepotPrice!$G$10:$G$52="Special"),0)),INDEX(M_DepotPrice!$C$10:$C$52,MATCH(1,(M_DepotPrice!$A$10:$A$52=I1164)*(M_DepotPrice!$G$10:$G$52="Default"),0)))} -> 3559 | N1164: =(L1164*M1164)*1.18 -> 79792.78 | O1164: =D1164 & "|" & I1164 & "|" & K1164 -> DSM300140|KD003|CK4-823
A1167: SUMMARY
A1168: Total Sale Rows: | B1168: =COUNTA(A9:A1164) -> 1156
A1169: Unique Salesmen: | B1169: =SUMPRODUCT(1/COUNTIF(D9:D1164,D9:D1164)) -> 17
A1170: Unique Outlets Visited: | B1170: =SUMPRODUCT(1/COUNTIF(G9:G1164,G9:G1164)) -> 20
A1171: Total Quantity Sold: | B1171: =SUM(L9:L1164) -> 6616.9405
A1172: Total Sale Value (TZS): | B1172: =SUM(N9:N1164) -> 55971817
A1174: Scenario Distribution (designed):
A1175: Clean matches: | B1175: 13 salesmen
A1176: Shortage (Default Outlet posting): | B1176: 1 salesman — Riziki Rajabu (MOS100645)
A1177: Excess (Unload adjustment): | B1177: 1 salesman — Joyline J Lyimo (MOS100802)
A1178: Safari sales (multi-day): | B1178: 1 salesman — Omary O. Seif (DSM300140)
A1179: Sub-unit / decimal sales: | B1179: 1 salesman — Doglas E. Shirima (ARS000069)
A1180: No sales (Force-Push pending): | B1180: James Tegemea Ndosi (MOS100801)

Sheet T_Unload
A1: T_Unload — Mobile Unload (Auto-Derived)
A2: Auto-derived from T_Load and T_Sales. Each row = one unique Stock Key (Salesman + SKU + Batch).
A3: Expected ROP = Sum of Load Qty − Sum of Sales Qty (per Stock Key). This is what the system EXPECTS to be in the van.
A4: In the live system: salesman clicks "Unload" on his mobile; quantities flow automatically. He cannot manipulate these numbers.
A5: Next step (T_ROP): Clerk enters Actual ROP at the depot. Variance = Expected ROP − Actual ROP.
A7: Column Groups: | B7: Identification | D7: Resolved by SFA | F7: Computed | H7: State | J7: Derived Key
A9: Unload ID | B9: Stock Key | C9: Salesman SAP Code | D9: Salesman Name | E9: Depot | F9: SKU Code | G9: SKU Name | H9: Batch Number | I9: Load Qty (Sum) | J9: Sales Qty (Sum) | K9: Expected ROP | L9: Unload Date | M9: Unload Status
A10: U-0001 | B10: ARS000069|FG001|CK3-33379 | C10: ARS000069 | D10: =IFERROR(INDEX(M_User!$A$12:$J$67,MATCH(C10,M_User!$D$12:$D$67,0),3),"UNMAPPED") -> Doglas E. Shirima | E10: =IFERROR(INDEX(M_User!$A$12:$J$67,MATCH(C10,M_User!$D$12:$D$67,0),5),"UNMAPPED") -> ARS | F10: FG001 | G10: =IFERROR(INDEX(M_SKU!$A$18:$J$57,MATCH(F10,M_SKU!$B$18:$B$57,0),1),"UNKNOWN SKU") -> Coke RGB 350ml | H10: CK3-33379 | I10: =SUMIF(T_Load!$U$9:$U$439,B10,T_Load!$O$9:$O$439) -> 15 | J10: =SUMIF(T_Sales!$O$9:$O$1164,B10,T_Sales!$L$9:$L$1164) -> 12.43255 | K10: =I10-J10 -> 2.5674504 | L10: 46179 | M10: Pending Unload
A11: U-0002 | B11: ARS000069|FG002|CK3-33372 | C11: ARS000069 | D11: =IFERROR(INDEX(M_User!$A$12:$J$67,MATCH(C11,M_User!$D$12:$D$67,0),3),"UNMAPPED") -> Doglas E. Shirima | E11: =IFERROR(INDEX(M_User!$A$12:$J$67,MATCH(C11,M_User!$D$12:$D$67,0),5),"UNMAPPED") -> ARS | F11: FG002 | G11: =IFERROR(INDEX(M_SKU!$A$18:$J$57,MATCH(F11,M_SKU!$B$18:$B$57,0),1),"UNKNOWN SKU") -> Fanta Orange RGB 350ml | H11: CK3-33372 | I11: =SUMIF(T_Load!$U$9:$U$439,B11,T_Load!$O$9:$O$439) -> 5 | J11: =SUMIF(T_Sales!$O$9:$O$1164,B11,T_Sales!$L$9:$L$1164) -> 3.9835374 | K11: =I11-J11 -> 1.0164626 | L11: 46179 | M11: Pending Unload
A12: U-0003 | B12: ARS000069|FG003|CK3-33290 | C12: ARS000069 | D12: =IFERROR(INDEX(M_User!$A$12:$J$67,MATCH(C12,M_User!$D$12:$D$67,0),3),"UNMAPPED") -> Doglas E. Shirima | E12: =IFERROR(INDEX(M_User!$A$12:$J$67,MATCH(C12,M_User!$D$12:$D$67,0),5),"UNMAPPED") -> ARS | F12: FG003 | G12: =IFERROR(INDEX(M_SKU!$A$18:$J$57,MATCH(F12,M_SKU!$B$18:$B$57,0),1),"UNKNOWN SKU") -> Fanta Passion RGB 350ml | H12: CK3-33290 | I12: =SUMIF(T_Load!$U$9:$U$439,B12,T_Load!$O$9:$O$439) -> 2 | J12: =SUMIF(T_Sales!$O$9:$O$1164,B12,T_Sales!$L$9:$L$1164) -> 1.5189308 | K12: =I12-J12 -> 0.48106918 | L12: 46179 | M12: Pending Unload
A13: U-0004 | B13: ARS000069|FG004|CK5-33354 | C13: ARS000069 | D13: =IFERROR(INDEX(M_User!$A$12:$J$67,MATCH(C13,M_User!$D$12:$D$67,0),3),"UNMAPPED") -> Doglas E. Shirima | E13: =IFERROR(INDEX(M_User!$A$12:$J$67,MATCH(C13,M_User!$D$12:$D$67,0),5),"UNMAPPED") -> ARS | F13: FG004 | G13: =IFERROR(INDEX(M_SKU!$A$18:$J$57,MATCH(F13,M_SKU!$B$18:$B$57,0),1),"UNKNOWN SKU") -> Fanta Pineapple RGB 350ml | H13: CK5-33354 | I13: =SUMIF(T_Load!$U$9:$U$439,B13,T_Load!$O$9:$O$439) -> 2 | J13: =SUMIF(T_Sales!$O$9:$O$1164,B13,T_Sales!$L$9:$L$1164) -> 1.4224357 | K13: =I13-J13 -> 0.57756435 | L13: 46179 | M13: Pending Unload
A14: U-0005 | B14: ARS000069|FG006|CK3-33306 | C14: ARS000069 | D14: =IFERROR(INDEX(M_User!$A$12:$J$67,MATCH(C14,M_User!$D$12:$D$67,0),3),"UNMAPPED") -> Doglas E. Shirima | E14: =IFERROR(INDEX(M_User!$A$12:$J$67,MATCH(C14,M_User!$D$12:$D$67,0),5),"UNMAPPED") -> ARS | F14: FG006 | G14: =IFERROR(INDEX(M_SKU!$A$18:$J$57,MATCH(F14,M_SKU!$B$18:$B$57,0),1),"UNKNOWN SKU") -> Sprite 350ml | H14: CK3-33306 | I14: =SUMIF(T_Load!$U$9:$U$439,B14,T_Load!$O$9:$O$439) -> 2 | J14: =SUMIF(T_Sales!$O$9:$O$1164,B14,T_Sales!$L$9:$L$1164) -> 1.5417 | K14: =I14-J14 -> 0.4583 | L14: 46179 | M14: Pending Unload
A15: U-0006 | B15: ARS000069|FG009|CK3-33348 | C15: ARS000069 | D15: =IFERROR(INDEX(M_User!$A$12:$J$67,MATCH(C15,M_User!$D$12:$D$67,0),3),"UNMAPPED") -> Doglas E. Shirima | E15: =IFERROR(INDEX(M_User!$A$12:$J$67,MATCH(C15,M_User!$D$12:$D$67,0),5),"UNMAPPED") -> ARS | F15: FG009 | G15: =IFERROR(INDEX(M_SKU!$A$18:$J$57,MATCH(F15,M_SKU!$B$18:$B$57,0),1),"UNKNOWN SKU") -> Krest Bitter Lemon RGB 300ml | H15: CK3-33348 | I15: =SUMIF(T_Load!$U$9:$U$439,B15,T_Load!$O$9:$O$439) -> 3 | J15: =SUMIF(T_Sales!$O$9:$O$1164,B15,T_Sales!$L$9:$L$1164) -> 2.4120724 | K15: =I15-J15 -> 0.58792761 | L15: 46179 | M15: Pending Unload
A16: U-0007 | B16: ARS000069|FG010|CK3-33301 | C16: ARS000069 | D16: =IFERROR(INDEX(M_User!$A$12:$J$67,MATCH(C16,M_User!$D$12:$D$67,0),3),"UNMAPPED") -> Doglas E. Shirima | E16: =IFERROR(INDEX(M_User!$A$12:$J$67,MATCH(C16,M_User!$D$12:$D$67,0),5),"UNMAPPED") -> ARS | F16: FG010 | G16: =IFERROR(INDEX(M_SKU!$A$18:$J$57,MATCH(F16,M_SKU!$B$18:$B$57,0),1),"UNKNOWN SKU") -> Krest Club Soda RGB 300ml | H16: CK3-33301 | I16: =SUMIF(T_Load!$U$9:$U$439,B16,T_Load!$O$9:$O$439) -> 3 | J16: =SUMIF(T_Sales!$O$9:$O$1164,B16,T_Sales!$L$9:$L$1164) -> 2.2570301 | K16: =I16-J16 -> 0.74296988 | L16: 46179 | M16: Pending Unload
A17: U-0008 | B17: ARS000069|FG011|CK3-33237 | C17: ARS000069 | D17: =IFERROR(INDEX(M_User!$A$12:$J$67,MATCH(C17,M_User!$D$12:$D$67,0),3),"UNMAPPED") -> Doglas E. Shirima | E17: =IFERROR(INDEX(M_User!$A$12:$J$67,MATCH(C17,M_User!$D$12:$D$67,0),5),"UNMAPPED") -> ARS | F17: FG011 | G17: =IFERROR(INDEX(M_SKU!$A$18:$J$57,MATCH(F17,M_SKU!$B$18:$B$57,0),1),"UNKNOWN SKU") -> Krest Tonic Water RGB 300ml | H17: CK3-33237 | I17: =SUMIF(T_Load!$U$9:$U$439,B17,T_Load!$O$9:$O$439) -> 3 | J17: =SUMIF(T_Sales!$O$9:$O$1164,B17,T_Sales!$L$9:$L$1164) -> 2.3133117 | K17: =I17-J17 -> 0.68668833 | L17: 46179 | M17: Pending Unload
A18: U-0009 | B18: ARS000069|FG012|CK3-33126 | C18: ARS000069 | D18: =IFERROR(INDEX(M_User!$A$12:$J$67,MATCH(C18,M_User!$D$12:$D$67,0),3),"UNMAPPED") -> Doglas E. Shirima | E18: =IFERROR(INDEX(M_User!$A$12:$J$67,MATCH(C18,M_User!$D$12:$D$67,0),5),"UNMAPPED") -> ARS | F18: FG012 | G18: =IFERROR(INDEX(M_SKU!$A$18:$J$57,MATCH(F18,M_SKU!$B$18:$B$57,0),1),"UNKNOWN SKU") -> Krest Ginger Ale RGB 300ml | H18: CK3-33126 | I18: =SUMIF(T_Load!$U$9:$U$439,B18,T_Load!$O$9:$O$439) -> 1 | J18: =SUMIF(T_Sales!$O$9:$O$1164,B18,T_Sales!$L$9:$L$1164) -> 0.75 | K18: =I18-J18 -> 0.25 | L18: 46179 | M18: Pending Unload
A19: U-0010 | B19: ARS000069|KD001|CK4-836 | C19: ARS000069 | D19: =IFERROR(INDEX(M_User!$A$12:$J$67,MATCH(C19,M_User!$D$12:$D$67,0),3),"UNMAPPED") -> Doglas E. Shirima | E19: =IFERROR(INDEX(M_User!$A$12:$J$67,MATCH(C19,M_User!$D$12:$D$67,0),5),"UNMAPPED") -> ARS | F19: KD001 | G19: =IFERROR(INDEX(M_SKU!$A$18:$J$57,MATCH(F19,M_SKU!$B$18:$B$57,0),1),"UNKNOWN SKU") -> KNMW 500ml | H19: CK4-836 | I19: =SUMIF(T_Load!$U$9:$U$439,B19,T_Load!$O$9:$O$439) -> 200 | J19: =SUMIF(T_Sales!$O$9:$O$1164,B19,T_Sales!$L$9:$L$1164) -> 154 | K19: =I19-J19 -> 46 | L19: 46179 | M19: Pending Unload
A20: U-0011 | B20: ARS000069|KD001|CK6-978 | C20: ARS000069 | D20: =IFERROR(INDEX(M_User!$A$12:$J$67,MATCH(C20,M_User!$D$12:$D$67,0),3),"UNMAPPED") -> Doglas E. Shirima | E20: =IFERROR(INDEX(M_User!$A$12:$J$67,MATCH(C20,M_User!$D$12:$D$67,0),5),"UNMAPPED") -> ARS | F20: KD001 | G20: =IFERROR(INDEX(M_SKU!$A$18:$J$57,MATCH(F20,M_SKU!$B$18:$B$57,0),1),"UNKNOWN SKU") -> KNMW 500ml | H20: CK6-978 | I20: =SUMIF(T_Load!$U$9:$U$439,B20,T_Load!$O$9:$O$439) -> 139 | J20: =SUMIF(T_Sales!$O$9:$O$1164,B20,T_Sales!$L$9:$L$1164) -> 100 | K20: =I20-J20 -> 39 | L20: 46179 | M20: Pending Unload
A21: U-0012 | B21: ARS000069|KD001|CK6-983 | C21: ARS000069 | D21: =IFERROR(INDEX(M_User!$A$12:$J$67,MATCH(C21,M_User!$D$12:$D$67,0),3),"UNMAPPED") -> Doglas E. Shirima | E21: =IFERROR(INDEX(M_User!$A$12:$J$67,MATCH(C21,M_User!$D$12:$D$67,0),5),"UNMAPPED") -> ARS | F21: KD001 | G21: =IFERROR(INDEX(M_SKU!$A$18:$J$57,MATCH(F21,M_SKU!$B$18:$B$57,0),1),"UNKNOWN SKU") -> KNMW 500ml | H21: CK6-983 | I21: =SUMIF(T_Load!$U$9:$U$439,B21,T_Load!$O$9:$O$439) -> 1 | J21: =SUMIF(T_Sales!$O$9:$O$1164,B21,T_Sales!$L$9:$L$1164) -> 1 | K21: =I21-J21 -> 0 | L21: 46179 | M21: Pending Unload
... A433: U-0424 | B433: MOS100842|PO015|CK5-33366 | C433: MOS100842 | D433: =IFERROR(INDEX(M_User!$A$12:$J$67,MATCH(C433,M_User!$D$12:$D$67,0),3),"UNMAPPED") -> Samson Felix Ngowi | E433: =IFERROR(INDEX(M_User!$A$12:$J$67,MATCH(C433,M_User!$D$12:$D$67,0),5),"UNMAPPED") -> MOS | F433: PO015 | G433: =IFERROR(INDEX(M_SKU!$A$18:$J$57,MATCH(F433,M_SKU!$B$18:$B$57,0),1),"UNKNOWN SKU") -> Sparletta Pine Apple Pet 300ML (x 12) | H433: CK5-33366 | I433: =SUMIF(T_Load!$U$9:$U$439,B433,T_Load!$O$9:$O$439) -> 5 | J433: =SUMIF(T_Sales!$O$9:$O$1164,B433,T_Sales!$L$9:$L$1164) -> 4 | K433: =I433-J433 -> 1 | L433: 46179 | M433: Pending Unload
A436: SUMMARY
A437: Total Unload Rows: | E437: =COUNTA(A10:A433) -> 424
A438: Unique Salesmen: | E438: =SUMPRODUCT(1/COUNTIF(C10:C433,C10:C433)) -> 18
A439: Total Load Qty: | E439: =SUM(I10:I433) -> 8286
A440: Total Sales Qty: | E440: =SUM(J10:J433) -> 6616.9405
A441: Total Expected ROP: | E441: =SUM(K10:K433) -> 1669.0595
A443: Status Breakdown:
A444: Pending Unload: | E444: =COUNTIF(M10:M433,"Pending Unload") -> 400
A445: Blocked (Force-Push): | E445: =COUNTIF(M10:M433,"Blocked (Force-Push)") -> 24
A447: Scenario Verification:
A448: Joyline (MOS100802) Expected ROP — should be NEGATIVE (excess scenario): | E448: =SUMIFS(K10:K433,C10:C433,"MOS100802") -> -1.170759
A449: Riziki (MOS100645) Expected ROP — should be HIGH (shortage scenario, low sales): | E449: =SUMIFS(K10:K433,C10:C433,"MOS100645") -> 187.50225
A450: James (MOS100801) Expected ROP — should equal Load Qty (no sales): | E450: =SUMIFS(K10:K433,C10:C433,"MOS100801") -> 320

Sheet T_ROP
A1: T_ROP — Integration Page (ROP Verification)
A2: The heart of the SAP Integration & Compliance module. Clerk verifies physical stock against system Expected ROP.
A3: The ONLY manual input in this entire flow is the "Actual ROP" column (highlighted pale yellow). Everything else is automatic.
A4: Variance Logic (auto):
A5: • Variance = Expected ROP − Actual ROP
A6: • Variance = 0 → CLEAN (no further action)
A7: • Variance > 0 → SHORTAGE → POST TO DEFAULT OUTLET at depot price (creates new sale record)
A8: • Variance < 0 → EXCESS → ADJUST UNLOAD UPWARD (NO new sales; sales are immutable)
A10: Column Groups: | B10: Identification | D10: Resolved by SFA | F10: Expected (Auto) | H10: CLERK INPUT | J10: Computed | L10: Resolution | N10: State
A12: ROP ID | B12: Stock Key | C12: Salesman SAP Code | D12: Salesman Name | E12: Depot | F12: SKU Code | G12: SKU Name | H12: Batch Number | I12: Expected ROP | J12: Actual ROP (Clerk) | K12: Variance | L12: Resolution Action | M12: Default Outlet Posting Qty | N12: Unload Adjustment Qty | O12: Status | P12: Verified By | Q12: Verified On
A13: ROP-0001 | B13: ARS000069|FG001|CK3-33379 | C13: ARS000069 | D13: =IFERROR(INDEX(M_User!$A$12:$J$67,MATCH(C13,M_User!$D$12:$D$67,0),3),"UNMAPPED") -> Doglas E. Shirima | E13: =IFERROR(INDEX(M_User!$A$12:$J$67,MATCH(C13,M_User!$D$12:$D$67,0),5),"UNMAPPED") -> ARS | F13: FG001 | G13: =IFERROR(INDEX(M_SKU!$A$18:$J$57,MATCH(F13,M_SKU!$B$18:$B$57,0),1),"UNKNOWN SKU") -> Coke RGB 350ml | H13: CK3-33379 | I13: =IFERROR(INDEX(T_Unload!$K$10:$K$433,MATCH(B13,T_Unload!$B$10:$B$433,0)),0) -> 2.5674504 | J13: 2.5675 | K13: =IF(ISBLANK(J13),"",I13-J13) -> -4.9617914e-05 | L13: =IF(K13="","Awaiting Verification",IF(ABS(K13)<0.0001,"CLEAN",IF(K13>0,"Post to Default Outlet","Adjust Unload Upward"))) -> CLEAN | M13: =IF(AND(ISNUMBER(K13),K13>0.0001),K13,0) -> 0 | N13: =IF(AND(ISNUMBER(K13),K13<-0.0001),-K13,0) -> 0 | O13: Pending Verification
A14: ROP-0002 | B14: ARS000069|FG002|CK3-33372 | C14: ARS000069 | D14: =IFERROR(INDEX(M_User!$A$12:$J$67,MATCH(C14,M_User!$D$12:$D$67,0),3),"UNMAPPED") -> Doglas E. Shirima | E14: =IFERROR(INDEX(M_User!$A$12:$J$67,MATCH(C14,M_User!$D$12:$D$67,0),5),"UNMAPPED") -> ARS | F14: FG002 | G14: =IFERROR(INDEX(M_SKU!$A$18:$J$57,MATCH(F14,M_SKU!$B$18:$B$57,0),1),"UNKNOWN SKU") -> Fanta Orange RGB 350ml | H14: CK3-33372 | I14: =IFERROR(INDEX(T_Unload!$K$10:$K$433,MATCH(B14,T_Unload!$B$10:$B$433,0)),0) -> 1.0164626 | J14: 1.0165 | K14: =IF(ISBLANK(J14),"",I14-J14) -> -3.7429372e-05 | L14: =IF(K14="","Awaiting Verification",IF(ABS(K14)<0.0001,"CLEAN",IF(K14>0,"Post to Default Outlet","Adjust Unload Upward"))) -> CLEAN | M14: =IF(AND(ISNUMBER(K14),K14>0.0001),K14,0) -> 0 | N14: =IF(AND(ISNUMBER(K14),K14<-0.0001),-K14,0) -> 0 | O14: Pending Verification
A15: ROP-0003 | B15: ARS000069|FG003|CK3-33290 | C15: ARS000069 | D15: =IFERROR(INDEX(M_User!$A$12:$J$67,MATCH(C15,M_User!$D$12:$D$67,0),3),"UNMAPPED") -> Doglas E. Shirima | E15: =IFERROR(INDEX(M_User!$A$12:$J$67,MATCH(C15,M_User!$D$12:$D$67,0),5),"UNMAPPED") -> ARS | F15: FG003 | G15: =IFERROR(INDEX(M_SKU!$A$18:$J$57,MATCH(F15,M_SKU!$B$18:$B$57,0),1),"UNKNOWN SKU") -> Fanta Passion RGB 350ml | H15: CK3-33290 | I15: =IFERROR(INDEX(T_Unload!$K$10:$K$433,MATCH(B15,T_Unload!$B$10:$B$433,0)),0) -> 0.48106918 | J15: 0.4811 | K15: =IF(ISBLANK(J15),"",I15-J15) -> -3.0819353e-05 | L15: =IF(K15="","Awaiting Verification",IF(ABS(K15)<0.0001,"CLEAN",IF(K15>0,"Post to Default Outlet","Adjust Unload Upward"))) -> CLEAN | M15: =IF(AND(ISNUMBER(K15),K15>0.0001),K15,0) -> 0 | N15: =IF(AND(ISNUMBER(K15),K15<-0.0001),-K15,0) -> 0 | O15: Pending Verification
A16: ROP-0004 | B16: ARS000069|FG004|CK5-33354 | C16: ARS000069 | D16: =IFERROR(INDEX(M_User!$A$12:$J$67,MATCH(C16,M_User!$D$12:$D$67,0),3),"UNMAPPED") -> Doglas E. Shirima | E16: =IFERROR(INDEX(M_User!$A$12:$J$67,MATCH(C16,M_User!$D$12:$D$67,0),5),"UNMAPPED") -> ARS | F16: FG004 | G16: =IFERROR(INDEX(M_SKU!$A$18:$J$57,MATCH(F16,M_SKU!$B$18:$B$57,0),1),"UNKNOWN SKU") -> Fanta Pineapple RGB 350ml | H16: CK5-33354 | I16: =IFERROR(INDEX(T_Unload!$K$10:$K$433,MATCH(B16,T_Unload!$B$10:$B$433,0)),0) -> 0.57756435 | J16: 0.5776 | K16: =IF(ISBLANK(J16),"",I16-J16) -> -3.5650565e-05 | L16: =IF(K16="","Awaiting Verification",IF(ABS(K16)<0.0001,"CLEAN",IF(K16>0,"Post to Default Outlet","Adjust Unload Upward"))) -> CLEAN | M16: =IF(AND(ISNUMBER(K16),K16>0.0001),K16,0) -> 0 | N16: =IF(AND(ISNUMBER(K16),K16<-0.0001),-K16,0) -> 0 | O16: Pending Verification
A17: ROP-0005 | B17: ARS000069|FG006|CK3-33306 | C17: ARS000069 | D17: =IFERROR(INDEX(M_User!$A$12:$J$67,MATCH(C17,M_User!$D$12:$D$67,0),3),"UNMAPPED") -> Doglas E. Shirima | E17: =IFERROR(INDEX(M_User!$A$12:$J$67,MATCH(C17,M_User!$D$12:$D$67,0),5),"UNMAPPED") -> ARS | F17: FG006 | G17: =IFERROR(INDEX(M_SKU!$A$18:$J$57,MATCH(F17,M_SKU!$B$18:$B$57,0),1),"UNKNOWN SKU") -> Sprite 350ml | H17: CK3-33306 | I17: =IFERROR(INDEX(T_Unload!$K$10:$K$433,MATCH(B17,T_Unload!$B$10:$B$433,0)),0) -> 0.4583 | J17: 0.4583 | K17: =IF(ISBLANK(J17),"",I17-J17) -> -5.5511151e-17 | L17: =IF(K17="","Awaiting Verification",IF(ABS(K17)<0.0001,"CLEAN",IF(K17>0,"Post to Default Outlet","Adjust Unload Upward"))) -> CLEAN | M17: =IF(AND(ISNUMBER(K17),K17>0.0001),K17,0) -> 0 | N17: =IF(AND(ISNUMBER(K17),K17<-0.0001),-K17,0) -> 0 | O17: Pending Verification
A18: ROP-0006 | B18: ARS000069|FG009|CK3-33348 | C18: ARS000069 | D18: =IFERROR(INDEX(M_User!$A$12:$J$67,MATCH(C18,M_User!$D$12:$D$67,0),3),"UNMAPPED") -> Doglas E. Shirima | E18: =IFERROR(INDEX(M_User!$A$12:$J$67,MATCH(C18,M_User!$D$12:$D$67,0),5),"UNMAPPED") -> ARS | F18: FG009 | G18: =IFERROR(INDEX(M_SKU!$A$18:$J$57,MATCH(F18,M_SKU!$B$18:$B$57,0),1),"UNKNOWN SKU") -> Krest Bitter Lemon RGB 300ml | H18: CK3-33348 | I18: =IFERROR(INDEX(T_Unload!$K$10:$K$433,MATCH(B18,T_Unload!$B$10:$B$433,0)),0) -> 0.58792761 | J18: 0.5879 | K18: =IF(ISBLANK(J18),"",I18-J18) -> 2.7611692e-05 | L18: =IF(K18="","Awaiting Verification",IF(ABS(K18)<0.0001,"CLEAN",IF(K18>0,"Post to Default Outlet","Adjust Unload Upward"))) -> CLEAN | M18: =IF(AND(ISNUMBER(K18),K18>0.0001),K18,0) -> 0 | N18: =IF(AND(ISNUMBER(K18),K18<-0.0001),-K18,0) -> 0 | O18: Pending Verification
A19: ROP-0007 | B19: ARS000069|FG010|CK3-33301 | C19: ARS000069 | D19: =IFERROR(INDEX(M_User!$A$12:$J$67,MATCH(C19,M_User!$D$12:$D$67,0),3),"UNMAPPED") -> Doglas E. Shirima | E19: =IFERROR(INDEX(M_User!$A$12:$J$67,MATCH(C19,M_User!$D$12:$D$67,0),5),"UNMAPPED") -> ARS | F19: FG010 | G19: =IFERROR(INDEX(M_SKU!$A$18:$J$57,MATCH(F19,M_SKU!$B$18:$B$57,0),1),"UNKNOWN SKU") -> Krest Club Soda RGB 300ml | H19: CK3-33301 | I19: =IFERROR(INDEX(T_Unload!$K$10:$K$433,MATCH(B19,T_Unload!$B$10:$B$433,0)),0) -> 0.74296988 | J19: 0.743 | K19: =IF(ISBLANK(J19),"",I19-J19) -> -3.0122311e-05 | L19: =IF(K19="","Awaiting Verification",IF(ABS(K19)<0.0001,"CLEAN",IF(K19>0,"Post to Default Outlet","Adjust Unload Upward"))) -> CLEAN | M19: =IF(AND(ISNUMBER(K19),K19>0.0001),K19,0) -> 0 | N19: =IF(AND(ISNUMBER(K19),K19<-0.0001),-K19,0) -> 0 | O19: Pending Verification
A20: ROP-0008 | B20: ARS000069|FG011|CK3-33237 | C20: ARS000069 | D20: =IFERROR(INDEX(M_User!$A$12:$J$67,MATCH(C20,M_User!$D$12:$D$67,0),3),"UNMAPPED") -> Doglas E. Shirima | E20: =IFERROR(INDEX(M_User!$A$12:$J$67,MATCH(C20,M_User!$D$12:$D$67,0),5),"UNMAPPED") -> ARS | F20: FG011 | G20: =IFERROR(INDEX(M_SKU!$A$18:$J$57,MATCH(F20,M_SKU!$B$18:$B$57,0),1),"UNKNOWN SKU") -> Krest Tonic Water RGB 300ml | H20: CK3-33237 | I20: =IFERROR(INDEX(T_Unload!$K$10:$K$433,MATCH(B20,T_Unload!$B$10:$B$433,0)),0) -> 0.68668833 | J20: 0.6867 | K20: =IF(ISBLANK(J20),"",I20-J20) -> -1.1674483e-05 | L20: =IF(K20="","Awaiting Verification",IF(ABS(K20)<0.0001,"CLEAN",IF(K20>0,"Post to Default Outlet","Adjust Unload Upward"))) -> CLEAN | M20: =IF(AND(ISNUMBER(K20),K20>0.0001),K20,0) -> 0 | N20: =IF(AND(ISNUMBER(K20),K20<-0.0001),-K20,0) -> 0 | O20: Pending Verification
A21: ROP-0009 | B21: ARS000069|FG012|CK3-33126 | C21: ARS000069 | D21: =IFERROR(INDEX(M_User!$A$12:$J$67,MATCH(C21,M_User!$D$12:$D$67,0),3),"UNMAPPED") -> Doglas E. Shirima | E21: =IFERROR(INDEX(M_User!$A$12:$J$67,MATCH(C21,M_User!$D$12:$D$67,0),5),"UNMAPPED") -> ARS | F21: FG012 | G21: =IFERROR(INDEX(M_SKU!$A$18:$J$57,MATCH(F21,M_SKU!$B$18:$B$57,0),1),"UNKNOWN SKU") -> Krest Ginger Ale RGB 300ml | H21: CK3-33126 | I21: =IFERROR(INDEX(T_Unload!$K$10:$K$433,MATCH(B21,T_Unload!$B$10:$B$433,0)),0) -> 0.25 | J21: 0.25 | K21: =IF(ISBLANK(J21),"",I21-J21) -> 0 | L21: =IF(K21="","Awaiting Verification",IF(ABS(K21)<0.0001,"CLEAN",IF(K21>0,"Post to Default Outlet","Adjust Unload Upward"))) -> CLEAN | M21: =IF(AND(ISNUMBER(K21),K21>0.0001),K21,0) -> 0 | N21: =IF(AND(ISNUMBER(K21),K21<-0.0001),-K21,0) -> 0 | O21: Pending Verification
A22: ROP-0010 | B22: ARS000069|KD001|CK4-836 | C22: ARS000069 | D22: =IFERROR(INDEX(M_User!$A$12:$J$67,MATCH(C22,M_User!$D$12:$D$67,0),3),"UNMAPPED") -> Doglas E. Shirima | E22: =IFERROR(INDEX(M_User!$A$12:$J$67,MATCH(C22,M_User!$D$12:$D$67,0),5),"UNMAPPED") -> ARS | F22: KD001 | G22: =IFERROR(INDEX(M_SKU!$A$18:$J$57,MATCH(F22,M_SKU!$B$18:$B$57,0),1),"UNKNOWN SKU") -> KNMW 500ml | H22: CK4-836 | I22: =IFERROR(INDEX(T_Unload!$K$10:$K$433,MATCH(B22,T_Unload!$B$10:$B$433,0)),0) -> 46 | J22: 46 | K22: =IF(ISBLANK(J22),"",I22-J22) -> 0 | L22: =IF(K22="","Awaiting Verification",IF(ABS(K22)<0.0001,"CLEAN",IF(K22>0,"Post to Default Outlet","Adjust Unload Upward"))) -> CLEAN | M22: =IF(AND(ISNUMBER(K22),K22>0.0001),K22,0) -> 0 | N22: =IF(AND(ISNUMBER(K22),K22<-0.0001),-K22,0) -> 0 | O22: Pending Verification
A23: ROP-0011 | B23: ARS000069|KD001|CK6-978 | C23: ARS000069 | D23: =IFERROR(INDEX(M_User!$A$12:$J$67,MATCH(C23,M_User!$D$12:$D$67,0),3),"UNMAPPED") -> Doglas E. Shirima | E23: =IFERROR(INDEX(M_User!$A$12:$J$67,MATCH(C23,M_User!$D$12:$D$67,0),5),"UNMAPPED") -> ARS | F23: KD001 | G23: =IFERROR(INDEX(M_SKU!$A$18:$J$57,MATCH(F23,M_SKU!$B$18:$B$57,0),1),"UNKNOWN SKU") -> KNMW 500ml | H23: CK6-978 | I23: =IFERROR(INDEX(T_Unload!$K$10:$K$433,MATCH(B23,T_Unload!$B$10:$B$433,0)),0) -> 39 | J23: 39 | K23: =IF(ISBLANK(J23),"",I23-J23) -> 0 | L23: =IF(K23="","Awaiting Verification",IF(ABS(K23)<0.0001,"CLEAN",IF(K23>0,"Post to Default Outlet","Adjust Unload Upward"))) -> CLEAN | M23: =IF(AND(ISNUMBER(K23),K23>0.0001),K23,0) -> 0 | N23: =IF(AND(ISNUMBER(K23),K23<-0.0001),-K23,0) -> 0 | O23: Pending Verification
A24: ROP-0012 | B24: ARS000069|KD001|CK6-983 | C24: ARS000069 | D24: =IFERROR(INDEX(M_User!$A$12:$J$67,MATCH(C24,M_User!$D$12:$D$67,0),3),"UNMAPPED") -> Doglas E. Shirima | E24: =IFERROR(INDEX(M_User!$A$12:$J$67,MATCH(C24,M_User!$D$12:$D$67,0),5),"UNMAPPED") -> ARS | F24: KD001 | G24: =IFERROR(INDEX(M_SKU!$A$18:$J$57,MATCH(F24,M_SKU!$B$18:$B$57,0),1),"UNKNOWN SKU") -> KNMW 500ml | H24: CK6-983 | I24: =IFERROR(INDEX(T_Unload!$K$10:$K$433,MATCH(B24,T_Unload!$B$10:$B$433,0)),0) -> 0 | J24: 0 | K24: =IF(ISBLANK(J24),"",I24-J24) -> 0 | L24: =IF(K24="","Awaiting Verification",IF(ABS(K24)<0.0001,"CLEAN",IF(K24>0,"Post to Default Outlet","Adjust Unload Upward"))) -> CLEAN | M24: =IF(AND(ISNUMBER(K24),K24>0.0001),K24,0) -> 0 | N24: =IF(AND(ISNUMBER(K24),K24<-0.0001),-K24,0) -> 0 | O24: Pending Verification
... A341: ROP-0329 | B341: MOS100788|PO015|CK5-33366 | C341: MOS100788 | D341: =IFERROR(INDEX(M_User!$A$12:$J$67,MATCH(C341,M_User!$D$12:$D$67,0),3),"UNMAPPED") -> Masunga Mwala Ramadhani | E341: =IFERROR(INDEX(M_User!$A$12:$J$67,MATCH(C341,M_User!$D$12:$D$67,0),5),"UNMAPPED") -> MOS | F341: PO015 | G341: =IFERROR(INDEX(M_SKU!$A$18:$J$57,MATCH(F341,M_SKU!$B$18:$B$57,0),1),"UNKNOWN SKU") -> Sparletta Pine Apple Pet 300ML (x 12) | H341: CK5-33366 | I341: =IFERROR(INDEX(T_Unload!$K$10:$K$433,MATCH(B341,T_Unload!$B$10:$B$433,0)),0) -> 2 | J341: 2 | K341: =IF(ISBLANK(J341),"",I341-J341) -> 0 | L341: =IF(K341="","Awaiting Verification",IF(ABS(K341)<0.0001,"CLEAN",IF(K341>0,"Post to Default Outlet","Adjust Unload Upward"))) -> CLEAN | M341: =IF(AND(ISNUMBER(K341),K341>0.0001),K341,0) -> 0 | N341: =IF(AND(ISNUMBER(K341),K341<-0.0001),-K341,0) -> 0 | O341: Pending Verification
A342: ROP-0330 | B342: MOS100801|FG001|CK3-33409 | C342: MOS100801 | D342: =IFERROR(INDEX(M_User!$A$12:$J$67,MATCH(C342,M_User!$D$12:$D$67,0),3),"UNMAPPED") -> UNMAPPED | E342: =IFERROR(INDEX(M_User!$A$12:$J$67,MATCH(C342,M_User!$D$12:$D$67,0),5),"UNMAPPED") -> UNMAPPED | F342: FG001 | G342: =IFERROR(INDEX(M_SKU!$A$18:$J$57,MATCH(F342,M_SKU!$B$18:$B$57,0),1),"UNKNOWN SKU") -> Coke RGB 350ml | H342: CK3-33409 | I342: =IFERROR(INDEX(T_Unload!$K$10:$K$433,MATCH(B342,T_Unload!$B$10:$B$433,0)),0) -> 40 | L342: Awaiting Force-Push | O342: Blocked - Force-Push Required
A343: ROP-0331 | B343: MOS100801|FG002|CK3-33407 | C343: MOS100801 | D343: =IFERROR(INDEX(M_User!$A$12:$J$67,MATCH(C343,M_User!$D$12:$D$67,0),3),"UNMAPPED") -> UNMAPPED | E343: =IFERROR(INDEX(M_User!$A$12:$J$67,MATCH(C343,M_User!$D$12:$D$67,0),5),"UNMAPPED") -> UNMAPPED | F343: FG002 | G343: =IFERROR(INDEX(M_SKU!$A$18:$J$57,MATCH(F343,M_SKU!$B$18:$B$57,0),1),"UNKNOWN SKU") -> Fanta Orange RGB 350ml | H343: CK3-33407 | I343: =IFERROR(INDEX(T_Unload!$K$10:$K$433,MATCH(B343,T_Unload!$B$10:$B$433,0)),0) -> 15 | L343: Awaiting Force-Push | O343: Blocked - Force-Push Required
A344: ROP-0332 | B344: MOS100801|FG003|CK3-33356 | C344: MOS100801 | D344: =IFERROR(INDEX(M_User!$A$12:$J$67,MATCH(C344,M_User!$D$12:$D$67,0),3),"UNMAPPED") -> UNMAPPED | E344: =IFERROR(INDEX(M_User!$A$12:$J$67,MATCH(C344,M_User!$D$12:$D$67,0),5),"UNMAPPED") -> UNMAPPED | F344: FG003 | G344: =IFERROR(INDEX(M_SKU!$A$18:$J$57,MATCH(F344,M_SKU!$B$18:$B$57,0),1),"UNKNOWN SKU") -> Fanta Passion RGB 350ml | H344: CK3-33356 | I344: =IFERROR(INDEX(T_Unload!$K$10:$K$433,MATCH(B344,T_Unload!$B$10:$B$433,0)),0) -> 7 | L344: Awaiting Force-Push | O344: Blocked - Force-Push Required
A345: ROP-0333 | B345: MOS100801|FG004|CK3-33385 | C345: MOS100801 | D345: =IFERROR(INDEX(M_User!$A$12:$J$67,MATCH(C345,M_User!$D$12:$D$67,0),3),"UNMAPPED") -> UNMAPPED | E345: =IFERROR(INDEX(M_User!$A$12:$J$67,MATCH(C345,M_User!$D$12:$D$67,0),5),"UNMAPPED") -> UNMAPPED | F345: FG004 | G345: =IFERROR(INDEX(M_SKU!$A$18:$J$57,MATCH(F345,M_SKU!$B$18:$B$57,0),1),"UNKNOWN SKU") -> Fanta Pineapple RGB 350ml | H345: CK3-33385 | I345: =IFERROR(INDEX(T_Unload!$K$10:$K$433,MATCH(B345,T_Unload!$B$10:$B$433,0)),0) -> 7 | L345: Awaiting Force-Push | O345: Blocked - Force-Push Required
A346: ROP-0334 | B346: MOS100801|FG005|CK3-33402 | C346: MOS100801 | D346: =IFERROR(INDEX(M_User!$A$12:$J$67,MATCH(C346,M_User!$D$12:$D$67,0),3),"UNMAPPED") -> UNMAPPED | E346: =IFERROR(INDEX(M_User!$A$12:$J$67,MATCH(C346,M_User!$D$12:$D$67,0),5),"UNMAPPED") -> UNMAPPED | F346: FG005 | G346: =IFERROR(INDEX(M_SKU!$A$18:$J$57,MATCH(F346,M_SKU!$B$18:$B$57,0),1),"UNKNOWN SKU") -> Fanta Fruit Blast RGB 350 ml | H346: CK3-33402 | I346: =IFERROR(INDEX(T_Unload!$K$10:$K$433,MATCH(B346,T_Unload!$B$10:$B$433,0)),0) -> 5 | L346: Awaiting Force-Push | O346: Blocked - Force-Push Required
A347: ROP-0335 | B347: MOS100801|FG006|CK3-33414 | C347: MOS100801 | D347: =IFERROR(INDEX(M_User!$A$12:$J$67,MATCH(C347,M_User!$D$12:$D$67,0),3),"UNMAPPED") -> UNMAPPED | E347: =IFERROR(INDEX(M_User!$A$12:$J$67,MATCH(C347,M_User!$D$12:$D$67,0),5),"UNMAPPED") -> UNMAPPED | F347: FG006 | G347: =IFERROR(INDEX(M_SKU!$A$18:$J$57,MATCH(F347,M_SKU!$B$18:$B$57,0),1),"UNKNOWN SKU") -> Sprite 350ml | H347: CK3-33414 | I347: =IFERROR(INDEX(T_Unload!$K$10:$K$433,MATCH(B347,T_Unload!$B$10:$B$433,0)),0) -> 7 | L347: Awaiting Force-Push | O347: Blocked - Force-Push Required
A348: ROP-0336 | B348: MOS100801|FG007|CK3-33404 | C348: MOS100801 | D348: =IFERROR(INDEX(M_User!$A$12:$J$67,MATCH(C348,M_User!$D$12:$D$67,0),3),"UNMAPPED") -> UNMAPPED | E348: =IFERROR(INDEX(M_User!$A$12:$J$67,MATCH(C348,M_User!$D$12:$D$67,0),5),"UNMAPPED") -> UNMAPPED | F348: FG007 | G348: =IFERROR(INDEX(M_SKU!$A$18:$J$57,MATCH(F348,M_SKU!$B$18:$B$57,0),1),"UNKNOWN SKU") -> Stoney Tangawizi RGB 350ml | H348: CK3-33404 | I348: =IFERROR(INDEX(T_Unload!$K$10:$K$433,MATCH(B348,T_Unload!$B$10:$B$433,0)),0) -> 5 | L348: Awaiting Force-Push | O348: Blocked - Force-Push Required
A349: ROP-0337 | B349: MOS100801|FG008|CK3-33365 | C349: MOS100801 | D349: =IFERROR(INDEX(M_User!$A$12:$J$67,MATCH(C349,M_User!$D$12:$D$67,0),3),"UNMAPPED") -> UNMAPPED | E349: =IFERROR(INDEX(M_User!$A$12:$J$67,MATCH(C349,M_User!$D$12:$D$67,0),5),"UNMAPPED") -> UNMAPPED | F349: FG008 | G349: =IFERROR(INDEX(M_SKU!$A$18:$J$57,MATCH(F349,M_SKU!$B$18:$B$57,0),1),"UNKNOWN SKU") -> Sparletta Pinenut RGB 350ml | H349: CK3-33365 | I349: =IFERROR(INDEX(T_Unload!$K$10:$K$433,MATCH(B349,T_Unload!$B$10:$B$433,0)),0) -> 5 | L349: Awaiting Force-Push | O349: Blocked - Force-Push Required
A350: ROP-0338 | B350: MOS100801|FG009|CK3-33348 | C350: MOS100801 | D350: =IFERROR(INDEX(M_User!$A$12:$J$67,MATCH(C350,M_User!$D$12:$D$67,0),3),"UNMAPPED") -> UNMAPPED | E350: =IFERROR(INDEX(M_User!$A$12:$J$67,MATCH(C350,M_User!$D$12:$D$67,0),5),"UNMAPPED") -> UNMAPPED | F350: FG009 | G350: =IFERROR(INDEX(M_SKU!$A$18:$J$57,MATCH(F350,M_SKU!$B$18:$B$57,0),1),"UNKNOWN SKU") -> Krest Bitter Lemon RGB 300ml | H350: CK3-33348 | I350: =IFERROR(INDEX(T_Unload!$K$10:$K$433,MATCH(B350,T_Unload!$B$10:$B$433,0)),0) -> 3 | L350: Awaiting Force-Push | O350: Blocked - Force-Push Required
A351: ROP-0339 | B351: MOS100801|FG010|CK3-33301 | C351: MOS100801 | D351: =IFERROR(INDEX(M_User!$A$12:$J$67,MATCH(C351,M_User!$D$12:$D$67,0),3),"UNMAPPED") -> UNMAPPED | E351: =IFERROR(INDEX(M_User!$A$12:$J$67,MATCH(C351,M_User!$D$12:$D$67,0),5),"UNMAPPED") -> UNMAPPED | F351: FG010 | G351: =IFERROR(INDEX(M_SKU!$A$18:$J$57,MATCH(F351,M_SKU!$B$18:$B$57,0),1),"UNKNOWN SKU") -> Krest Club Soda RGB 300ml | H351: CK3-33301 | I351: =IFERROR(INDEX(T_Unload!$K$10:$K$433,MATCH(B351,T_Unload!$B$10:$B$433,0)),0) -> 3 | L351: Awaiting Force-Push | O351: Blocked - Force-Push Required
A352: ROP-0340 | B352: MOS100801|FG011|CK3-33347 | C352: MOS100801 | D352: =IFERROR(INDEX(M_User!$A$12:$J$67,MATCH(C352,M_User!$D$12:$D$67,0),3),"UNMAPPED") -> UNMAPPED | E352: =IFERROR(INDEX(M_User!$A$12:$J$67,MATCH(C352,M_User!$D$12:$D$67,0),5),"UNMAPPED") -> UNMAPPED | F352: FG011 | G352: =IFERROR(INDEX(M_SKU!$A$18:$J$57,MATCH(F352,M_SKU!$B$18:$B$57,0),1),"UNKNOWN SKU") -> Krest Tonic Water RGB 300ml | H352: CK3-33347 | I352: =IFERROR(INDEX(T_Unload!$K$10:$K$433,MATCH(B352,T_Unload!$B$10:$B$433,0)),0) -> 3 | L352: Awaiting Force-Push | O352: Blocked - Force-Push Required
A353: ROP-0341 | B353: MOS100801|FG012|CK3-33126 | C353: MOS100801 | D353: =IFERROR(INDEX(M_User!$A$12:$J$67,MATCH(C353,M_User!$D$12:$D$67,0),3),"UNMAPPED") -> UNMAPPED | E353: =IFERROR(INDEX(M_User!$A$12:$J$67,MATCH(C353,M_User!$D$12:$D$67,0),5),"UNMAPPED") -> UNMAPPED | F353: FG012 | G353: =IFERROR(INDEX(M_SKU!$A$18:$J$57,MATCH(F353,M_SKU!$B$18:$B$57,0),1),"UNKNOWN SKU") -> Krest Ginger Ale RGB 300ml | H353: CK3-33126 | I353: =IFERROR(INDEX(T_Unload!$K$10:$K$433,MATCH(B353,T_Unload!$B$10:$B$433,0)),0) -> 3 | L353: Awaiting Force-Push | O353: Blocked - Force-Push Required
... A365: ROP-0353 | B365: MOS100801|PO015|CK5-33366 | C365: MOS100801 | D365: =IFERROR(INDEX(M_User!$A$12:$J$67,MATCH(C365,M_User!$D$12:$D$67,0),3),"UNMAPPED") -> UNMAPPED | E365: =IFERROR(INDEX(M_User!$A$12:$J$67,MATCH(C365,M_User!$D$12:$D$67,0),5),"UNMAPPED") -> UNMAPPED | F365: PO015 | G365: =IFERROR(INDEX(M_SKU!$A$18:$J$57,MATCH(F365,M_SKU!$B$18:$B$57,0),1),"UNKNOWN SKU") -> Sparletta Pine Apple Pet 300ML (x 12) | H365: CK5-33366 | I365: =IFERROR(INDEX(T_Unload!$K$10:$K$433,MATCH(B365,T_Unload!$B$10:$B$433,0)),0) -> 5 | L365: Awaiting Force-Push | O365: Blocked - Force-Push Required
A366: ROP-0354 | B366: MOS100802|FG001|CK3-33410 | C366: MOS100802 | D366: =IFERROR(INDEX(M_User!$A$12:$J$67,MATCH(C366,M_User!$D$12:$D$67,0),3),"UNMAPPED") -> Joyline J Lyimo | E366: =IFERROR(INDEX(M_User!$A$12:$J$67,MATCH(C366,M_User!$D$12:$D$67,0),5),"UNMAPPED") -> MOS | F366: FG001 | G366: =IFERROR(INDEX(M_SKU!$A$18:$J$57,MATCH(F366,M_SKU!$B$18:$B$57,0),1),"UNKNOWN SKU") -> Coke RGB 350ml | H366: CK3-33410 | I366: =IFERROR(INDEX(T_Unload!$K$10:$K$433,MATCH(B366,T_Unload!$B$10:$B$433,0)),0) -> 1.6546748 | J366: 1.74 | K366: =IF(ISBLANK(J366),"",I366-J366) -> -0.085325234 | L366: =IF(K366="","Awaiting Verification",IF(ABS(K366)<0.0001,"CLEAN",IF(K366>0,"Post to Default Outlet","Adjust Unload Upward"))) -> Adjust Unload Upward | M366: =IF(AND(ISNUMBER(K366),K366>0.0001),K366,0) -> 0 | N366: =IF(AND(ISNUMBER(K366),K366<-0.0001),-K366,0) -> 0.085325234 | O366: Pending Verification
A367: ROP-0355 | B367: MOS100802|FG002|CK3-33407 | C367: MOS100802 | D367: =IFERROR(INDEX(M_User!$A$12:$J$67,MATCH(C367,M_User!$D$12:$D$67,0),3),"UNMAPPED") -> Joyline J Lyimo | E367: =IFERROR(INDEX(M_User!$A$12:$J$67,MATCH(C367,M_User!$D$12:$D$67,0),5),"UNMAPPED") -> MOS | F367: FG002 | G367: =IFERROR(INDEX(M_SKU!$A$18:$J$57,MATCH(F367,M_SKU!$B$18:$B$57,0),1),"UNKNOWN SKU") -> Fanta Orange RGB 350ml | H367: CK3-33407 | I367: =IFERROR(INDEX(T_Unload!$K$10:$K$433,MATCH(B367,T_Unload!$B$10:$B$433,0)),0) -> -0.62874905 | J367: 1.63 | K367: =IF(ISBLANK(J367),"",I367-J367) -> -2.2587491 | L367: =IF(K367="","Awaiting Verification",IF(ABS(K367)<0.0001,"CLEAN",IF(K367>0,"Post to Default Outlet","Adjust Unload Upward"))) -> Adjust Unload Upward | M367: =IF(AND(ISNUMBER(K367),K367>0.0001),K367,0) -> 0 | N367: =IF(AND(ISNUMBER(K367),K367<-0.0001),-K367,0) -> 2.2587491 | O367: Pending Verification
A368: ROP-0356 | B368: MOS100802|FG003|CK3-33356 | C368: MOS100802 | D368: =IFERROR(INDEX(M_User!$A$12:$J$67,MATCH(C368,M_User!$D$12:$D$67,0),3),"UNMAPPED") -> Joyline J Lyimo | E368: =IFERROR(INDEX(M_User!$A$12:$J$67,MATCH(C368,M_User!$D$12:$D$67,0),5),"UNMAPPED") -> MOS | F368: FG003 | G368: =IFERROR(INDEX(M_SKU!$A$18:$J$57,MATCH(F368,M_SKU!$B$18:$B$57,0),1),"UNKNOWN SKU") -> Fanta Passion RGB 350ml | H368: CK3-33356 | I368: =IFERROR(INDEX(T_Unload!$K$10:$K$433,MATCH(B368,T_Unload!$B$10:$B$433,0)),0) -> 0.26136294 | J368: 1 | K368: =IF(ISBLANK(J368),"",I368-J368) -> -0.73863706 | L368: =IF(K368="","Awaiting Verification",IF(ABS(K368)<0.0001,"CLEAN",IF(K368>0,"Post to Default Outlet","Adjust Unload Upward"))) -> Adjust Unload Upward | M368: =IF(AND(ISNUMBER(K368),K368>0.0001),K368,0) -> 0 | N368: =IF(AND(ISNUMBER(K368),K368<-0.0001),-K368,0) -> 0.73863706 | O368: Pending Verification
A369: ROP-0357 | B369: MOS100802|FG004|CK3-33385 | C369: MOS100802 | D369: =IFERROR(INDEX(M_User!$A$12:$J$67,MATCH(C369,M_User!$D$12:$D$67,0),3),"UNMAPPED") -> Joyline J Lyimo | E369: =IFERROR(INDEX(M_User!$A$12:$J$67,MATCH(C369,M_User!$D$12:$D$67,0),5),"UNMAPPED") -> MOS | F369: FG004 | G369: =IFERROR(INDEX(M_SKU!$A$18:$J$57,MATCH(F369,M_SKU!$B$18:$B$57,0),1),"UNKNOWN SKU") -> Fanta Pineapple RGB 350ml | H369: CK3-33385 | I369: =IFERROR(INDEX(T_Unload!$K$10:$K$433,MATCH(B369,T_Unload!$B$10:$B$433,0)),0) -> -0.52024219 | J369: 1.52 | K369: =IF(ISBLANK(J369),"",I369-J369) -> -2.0402422 | L369: =IF(K369="","Awaiting Verification",IF(ABS(K369)<0.0001,"CLEAN",IF(K369>0,"Post to Default Outlet","Adjust Unload Upward"))) -> Adjust Unload Upward | M369: =IF(AND(ISNUMBER(K369),K369>0.0001),K369,0) -> 0 | N369: =IF(AND(ISNUMBER(K369),K369<-0.0001),-K369,0) -> 2.0402422 | O369: Pending Verification
A370: ROP-0358 | B370: MOS100802|FG005|CK3-33402 | C370: MOS100802 | D370: =IFERROR(INDEX(M_User!$A$12:$J$67,MATCH(C370,M_User!$D$12:$D$67,0),3),"UNMAPPED") -> Joyline J Lyimo | E370: =IFERROR(INDEX(M_User!$A$12:$J$67,MATCH(C370,M_User!$D$12:$D$67,0),5),"UNMAPPED") -> MOS | F370: FG005 | G370: =IFERROR(INDEX(M_SKU!$A$18:$J$57,MATCH(F370,M_SKU!$B$18:$B$57,0),1),"UNKNOWN SKU") -> Fanta Fruit Blast RGB 350 ml | H370: CK3-33402 | I370: =IFERROR(INDEX(T_Unload!$K$10:$K$433,MATCH(B370,T_Unload!$B$10:$B$433,0)),0) -> 0.012526006 | J370: 1 | K370: =IF(ISBLANK(J370),"",I370-J370) -> -0.98747399 | L370: =IF(K370="","Awaiting Verification",IF(ABS(K370)<0.0001,"CLEAN",IF(K370>0,"Post to Default Outlet","Adjust Unload Upward"))) -> Adjust Unload Upward | M370: =IF(AND(ISNUMBER(K370),K370>0.0001),K370,0) -> 0 | N370: =IF(AND(ISNUMBER(K370),K370<-0.0001),-K370,0) -> 0.98747399 | O370: Pending Verification
A371: ROP-0359 | B371: MOS100802|FG006|CK3-33414 | C371: MOS100802 | D371: =IFERROR(INDEX(M_User!$A$12:$J$67,MATCH(C371,M_User!$D$12:$D$67,0),3),"UNMAPPED") -> Joyline J Lyimo | E371: =IFERROR(INDEX(M_User!$A$12:$J$67,MATCH(C371,M_User!$D$12:$D$67,0),5),"UNMAPPED") -> MOS | F371: FG006 | G371: =IFERROR(INDEX(M_SKU!$A$18:$J$57,MATCH(F371,M_SKU!$B$18:$B$57,0),1),"UNKNOWN SKU") -> Sprite 350ml | H371: CK3-33414 | I371: =IFERROR(INDEX(T_Unload!$K$10:$K$433,MATCH(B371,T_Unload!$B$10:$B$433,0)),0) -> -0.32368995 | J371: 1.32 | K371: =IF(ISBLANK(J371),"",I371-J371) -> -1.6436899 | L371: =IF(K371="","Awaiting Verification",IF(ABS(K371)<0.0001,"CLEAN",IF(K371>0,"Post to Default Outlet","Adjust Unload Upward"))) -> Adjust Unload Upward | M371: =IF(AND(ISNUMBER(K371),K371>0.0001),K371,0) -> 0 | N371: =IF(AND(ISNUMBER(K371),K371<-0.0001),-K371,0) -> 1.6436899 | O371: Pending Verification
A372: ROP-0360 | B372: MOS100802|FG007|CK3-33404 | C372: MOS100802 | D372: =IFERROR(INDEX(M_User!$A$12:$J$67,MATCH(C372,M_User!$D$12:$D$67,0),3),"UNMAPPED") -> Joyline J Lyimo | E372: =IFERROR(INDEX(M_User!$A$12:$J$67,MATCH(C372,M_User!$D$12:$D$67,0),5),"UNMAPPED") -> MOS | F372: FG007 | G372: =IFERROR(INDEX(M_SKU!$A$18:$J$57,MATCH(F372,M_SKU!$B$18:$B$57,0),1),"UNKNOWN SKU") -> Stoney Tangawizi RGB 350ml | H372: CK3-33404 | I372: =IFERROR(INDEX(T_Unload!$K$10:$K$433,MATCH(B372,T_Unload!$B$10:$B$433,0)),0) -> 0.064297059 | J372: 1 | K372: =IF(ISBLANK(J372),"",I372-J372) -> -0.93570294 | L372: =IF(K372="","Awaiting Verification",IF(ABS(K372)<0.0001,"CLEAN",IF(K372>0,"Post to Default Outlet","Adjust Unload Upward"))) -> Adjust Unload Upward | M372: =IF(AND(ISNUMBER(K372),K372>0.0001),K372,0) -> 0 | N372: =IF(AND(ISNUMBER(K372),K372<-0.0001),-K372,0) -> 0.93570294 | O372: Pending Verification
A373: ROP-0361 | B373: MOS100802|FG008|CK3-33365 | C373: MOS100802 | D373: =IFERROR(INDEX(M_User!$A$12:$J$67,MATCH(C373,M_User!$D$12:$D$67,0),3),"UNMAPPED") -> Joyline J Lyimo | E373: =IFERROR(INDEX(M_User!$A$12:$J$67,MATCH(C373,M_User!$D$12:$D$67,0),5),"UNMAPPED") -> MOS | F373: FG008 | G373: =IFERROR(INDEX(M_SKU!$A$18:$J$57,MATCH(F373,M_SKU!$B$18:$B$57,0),1),"UNKNOWN SKU") -> Sparletta Pinenut RGB 350ml | H373: CK3-33365 | I373: =IFERROR(INDEX(T_Unload!$K$10:$K$433,MATCH(B373,T_Unload!$B$10:$B$433,0)),0) -> 0.07767422 | J373: 1 | K373: =IF(ISBLANK(J373),"",I373-J373) -> -0.92232578 | L373: =IF(K373="","Awaiting Verification",IF(ABS(K373)<0.0001,"CLEAN",IF(K373>0,"Post to Default Outlet","Adjust Unload Upward"))) -> Adjust Unload Upward | M373: =IF(AND(ISNUMBER(K373),K373>0.0001),K373,0) -> 0 | N373: =IF(AND(ISNUMBER(K373),K373<-0.0001),-K373,0) -> 0.92232578 | O373: Pending Verification
A374: ROP-0362 | B374: MOS100802|FG009|CK3-33348 | C374: MOS100802 | D374: =IFERROR(INDEX(M_User!$A$12:$J$67,MATCH(C374,M_User!$D$12:$D$67,0),3),"UNMAPPED") -> Joyline J Lyimo | E374: =IFERROR(INDEX(M_User!$A$12:$J$67,MATCH(C374,M_User!$D$12:$D$67,0),5),"UNMAPPED") -> MOS | F374: FG009 | G374: =IFERROR(INDEX(M_SKU!$A$18:$J$57,MATCH(F374,M_SKU!$B$18:$B$57,0),1),"UNKNOWN SKU") -> Krest Bitter Lemon RGB 300ml | H374: CK3-33348 | I374: =IFERROR(INDEX(T_Unload!$K$10:$K$433,MATCH(B374,T_Unload!$B$10:$B$433,0)),0) -> 0.065510555 | J374: 1 | K374: =IF(ISBLANK(J374),"",I374-J374) -> -0.93448945 | L374: =IF(K374="","Awaiting Verification",IF(ABS(K374)<0.0001,"CLEAN",IF(K374>0,"Post to Default Outlet","Adjust Unload Upward"))) -> Adjust Unload Upward | M374: =IF(AND(ISNUMBER(K374),K374>0.0001),K374,0) -> 0 | N374: =IF(AND(ISNUMBER(K374),K374<-0.0001),-K374,0) -> 0.93448945 | O374: Pending Verification
A375: ROP-0363 | B375: MOS100802|FG010|CK3-33301 | C375: MOS100802 | D375: =IFERROR(INDEX(M_User!$A$12:$J$67,MATCH(C375,M_User!$D$12:$D$67,0),3),"UNMAPPED") -> Joyline J Lyimo | E375: =IFERROR(INDEX(M_User!$A$12:$J$67,MATCH(C375,M_User!$D$12:$D$67,0),5),"UNMAPPED") -> MOS | F375: FG010 | G375: =IFERROR(INDEX(M_SKU!$A$18:$J$57,MATCH(F375,M_SKU!$B$18:$B$57,0),1),"UNKNOWN SKU") -> Krest Club Soda RGB 300ml | H375: CK3-33301 | I375: =IFERROR(INDEX(T_Unload!$K$10:$K$433,MATCH(B375,T_Unload!$B$10:$B$433,0)),0) -> 0.095763909 | J375: 1 | K375: =IF(ISBLANK(J375),"",I375-J375) -> -0.90423609 | L375: =IF(K375="","Awaiting Verification",IF(ABS(K375)<0.0001,"CLEAN",IF(K375>0,"Post to Default Outlet","Adjust Unload Upward"))) -> Adjust Unload Upward | M375: =IF(AND(ISNUMBER(K375),K375>0.0001),K375,0) -> 0 | N375: =IF(AND(ISNUMBER(K375),K375<-0.0001),-K375,0) -> 0.90423609 | O375: Pending Verification
A376: ROP-0364 | B376: MOS100802|FG011|CK3-33347 | C376: MOS100802 | D376: =IFERROR(INDEX(M_User!$A$12:$J$67,MATCH(C376,M_User!$D$12:$D$67,0),3),"UNMAPPED") -> Joyline J Lyimo | E376: =IFERROR(INDEX(M_User!$A$12:$J$67,MATCH(C376,M_User!$D$12:$D$67,0),5),"UNMAPPED") -> MOS | F376: FG011 | G376: =IFERROR(INDEX(M_SKU!$A$18:$J$57,MATCH(F376,M_SKU!$B$18:$B$57,0),1),"UNKNOWN SKU") -> Krest Tonic Water RGB 300ml | H376: CK3-33347 | I376: =IFERROR(INDEX(T_Unload!$K$10:$K$433,MATCH(B376,T_Unload!$B$10:$B$433,0)),0) -> 0.033375304 | J376: 1 | K376: =IF(ISBLANK(J376),"",I376-J376) -> -0.9666247 | L376: =IF(K376="","Awaiting Verification",IF(ABS(K376)<0.0001,"CLEAN",IF(K376>0,"Post to Default Outlet","Adjust Unload Upward"))) -> Adjust Unload Upward | M376: =IF(AND(ISNUMBER(K376),K376>0.0001),K376,0) -> 0 | N376: =IF(AND(ISNUMBER(K376),K376<-0.0001),-K376,0) -> 0.9666247 | O376: Pending Verification
A377: ROP-0365 | B377: MOS100802|FG012|CK3-33126 | C377: MOS100802 | D377: =IFERROR(INDEX(M_User!$A$12:$J$67,MATCH(C377,M_User!$D$12:$D$67,0),3),"UNMAPPED") -> Joyline J Lyimo | E377: =IFERROR(INDEX(M_User!$A$12:$J$67,MATCH(C377,M_User!$D$12:$D$67,0),5),"UNMAPPED") -> MOS | F377: FG012 | G377: =IFERROR(INDEX(M_SKU!$A$18:$J$57,MATCH(F377,M_SKU!$B$18:$B$57,0),1),"UNKNOWN SKU") -> Krest Ginger Ale RGB 300ml | H377: CK3-33126 | I377: =IFERROR(INDEX(T_Unload!$K$10:$K$433,MATCH(B377,T_Unload!$B$10:$B$433,0)),0) -> 0.03673746 | J377: 1 | K377: =IF(ISBLANK(J377),"",I377-J377) -> -0.96326254 | L377: =IF(K377="","Awaiting Verification",IF(ABS(K377)<0.0001,"CLEAN",IF(K377>0,"Post to Default Outlet","Adjust Unload Upward"))) -> Adjust Unload Upward | M377: =IF(AND(ISNUMBER(K377),K377>0.0001),K377,0) -> 0 | N377: =IF(AND(ISNUMBER(K377),K377<-0.0001),-K377,0) -> 0.96326254 | O377: Pending Verification
... A436: ROP-0424 | B436: MOS100842|PO015|CK5-33366 | C436: MOS100842 | D436: =IFERROR(INDEX(M_User!$A$12:$J$67,MATCH(C436,M_User!$D$12:$D$67,0),3),"UNMAPPED") -> Samson Felix Ngowi | E436: =IFERROR(INDEX(M_User!$A$12:$J$67,MATCH(C436,M_User!$D$12:$D$67,0),5),"UNMAPPED") -> MOS | F436: PO015 | G436: =IFERROR(INDEX(M_SKU!$A$18:$J$57,MATCH(F436,M_SKU!$B$18:$B$57,0),1),"UNKNOWN SKU") -> Sparletta Pine Apple Pet 300ML (x 12) | H436: CK5-33366 | I436: =IFERROR(INDEX(T_Unload!$K$10:$K$433,MATCH(B436,T_Unload!$B$10:$B$433,0)),0) -> 1 | J436: 1 | K436: =IF(ISBLANK(J436),"",I436-J436) -> 0 | L436: =IF(K436="","Awaiting Verification",IF(ABS(K436)<0.0001,"CLEAN",IF(K436>0,"Post to Default Outlet","Adjust Unload Upward"))) -> CLEAN | M436: =IF(AND(ISNUMBER(K436),K436>0.0001),K436,0) -> 0 | N436: =IF(AND(ISNUMBER(K436),K436<-0.0001),-K436,0) -> 0 | O436: Pending Verification
A439: SUMMARY
A440: Total ROP Rows: | B440: =COUNTA(A13:A436) -> 424
A442: Resolution Action Breakdown:
A443: CLEAN (no action): | B443: =COUNTIF(L13:L436,"CLEAN") -> 192
A444: Post to Default Outlet (shortage): | B444: =COUNTIF(L13:L436,"Post to Default Outlet") -> 103
A445: Adjust Unload Upward (excess): | B445: =COUNTIF(L13:L436,"Adjust Unload Upward") -> 105
A446: Awaiting Force-Push: | B446: =COUNTIF(L13:L436,"Awaiting Force-Push") -> 24
A448: Quantity Totals:
A449: Total Expected ROP: | B449: =SUM(I13:I436) -> 1669.0595
A450: Total Actual ROP: | B450: =SUM(J13:J436) -> 1357.4152
A451: Total Default Outlet Posting: | B451: =SUM(M13:M436) -> 28.240627
A452: Total Unload Adjustment: | B452: =SUM(N13:N436) -> 36.59609
A454: Scenario Verification:
A455: Riziki (MOS100645) - SHORTAGE - rows with Default Outlet Posting: | B455: =COUNTIFS(C13:C436,"MOS100645",L13:L436,"Post to Default Outlet") -> 23
A456: Joyline (MOS100802) - EXCESS - rows with Unload Adjustment: | B456: =COUNTIFS(C13:C436,"MOS100802",L13:L436,"Adjust Unload Upward") -> 23
A457: James (MOS100801) - UNMAPPED - rows awaiting Force-Push: | B457: =COUNTIFS(C13:C436,"MOS100801",L13:L436,"Awaiting Force-Push") -> 24
A458: All other salesmen - CLEAN matches: | B458: =COUNTIF(L13:L436,"CLEAN") -> 192
A460: Note: Default Outlet postings will be priced at depot default price in T_DefaultOutletPosting (next sheet).

Sheet T_DefaultOutletPosting
A1: T_DefaultOutletPosting — Auto-Generated Shortage Postings
A2: Auto-generated from T_ROP where Resolution Action = "Post to Default Outlet".
A3: Each row mirrors a T_Sales record: a new sale is created against the Depot's Default Outlet at Depot Default Price.
A4: The Salesman remains ACCOUNTABLE for the cash collection of this shortage value. This row is pushed to SAP as a new sale.
A6: Column Groups: | B6: Identification | D6: From T_ROP | F6: Resolved by SFA | H6: Pricing | J6: State
A8: Posting ID | B8: Source ROP ID | C8: Posting Date | D8: Salesman SAP Code | E8: Salesman Name | F8: Depot | G8: Default Outlet Code | H8: Default Outlet Name | I8: SKU Code | J8: SKU Name | K8: Batch Number | L8: Shortage Qty (Posted) | M8: Unit Price (TZS) | N8: Posting Value (TZS) | O8: Salesman Accountable | P8: SAP Push Status | Q8: Pushed On
A9: DOP-0001 | B9: ROP-0040 | C9: 46179 | D9: MOS100079 | E9: =IFERROR(INDEX(M_User!$A$12:$J$67,MATCH(D9,M_User!$D$12:$D$67,0),3),"UNMAPPED") -> Meshack Jeremiah | F9: =IFERROR(INDEX(M_User!$A$12:$J$67,MATCH(D9,M_User!$D$12:$D$67,0),5),"UNMAPPED") -> MOS | G9: =IFERROR(INDEX(M_Depot!$C$7:$C$24,MATCH(F9,M_Depot!$B$7:$B$24,0)),"NO DEPOT") -> MOS1000001 | H9: =IFERROR(INDEX(M_Depot!$D$7:$D$24,MATCH(F9,M_Depot!$B$7:$B$24,0)),"NO DEPOT") -> MOSHI Ambush | I9: FG002 | J9: =IFERROR(INDEX(M_SKU!$A$18:$J$57,MATCH(I9,M_SKU!$B$18:$B$57,0),1),"UNKNOWN SKU") -> Fanta Orange RGB 350ml | K9: CK3-33407 | L9: 0.0013449316 | M9: {=IFERROR(INDEX(M_DepotPrice!$C$10:$C$52,MATCH(1,(M_DepotPrice!$A$10:$A$52=I9)*(M_DepotPrice!$H$10:$H$52=IFERROR(INDEX(M_Depot!$A$7:$A$24,MATCH(F9,M_Depot!$B$7:$B$24,0)),""))*(M_DepotPrice!$G$10:$G$52="Special"),0)),INDEX(M_DepotPrice!$C$10:$C$52,MATCH(1,(M_DepotPrice!$A$10:$A$52=I9)*(M_DepotPrice!$G$10:$G$52="Default"),0)))*1.18} -> 13900.4 | N9: =L9*M9 -> 18.695088 | O9: YES | P9: Pending Push
A10: DOP-0002 | B10: ROP-0043 | C10: 46179 | D10: MOS100079 | E10: =IFERROR(INDEX(M_User!$A$12:$J$67,MATCH(D10,M_User!$D$12:$D$67,0),3),"UNMAPPED") -> Meshack Jeremiah | F10: =IFERROR(INDEX(M_User!$A$12:$J$67,MATCH(D10,M_User!$D$12:$D$67,0),5),"UNMAPPED") -> MOS | G10: =IFERROR(INDEX(M_Depot!$C$7:$C$24,MATCH(F10,M_Depot!$B$7:$B$24,0)),"NO DEPOT") -> MOS1000001 | H10: =IFERROR(INDEX(M_Depot!$D$7:$D$24,MATCH(F10,M_Depot!$B$7:$B$24,0)),"NO DEPOT") -> MOSHI Ambush | I10: FG005 | J10: =IFERROR(INDEX(M_SKU!$A$18:$J$57,MATCH(I10,M_SKU!$B$18:$B$57,0),1),"UNKNOWN SKU") -> Fanta Fruit Blast RGB 350 ml | K10: CK3-33402 | L10: 0.0024568595 | M10: {=IFERROR(INDEX(M_DepotPrice!$C$10:$C$52,MATCH(1,(M_DepotPrice!$A$10:$A$52=I10)*(M_DepotPrice!$H$10:$H$52=IFERROR(INDEX(M_Depot!$A$7:$A$24,MATCH(F10,M_Depot!$B$7:$B$24,0)),""))*(M_DepotPrice!$G$10:$G$52="Special"),0)),INDEX(M_DepotPrice!$C$10:$C$52,MATCH(1,(M_DepotPrice!$A$10:$A$52=I10)*(M_DepotPrice!$G$10:$G$52="Default"),0)))*1.18} -> 13900.4 | N10: =L10*M10 -> 34.15133 | O10: YES | P10: Pending Push
A11: DOP-0003 | B11: ROP-0045 | C11: 46179 | D11: MOS100079 | E11: =IFERROR(INDEX(M_User!$A$12:$J$67,MATCH(D11,M_User!$D$12:$D$67,0),3),"UNMAPPED") -> Meshack Jeremiah | F11: =IFERROR(INDEX(M_User!$A$12:$J$67,MATCH(D11,M_User!$D$12:$D$67,0),5),"UNMAPPED") -> MOS | G11: =IFERROR(INDEX(M_Depot!$C$7:$C$24,MATCH(F11,M_Depot!$B$7:$B$24,0)),"NO DEPOT") -> MOS1000001 | H11: =IFERROR(INDEX(M_Depot!$D$7:$D$24,MATCH(F11,M_Depot!$B$7:$B$24,0)),"NO DEPOT") -> MOSHI Ambush | I11: FG007 | J11: =IFERROR(INDEX(M_SKU!$A$18:$J$57,MATCH(I11,M_SKU!$B$18:$B$57,0),1),"UNKNOWN SKU") -> Stoney Tangawizi RGB 350ml | K11: CK3-33404 | L11: 0.0040704576 | M11: {=IFERROR(INDEX(M_DepotPrice!$C$10:$C$52,MATCH(1,(M_DepotPrice!$A$10:$A$52=I11)*(M_DepotPrice!$H$10:$H$52=IFERROR(INDEX(M_Depot!$A$7:$A$24,MATCH(F11,M_Depot!$B$7:$B$24,0)),""))*(M_DepotPrice!$G$10:$G$52="Special"),0)),INDEX(M_DepotPrice!$C$10:$C$52,MATCH(1,(M_DepotPrice!$A$10:$A$52=I11)*(M_DepotPrice!$G$10:$G$52="Default"),0)))*1.18} -> 13900.4 | N11: =L11*M11 -> 56.580989 | O11: YES | P11: Pending Push
A12: DOP-0004 | B12: ROP-0046 | C12: 46179 | D12: MOS100079 | E12: =IFERROR(INDEX(M_User!$A$12:$J$67,MATCH(D12,M_User!$D$12:$D$67,0),3),"UNMAPPED") -> Meshack Jeremiah | F12: =IFERROR(INDEX(M_User!$A$12:$J$67,MATCH(D12,M_User!$D$12:$D$67,0),5),"UNMAPPED") -> MOS | G12: =IFERROR(INDEX(M_Depot!$C$7:$C$24,MATCH(F12,M_Depot!$B$7:$B$24,0)),"NO DEPOT") -> MOS1000001 | H12: =IFERROR(INDEX(M_Depot!$D$7:$D$24,MATCH(F12,M_Depot!$B$7:$B$24,0)),"NO DEPOT") -> MOSHI Ambush | I12: FG008 | J12: =IFERROR(INDEX(M_SKU!$A$18:$J$57,MATCH(I12,M_SKU!$B$18:$B$57,0),1),"UNKNOWN SKU") -> Sparletta Pinenut RGB 350ml | K12: CK3-33365 | L12: 0.0023942123 | M12: {=IFERROR(INDEX(M_DepotPrice!$C$10:$C$52,MATCH(1,(M_DepotPrice!$A$10:$A$52=I12)*(M_DepotPrice!$H$10:$H$52=IFERROR(INDEX(M_Depot!$A$7:$A$24,MATCH(F12,M_Depot!$B$7:$B$24,0)),""))*(M_DepotPrice!$G$10:$G$52="Special"),0)),INDEX(M_DepotPrice!$C$10:$C$52,MATCH(1,(M_DepotPrice!$A$10:$A$52=I12)*(M_DepotPrice!$G$10:$G$52="Default"),0)))*1.18} -> 13900.4 | N12: =L12*M12 -> 33.280508 | O12: YES | P12: Pending Push
A13: DOP-0005 | B13: ROP-0047 | C13: 46179 | D13: MOS100079 | E13: =IFERROR(INDEX(M_User!$A$12:$J$67,MATCH(D13,M_User!$D$12:$D$67,0),3),"UNMAPPED") -> Meshack Jeremiah | F13: =IFERROR(INDEX(M_User!$A$12:$J$67,MATCH(D13,M_User!$D$12:$D$67,0),5),"UNMAPPED") -> MOS | G13: =IFERROR(INDEX(M_Depot!$C$7:$C$24,MATCH(F13,M_Depot!$B$7:$B$24,0)),"NO DEPOT") -> MOS1000001 | H13: =IFERROR(INDEX(M_Depot!$D$7:$D$24,MATCH(F13,M_Depot!$B$7:$B$24,0)),"NO DEPOT") -> MOSHI Ambush | I13: FG009 | J13: =IFERROR(INDEX(M_SKU!$A$18:$J$57,MATCH(I13,M_SKU!$B$18:$B$57,0),1),"UNKNOWN SKU") -> Krest Bitter Lemon RGB 300ml | K13: CK3-33348 | L13: 0.0026302759 | M13: {=IFERROR(INDEX(M_DepotPrice!$C$10:$C$52,MATCH(1,(M_DepotPrice!$A$10:$A$52=I13)*(M_DepotPrice!$H$10:$H$52=IFERROR(INDEX(M_Depot!$A$7:$A$24,MATCH(F13,M_Depot!$B$7:$B$24,0)),""))*(M_DepotPrice!$G$10:$G$52="Special"),0)),INDEX(M_DepotPrice!$C$10:$C$52,MATCH(1,(M_DepotPrice!$A$10:$A$52=I13)*(M_DepotPrice!$G$10:$G$52="Default"),0)))*1.18} -> 13900.4 | N13: =L13*M13 -> 36.561887 | O13: YES | P13: Pending Push
A14: DOP-0006 | B14: ROP-0051 | C14: 46179 | D14: MOS100079 | E14: =IFERROR(INDEX(M_User!$A$12:$J$67,MATCH(D14,M_User!$D$12:$D$67,0),3),"UNMAPPED") -> Meshack Jeremiah | F14: =IFERROR(INDEX(M_User!$A$12:$J$67,MATCH(D14,M_User!$D$12:$D$67,0),5),"UNMAPPED") -> MOS | G14: =IFERROR(INDEX(M_Depot!$C$7:$C$24,MATCH(F14,M_Depot!$B$7:$B$24,0)),"NO DEPOT") -> MOS1000001 | H14: =IFERROR(INDEX(M_Depot!$D$7:$D$24,MATCH(F14,M_Depot!$B$7:$B$24,0)),"NO DEPOT") -> MOSHI Ambush | I14: FG024 | J14: =IFERROR(INDEX(M_SKU!$A$18:$J$57,MATCH(I14,M_SKU!$B$18:$B$57,0),1),"UNKNOWN SKU") -> Sparletta Red Apple RGB 350ml | K14: CK3-32758 | L14: 0.00047773802 | M14: {=IFERROR(INDEX(M_DepotPrice!$C$10:$C$52,MATCH(1,(M_DepotPrice!$A$10:$A$52=I14)*(M_DepotPrice!$H$10:$H$52=IFERROR(INDEX(M_Depot!$A$7:$A$24,MATCH(F14,M_Depot!$B$7:$B$24,0)),""))*(M_DepotPrice!$G$10:$G$52="Special"),0)),INDEX(M_DepotPrice!$C$10:$C$52,MATCH(1,(M_DepotPrice!$A$10:$A$52=I14)*(M_DepotPrice!$G$10:$G$52="Default"),0)))*1.18} -> 13900.4 | N14: =L14*M14 -> 6.6407496 | O14: YES | P14: Pending Push
A15: DOP-0007 | B15: ROP-0066 | C15: 46179 | D15: MOS100144 | E15: =IFERROR(INDEX(M_User!$A$12:$J$67,MATCH(D15,M_User!$D$12:$D$67,0),3),"UNMAPPED") -> Zefania Julius Ngoma | F15: =IFERROR(INDEX(M_User!$A$12:$J$67,MATCH(D15,M_User!$D$12:$D$67,0),5),"UNMAPPED") -> MOS | G15: =IFERROR(INDEX(M_Depot!$C$7:$C$24,MATCH(F15,M_Depot!$B$7:$B$24,0)),"NO DEPOT") -> MOS1000001 | H15: =IFERROR(INDEX(M_Depot!$D$7:$D$24,MATCH(F15,M_Depot!$B$7:$B$24,0)),"NO DEPOT") -> MOSHI Ambush | I15: FG004 | J15: =IFERROR(INDEX(M_SKU!$A$18:$J$57,MATCH(I15,M_SKU!$B$18:$B$57,0),1),"UNKNOWN SKU") -> Fanta Pineapple RGB 350ml | K15: CK3-33385 | L15: 0.0031459238 | M15: {=IFERROR(INDEX(M_DepotPrice!$C$10:$C$52,MATCH(1,(M_DepotPrice!$A$10:$A$52=I15)*(M_DepotPrice!$H$10:$H$52=IFERROR(INDEX(M_Depot!$A$7:$A$24,MATCH(F15,M_Depot!$B$7:$B$24,0)),""))*(M_DepotPrice!$G$10:$G$52="Special"),0)),INDEX(M_DepotPrice!$C$10:$C$52,MATCH(1,(M_DepotPrice!$A$10:$A$52=I15)*(M_DepotPrice!$G$10:$G$52="Default"),0)))*1.18} -> 13900.4 | N15: =L15*M15 -> 43.729599 | O15: YES | P15: Pending Push
A16: DOP-0008 | B16: ROP-0067 | C16: 46179 | D16: MOS100144 | E16: =IFERROR(INDEX(M_User!$A$12:$J$67,MATCH(D16,M_User!$D$12:$D$67,0),3),"UNMAPPED") -> Zefania Julius Ngoma | F16: =IFERROR(INDEX(M_User!$A$12:$J$67,MATCH(D16,M_User!$D$12:$D$67,0),5),"UNMAPPED") -> MOS | G16: =IFERROR(INDEX(M_Depot!$C$7:$C$24,MATCH(F16,M_Depot!$B$7:$B$24,0)),"NO DEPOT") -> MOS1000001 | H16: =IFERROR(INDEX(M_Depot!$D$7:$D$24,MATCH(F16,M_Depot!$B$7:$B$24,0)),"NO DEPOT") -> MOSHI Ambush | I16: FG005 | J16: =IFERROR(INDEX(M_SKU!$A$18:$J$57,MATCH(I16,M_SKU!$B$18:$B$57,0),1),"UNKNOWN SKU") -> Fanta Fruit Blast RGB 350 ml | K16: CK3-33402 | L16: 0.0043352658 | M16: {=IFERROR(INDEX(M_DepotPrice!$C$10:$C$52,MATCH(1,(M_DepotPrice!$A$10:$A$52=I16)*(M_DepotPrice!$H$10:$H$52=IFERROR(INDEX(M_Depot!$A$7:$A$24,MATCH(F16,M_Depot!$B$7:$B$24,0)),""))*(M_DepotPrice!$G$10:$G$52="Special"),0)),INDEX(M_DepotPrice!$C$10:$C$52,MATCH(1,(M_DepotPrice!$A$10:$A$52=I16)*(M_DepotPrice!$G$10:$G$52="Default"),0)))*1.18} -> 13900.4 | N16: =L16*M16 -> 60.261929 | O16: YES | P16: Pending Push
A17: DOP-0009 | B17: ROP-0068 | C17: 46179 | D17: MOS100144 | E17: =IFERROR(INDEX(M_User!$A$12:$J$67,MATCH(D17,M_User!$D$12:$D$67,0),3),"UNMAPPED") -> Zefania Julius Ngoma | F17: =IFERROR(INDEX(M_User!$A$12:$J$67,MATCH(D17,M_User!$D$12:$D$67,0),5),"UNMAPPED") -> MOS | G17: =IFERROR(INDEX(M_Depot!$C$7:$C$24,MATCH(F17,M_Depot!$B$7:$B$24,0)),"NO DEPOT") -> MOS1000001 | H17: =IFERROR(INDEX(M_Depot!$D$7:$D$24,MATCH(F17,M_Depot!$B$7:$B$24,0)),"NO DEPOT") -> MOSHI Ambush | I17: FG006 | J17: =IFERROR(INDEX(M_SKU!$A$18:$J$57,MATCH(I17,M_SKU!$B$18:$B$57,0),1),"UNKNOWN SKU") -> Sprite 350ml | K17: CK3-33414 | L17: 0.002669238 | M17: {=IFERROR(INDEX(M_DepotPrice!$C$10:$C$52,MATCH(1,(M_DepotPrice!$A$10:$A$52=I17)*(M_DepotPrice!$H$10:$H$52=IFERROR(INDEX(M_Depot!$A$7:$A$24,MATCH(F17,M_Depot!$B$7:$B$24,0)),""))*(M_DepotPrice!$G$10:$G$52="Special"),0)),INDEX(M_DepotPrice!$C$10:$C$52,MATCH(1,(M_DepotPrice!$A$10:$A$52=I17)*(M_DepotPrice!$G$10:$G$52="Default"),0)))*1.18} -> 13900.4 | N17: =L17*M17 -> 37.103476 | O17: YES | P17: Pending Push
A18: DOP-0010 | B18: ROP-0080 | C18: 46179 | D18: MOS100180 | E18: =IFERROR(INDEX(M_User!$A$12:$J$67,MATCH(D18,M_User!$D$12:$D$67,0),3),"UNMAPPED") -> Deodat Francis Materu | F18: =IFERROR(INDEX(M_User!$A$12:$J$67,MATCH(D18,M_User!$D$12:$D$67,0),5),"UNMAPPED") -> MOS | G18: =IFERROR(INDEX(M_Depot!$C$7:$C$24,MATCH(F18,M_Depot!$B$7:$B$24,0)),"NO DEPOT") -> MOS1000001 | H18: =IFERROR(INDEX(M_Depot!$D$7:$D$24,MATCH(F18,M_Depot!$B$7:$B$24,0)),"NO DEPOT") -> MOSHI Ambush | I18: FG001 | J18: =IFERROR(INDEX(M_SKU!$A$18:$J$57,MATCH(I18,M_SKU!$B$18:$B$57,0),1),"UNKNOWN SKU") -> Coke RGB 350ml | K18: CK3-33409 | L18: 0.0025662856 | M18: {=IFERROR(INDEX(M_DepotPrice!$C$10:$C$52,MATCH(1,(M_DepotPrice!$A$10:$A$52=I18)*(M_DepotPrice!$H$10:$H$52=IFERROR(INDEX(M_Depot!$A$7:$A$24,MATCH(F18,M_Depot!$B$7:$B$24,0)),""))*(M_DepotPrice!$G$10:$G$52="Special"),0)),INDEX(M_DepotPrice!$C$10:$C$52,MATCH(1,(M_DepotPrice!$A$10:$A$52=I18)*(M_DepotPrice!$G$10:$G$52="Default"),0)))*1.18} -> 13900.4 | N18: =L18*M18 -> 35.672396 | O18: YES | P18: Pending Push
A19: DOP-0011 | B19: ROP-0081 | C19: 46179 | D19: MOS100180 | E19: =IFERROR(INDEX(M_User!$A$12:$J$67,MATCH(D19,M_User!$D$12:$D$67,0),3),"UNMAPPED") -> Deodat Francis Materu | F19: =IFERROR(INDEX(M_User!$A$12:$J$67,MATCH(D19,M_User!$D$12:$D$67,0),5),"UNMAPPED") -> MOS | G19: =IFERROR(INDEX(M_Depot!$C$7:$C$24,MATCH(F19,M_Depot!$B$7:$B$24,0)),"NO DEPOT") -> MOS1000001 | H19: =IFERROR(INDEX(M_Depot!$D$7:$D$24,MATCH(F19,M_Depot!$B$7:$B$24,0)),"NO DEPOT") -> MOSHI Ambush | I19: FG002 | J19: =IFERROR(INDEX(M_SKU!$A$18:$J$57,MATCH(I19,M_SKU!$B$18:$B$57,0),1),"UNKNOWN SKU") -> Fanta Orange RGB 350ml | K19: CK3-33407 | L19: 0.00087388465 | M19: {=IFERROR(INDEX(M_DepotPrice!$C$10:$C$52,MATCH(1,(M_DepotPrice!$A$10:$A$52=I19)*(M_DepotPrice!$H$10:$H$52=IFERROR(INDEX(M_Depot!$A$7:$A$24,MATCH(F19,M_Depot!$B$7:$B$24,0)),""))*(M_DepotPrice!$G$10:$G$52="Special"),0)),INDEX(M_DepotPrice!$C$10:$C$52,MATCH(1,(M_DepotPrice!$A$10:$A$52=I19)*(M_DepotPrice!$G$10:$G$52="Default"),0)))*1.18} -> 13900.4 | N19: =L19*M19 -> 12.147346 | O19: YES | P19: Pending Push
A20: DOP-0012 | B20: ROP-0082 | C20: 46179 | D20: MOS100180 | E20: =IFERROR(INDEX(M_User!$A$12:$J$67,MATCH(D20,M_User!$D$12:$D$67,0),3),"UNMAPPED") -> Deodat Francis Materu | F20: =IFERROR(INDEX(M_User!$A$12:$J$67,MATCH(D20,M_User!$D$12:$D$67,0),5),"UNMAPPED") -> MOS | G20: =IFERROR(INDEX(M_Depot!$C$7:$C$24,MATCH(F20,M_Depot!$B$7:$B$24,0)),"NO DEPOT") -> MOS1000001 | H20: =IFERROR(INDEX(M_Depot!$D$7:$D$24,MATCH(F20,M_Depot!$B$7:$B$24,0)),"NO DEPOT") -> MOSHI Ambush | I20: FG003 | J20: =IFERROR(INDEX(M_SKU!$A$18:$J$57,MATCH(I20,M_SKU!$B$18:$B$57,0),1),"UNKNOWN SKU") -> Fanta Passion RGB 350ml | K20: CK3-33356 | L20: 0.0030781441 | M20: {=IFERROR(INDEX(M_DepotPrice!$C$10:$C$52,MATCH(1,(M_DepotPrice!$A$10:$A$52=I20)*(M_DepotPrice!$H$10:$H$52=IFERROR(INDEX(M_Depot!$A$7:$A$24,MATCH(F20,M_Depot!$B$7:$B$24,0)),""))*(M_DepotPrice!$G$10:$G$52="Special"),0)),INDEX(M_DepotPrice!$C$10:$C$52,MATCH(1,(M_DepotPrice!$A$10:$A$52=I20)*(M_DepotPrice!$G$10:$G$52="Default"),0)))*1.18} -> 13900.4 | N20: =L20*M20 -> 42.787434 | O20: YES | P20: Pending Push
... A111: DOP-0103 | B111: ROP-0413 | C111: 46179 | D111: MOS100842 | E111: =IFERROR(INDEX(M_User!$A$12:$J$67,MATCH(D111,M_User!$D$12:$D$67,0),3),"UNMAPPED") -> Samson Felix Ngowi | F111: =IFERROR(INDEX(M_User!$A$12:$J$67,MATCH(D111,M_User!$D$12:$D$67,0),5),"UNMAPPED") -> MOS | G111: =IFERROR(INDEX(M_Depot!$C$7:$C$24,MATCH(F111,M_Depot!$B$7:$B$24,0)),"NO DEPOT") -> MOS1000001 | H111: =IFERROR(INDEX(M_Depot!$D$7:$D$24,MATCH(F111,M_Depot!$B$7:$B$24,0)),"NO DEPOT") -> MOSHI Ambush | I111: FG024 | J111: =IFERROR(INDEX(M_SKU!$A$18:$J$57,MATCH(I111,M_SKU!$B$18:$B$57,0),1),"UNKNOWN SKU") -> Sparletta Red Apple RGB 350ml | K111: CK3-32758 | L111: 0.00041942809 | M111: {=IFERROR(INDEX(M_DepotPrice!$C$10:$C$52,MATCH(1,(M_DepotPrice!$A$10:$A$52=I111)*(M_DepotPrice!$H$10:$H$52=IFERROR(INDEX(M_Depot!$A$7:$A$24,MATCH(F111,M_Depot!$B$7:$B$24,0)),""))*(M_DepotPrice!$G$10:$G$52="Special"),0)),INDEX(M_DepotPrice!$C$10:$C$52,MATCH(1,(M_DepotPrice!$A$10:$A$52=I111)*(M_DepotPrice!$G$10:$G$52="Default"),0)))*1.18} -> 13900.4 | N111: =L111*M111 -> 5.8302183 | O111: YES | P111: Pending Push
A114: SUMMARY
A115: Total Postings Generated: | D115: =COUNTA(A9:A111) -> 103
A116: Unique Salesmen Affected: | D116: =SUMPRODUCT(1/COUNTIF(D9:D111,D9:D111)) -> 14
A117: Total Shortage Qty: | D117: =SUM(L9:L111) -> 28.240627
A118: Total Shortage Value (TZS): | D118: =SUM(N9:N111) -> 263742.5
A120: Top Shortage Salesmen:
A121: Riziki Rajabu (MOS100645) shortage value: | D121: =SUMIF(D9:D111,"MOS100645",N9:N111) -> 261171.22
A123: Note: These postings are visible as sales-against-depot-default-outlet. Salesmen must collect cash from depot equivalent to the shortage value.

Sheet T_VarianceReasons
A1: T_VarianceReasons — Supervisor Reason Logging (Parallel)
A2: Every non-CLEAN T_ROP row spawns one entry here. Supervisor must log Reason Category + Description within 24 hours.
A3: IMPORTANT: This flow is PARALLEL — it does NOT block Default Outlet posting or Unload adjustment. Those happen automatically.
A4: SLA Tracking: 24 hours from T_ROP date. Status auto-tracked as "Within SLA", "Breached", or "Pending".
A6: Column Groups: | B6: Identification | D6: From T_ROP | F6: Resolved by SFA | H6: SUPERVISOR INPUT | J6: SLA Tracking
A8: Reason ID | B8: Source ROP ID | C8: Variance Type | D8: Salesman SAP Code | E8: Salesman Name | F8: SKU Code | G8: SKU Name | H8: Batch Number | I8: Variance Qty | J8: Reason Category | K8: Reason Description | L8: Logged By (Supervisor) | M8: Logged On | N8: SLA Deadline | O8: SLA Status
A9: VR-0001 | B9: ROP-0039 | C9: Excess | D9: MOS100079 | E9: =IFERROR(INDEX(M_User!$A$12:$J$67,MATCH(D9,M_User!$D$12:$D$67,0),3),"UNMAPPED") -> Meshack Jeremiah | F9: FG001 | G9: =IFERROR(INDEX(M_SKU!$A$18:$J$57,MATCH(F9,M_SKU!$B$18:$B$57,0),1),"UNKNOWN SKU") -> Coke RGB 350ml | H9: CK3-33409 | I9: 0.0039580276 | N9: 46180 | O9: =IF(ISBLANK(M9),IF(TODAY()>N9,"BREACHED","PENDING"),IF(M9<=N9,"Within SLA","BREACHED")) -> BREACHED
A10: VR-0002 | B10: ROP-0040 | C10: Shortage | D10: MOS100079 | E10: =IFERROR(INDEX(M_User!$A$12:$J$67,MATCH(D10,M_User!$D$12:$D$67,0),3),"UNMAPPED") -> Meshack Jeremiah | F10: FG002 | G10: =IFERROR(INDEX(M_SKU!$A$18:$J$57,MATCH(F10,M_SKU!$B$18:$B$57,0),1),"UNKNOWN SKU") -> Fanta Orange RGB 350ml | H10: CK3-33407 | I10: 0.0013449316 | N10: 46180 | O10: =IF(ISBLANK(M10),IF(TODAY()>N10,"BREACHED","PENDING"),IF(M10<=N10,"Within SLA","BREACHED")) -> BREACHED
A11: VR-0003 | B11: ROP-0041 | C11: Excess | D11: MOS100079 | E11: =IFERROR(INDEX(M_User!$A$12:$J$67,MATCH(D11,M_User!$D$12:$D$67,0),3),"UNMAPPED") -> Meshack Jeremiah | F11: FG003 | G11: =IFERROR(INDEX(M_SKU!$A$18:$J$57,MATCH(F11,M_SKU!$B$18:$B$57,0),1),"UNKNOWN SKU") -> Fanta Passion RGB 350ml | H11: CK3-33356 | I11: 0.0030169508 | N11: 46180 | O11: =IF(ISBLANK(M11),IF(TODAY()>N11,"BREACHED","PENDING"),IF(M11<=N11,"Within SLA","BREACHED")) -> BREACHED
A12: VR-0004 | B12: ROP-0043 | C12: Shortage | D12: MOS100079 | E12: =IFERROR(INDEX(M_User!$A$12:$J$67,MATCH(D12,M_User!$D$12:$D$67,0),3),"UNMAPPED") -> Meshack Jeremiah | F12: FG005 | G12: =IFERROR(INDEX(M_SKU!$A$18:$J$57,MATCH(F12,M_SKU!$B$18:$B$57,0),1),"UNKNOWN SKU") -> Fanta Fruit Blast RGB 350 ml | H12: CK3-33402 | I12: 0.0024568595 | J12: Damage / Breakage | K12: Pallet damaged during transit; mixed breakage | L12: BBL_SUP_086 | M12: 46179 | N12: 46180 | O12: =IF(ISBLANK(M12),IF(TODAY()>N12,"BREACHED","PENDING"),IF(M12<=N12,"Within SLA","BREACHED")) -> Within SLA
A13: VR-0005 | B13: ROP-0044 | C13: Excess | D13: MOS100079 | E13: =IFERROR(INDEX(M_User!$A$12:$J$67,MATCH(D13,M_User!$D$12:$D$67,0),3),"UNMAPPED") -> Meshack Jeremiah | F13: FG006 | G13: =IFERROR(INDEX(M_SKU!$A$18:$J$57,MATCH(F13,M_SKU!$B$18:$B$57,0),1),"UNKNOWN SKU") -> Sprite 350ml | H13: CK3-33414 | I13: 0.0030874536 | N13: 46180 | O13: =IF(ISBLANK(M13),IF(TODAY()>N13,"BREACHED","PENDING"),IF(M13<=N13,"Within SLA","BREACHED")) -> BREACHED
A14: VR-0006 | B14: ROP-0045 | C14: Shortage | D14: MOS100079 | E14: =IFERROR(INDEX(M_User!$A$12:$J$67,MATCH(D14,M_User!$D$12:$D$67,0),3),"UNMAPPED") -> Meshack Jeremiah | F14: FG007 | G14: =IFERROR(INDEX(M_SKU!$A$18:$J$57,MATCH(F14,M_SKU!$B$18:$B$57,0),1),"UNKNOWN SKU") -> Stoney Tangawizi RGB 350ml | H14: CK3-33404 | I14: 0.0040704576 | N14: 46180 | O14: =IF(ISBLANK(M14),IF(TODAY()>N14,"BREACHED","PENDING"),IF(M14<=N14,"Within SLA","BREACHED")) -> BREACHED
A15: VR-0007 | B15: ROP-0046 | C15: Shortage | D15: MOS100079 | E15: =IFERROR(INDEX(M_User!$A$12:$J$67,MATCH(D15,M_User!$D$12:$D$67,0),3),"UNMAPPED") -> Meshack Jeremiah | F15: FG008 | G15: =IFERROR(INDEX(M_SKU!$A$18:$J$57,MATCH(F15,M_SKU!$B$18:$B$57,0),1),"UNKNOWN SKU") -> Sparletta Pinenut RGB 350ml | H15: CK3-33365 | I15: 0.0023942123 | N15: 46180 | O15: =IF(ISBLANK(M15),IF(TODAY()>N15,"BREACHED","PENDING"),IF(M15<=N15,"Within SLA","BREACHED")) -> BREACHED
A16: VR-0008 | B16: ROP-0047 | C16: Shortage | D16: MOS100079 | E16: =IFERROR(INDEX(M_User!$A$12:$J$67,MATCH(D16,M_User!$D$12:$D$67,0),3),"UNMAPPED") -> Meshack Jeremiah | F16: FG009 | G16: =IFERROR(INDEX(M_SKU!$A$18:$J$57,MATCH(F16,M_SKU!$B$18:$B$57,0),1),"UNKNOWN SKU") -> Krest Bitter Lemon RGB 300ml | H16: CK3-33348 | I16: 0.0026302759 | N16: 46180 | O16: =IF(ISBLANK(M16),IF(TODAY()>N16,"BREACHED","PENDING"),IF(M16<=N16,"Within SLA","BREACHED")) -> BREACHED
A17: VR-0009 | B17: ROP-0048 | C17: Excess | D17: MOS100079 | E17: =IFERROR(INDEX(M_User!$A$12:$J$67,MATCH(D17,M_User!$D$12:$D$67,0),3),"UNMAPPED") -> Meshack Jeremiah | F17: FG010 | G17: =IFERROR(INDEX(M_SKU!$A$18:$J$57,MATCH(F17,M_SKU!$B$18:$B$57,0),1),"UNKNOWN SKU") -> Krest Club Soda RGB 300ml | H17: CK3-33301 | I17: 0.0033622143 | N17: 46180 | O17: =IF(ISBLANK(M17),IF(TODAY()>N17,"BREACHED","PENDING"),IF(M17<=N17,"Within SLA","BREACHED")) -> BREACHED
A18: VR-0010 | B18: ROP-0049 | C18: Excess | D18: MOS100079 | E18: =IFERROR(INDEX(M_User!$A$12:$J$67,MATCH(D18,M_User!$D$12:$D$67,0),3),"UNMAPPED") -> Meshack Jeremiah | F18: FG011 | G18: =IFERROR(INDEX(M_SKU!$A$18:$J$57,MATCH(F18,M_SKU!$B$18:$B$57,0),1),"UNKNOWN SKU") -> Krest Tonic Water RGB 300ml | H18: CK3-33347 | I18: 0.0026009741 | N18: 46180 | O18: =IF(ISBLANK(M18),IF(TODAY()>N18,"BREACHED","PENDING"),IF(M18<=N18,"Within SLA","BREACHED")) -> BREACHED
A19: VR-0011 | B19: ROP-0050 | C19: Excess | D19: MOS100079 | E19: =IFERROR(INDEX(M_User!$A$12:$J$67,MATCH(D19,M_User!$D$12:$D$67,0),3),"UNMAPPED") -> Meshack Jeremiah | F19: FG012 | G19: =IFERROR(INDEX(M_SKU!$A$18:$J$57,MATCH(F19,M_SKU!$B$18:$B$57,0),1),"UNKNOWN SKU") -> Krest Ginger Ale RGB 300ml | H19: CK3-33126 | I19: 0.0046661472 | N19: 46180 | O19: =IF(ISBLANK(M19),IF(TODAY()>N19,"BREACHED","PENDING"),IF(M19<=N19,"Within SLA","BREACHED")) -> BREACHED
A20: VR-0012 | B20: ROP-0051 | C20: Shortage | D20: MOS100079 | E20: =IFERROR(INDEX(M_User!$A$12:$J$67,MATCH(D20,M_User!$D$12:$D$67,0),3),"UNMAPPED") -> Meshack Jeremiah | F20: FG024 | G20: =IFERROR(INDEX(M_SKU!$A$18:$J$57,MATCH(F20,M_SKU!$B$18:$B$57,0),1),"UNKNOWN SKU") -> Sparletta Red Apple RGB 350ml | H20: CK3-32758 | I20: 0.00047773802 | N20: 46180 | O20: =IF(ISBLANK(M20),IF(TODAY()>N20,"BREACHED","PENDING"),IF(M20<=N20,"Within SLA","BREACHED")) -> BREACHED
A21: VR-0013 | B21: ROP-0063 | C21: Excess | D21: MOS100144 | E21: =IFERROR(INDEX(M_User!$A$12:$J$67,MATCH(D21,M_User!$D$12:$D$67,0),3),"UNMAPPED") -> Zefania Julius Ngoma | F21: FG001 | G21: =IFERROR(INDEX(M_SKU!$A$18:$J$57,MATCH(F21,M_SKU!$B$18:$B$57,0),1),"UNKNOWN SKU") -> Coke RGB 350ml | H21: CK3-33409 | I21: 0.0030227209 | N21: 46180 | O21: =IF(ISBLANK(M21),IF(TODAY()>N21,"BREACHED","PENDING"),IF(M21<=N21,"Within SLA","BREACHED")) -> BREACHED
A22: VR-0014 | B22: ROP-0064 | C22: Excess | D22: MOS100144 | E22: =IFERROR(INDEX(M_User!$A$12:$J$67,MATCH(D22,M_User!$D$12:$D$67,0),3),"UNMAPPED") -> Zefania Julius Ngoma | F22: FG002 | G22: =IFERROR(INDEX(M_SKU!$A$18:$J$57,MATCH(F22,M_SKU!$B$18:$B$57,0),1),"UNKNOWN SKU") -> Fanta Orange RGB 350ml | H22: CK3-33407 | I22: 0.0048592864 | N22: 46180 | O22: =IF(ISBLANK(M22),IF(TODAY()>N22,"BREACHED","PENDING"),IF(M22<=N22,"Within SLA","BREACHED")) -> BREACHED
A23: VR-0015 | B23: ROP-0065 | C23: Excess | D23: MOS100144 | E23: =IFERROR(INDEX(M_User!$A$12:$J$67,MATCH(D23,M_User!$D$12:$D$67,0),3),"UNMAPPED") -> Zefania Julius Ngoma | F23: FG003 | G23: =IFERROR(INDEX(M_SKU!$A$18:$J$57,MATCH(F23,M_SKU!$B$18:$B$57,0),1),"UNKNOWN SKU") -> Fanta Passion RGB 350ml | H23: CK3-33356 | I23: 0.0034945933 | N23: 46180 | O23: =IF(ISBLANK(M23),IF(TODAY()>N23,"BREACHED","PENDING"),IF(M23<=N23,"Within SLA","BREACHED")) -> BREACHED
A24: VR-0016 | B24: ROP-0066 | C24: Shortage | D24: MOS100144 | E24: =IFERROR(INDEX(M_User!$A$12:$J$67,MATCH(D24,M_User!$D$12:$D$67,0),3),"UNMAPPED") -> Zefania Julius Ngoma | F24: FG004 | G24: =IFERROR(INDEX(M_SKU!$A$18:$J$57,MATCH(F24,M_SKU!$B$18:$B$57,0),1),"UNKNOWN SKU") -> Fanta Pineapple RGB 350ml | H24: CK3-33385 | I24: 0.0031459238 | N24: 46180 | O24: =IF(ISBLANK(M24),IF(TODAY()>N24,"BREACHED","PENDING"),IF(M24<=N24,"Within SLA","BREACHED")) -> BREACHED
... A26: VR-0018 | B26: ROP-0068 | C26: Shortage | D26: MOS100144 | E26: =IFERROR(INDEX(M_User!$A$12:$J$67,MATCH(D26,M_User!$D$12:$D$67,0),3),"UNMAPPED") -> Zefania Julius Ngoma | F26: FG006 | G26: =IFERROR(INDEX(M_SKU!$A$18:$J$57,MATCH(F26,M_SKU!$B$18:$B$57,0),1),"UNKNOWN SKU") -> Sprite 350ml | H26: CK3-33414 | I26: 0.002669238 | N26: 46180 | O26: =IF(ISBLANK(M26),IF(TODAY()>N26,"BREACHED","PENDING"),IF(M26<=N26,"Within SLA","BREACHED")) -> BREACHED
A27: VR-0019 | B27: ROP-0069 | C27: Excess | D27: MOS100144 | E27: =IFERROR(INDEX(M_User!$A$12:$J$67,MATCH(D27,M_User!$D$12:$D$67,0),3),"UNMAPPED") -> Zefania Julius Ngoma | F27: FG007 | G27: =IFERROR(INDEX(M_SKU!$A$18:$J$57,MATCH(F27,M_SKU!$B$18:$B$57,0),1),"UNKNOWN SKU") -> Stoney Tangawizi RGB 350ml | H27: CK3-33404 | I27: 0.0004876769 | J27: Mobile App Entry Error | K27: Salesman entered sale quantity higher than actually delivered | L27: BBL_SUP_047 | M27: 46180 | N27: 46180 | O27: =IF(ISBLANK(M27),IF(TODAY()>N27,"BREACHED","PENDING"),IF(M27<=N27,"Within SLA","BREACHED")) -> Within SLA
A28: VR-0020 | B28: ROP-0070 | C28: Excess | D28: MOS100144 | E28: =IFERROR(INDEX(M_User!$A$12:$J$67,MATCH(D28,M_User!$D$12:$D$67,0),3),"UNMAPPED") -> Zefania Julius Ngoma | F28: FG008 | G28: =IFERROR(INDEX(M_SKU!$A$18:$J$57,MATCH(F28,M_SKU!$B$18:$B$57,0),1),"UNKNOWN SKU") -> Sparletta Pinenut RGB 350ml | H28: CK3-33365 | I28: 0.0048925705 | J28: Mobile App Entry Error | K28: Salesman entered sale quantity higher than actually delivered | L28: BBL_SUP_028 | M28: 46179 | N28: 46180 | O28: =IF(ISBLANK(M28),IF(TODAY()>N28,"BREACHED","PENDING"),IF(M28<=N28,"Within SLA","BREACHED")) -> Within SLA
A29: VR-0021 | B29: ROP-0071 | C29: Excess | D29: MOS100144 | E29: =IFERROR(INDEX(M_User!$A$12:$J$67,MATCH(D29,M_User!$D$12:$D$67,0),3),"UNMAPPED") -> Zefania Julius Ngoma | F29: FG024 | G29: =IFERROR(INDEX(M_SKU!$A$18:$J$57,MATCH(F29,M_SKU!$B$18:$B$57,0),1),"UNKNOWN SKU") -> Sparletta Red Apple RGB 350ml | H29: CK3-32758 | I29: 0.0030962628 | N29: 46180 | O29: =IF(ISBLANK(M29),IF(TODAY()>N29,"BREACHED","PENDING"),IF(M29<=N29,"Within SLA","BREACHED")) -> BREACHED
A30: VR-0022 | B30: ROP-0080 | C30: Shortage | D30: MOS100180 | E30: =IFERROR(INDEX(M_User!$A$12:$J$67,MATCH(D30,M_User!$D$12:$D$67,0),3),"UNMAPPED") -> Deodat Francis Materu | F30: FG001 | G30: =IFERROR(INDEX(M_SKU!$A$18:$J$57,MATCH(F30,M_SKU!$B$18:$B$57,0),1),"UNKNOWN SKU") -> Coke RGB 350ml | H30: CK3-33409 | I30: 0.0025662856 | N30: 46180 | O30: =IF(ISBLANK(M30),IF(TODAY()>N30,"BREACHED","PENDING"),IF(M30<=N30,"Within SLA","BREACHED")) -> BREACHED
A31: VR-0023 | B31: ROP-0081 | C31: Shortage | D31: MOS100180 | E31: =IFERROR(INDEX(M_User!$A$12:$J$67,MATCH(D31,M_User!$D$12:$D$67,0),3),"UNMAPPED") -> Deodat Francis Materu | F31: FG002 | G31: =IFERROR(INDEX(M_SKU!$A$18:$J$57,MATCH(F31,M_SKU!$B$18:$B$57,0),1),"UNKNOWN SKU") -> Fanta Orange RGB 350ml | H31: CK3-33407 | I31: 0.00087388465 | N31: 46180 | O31: =IF(ISBLANK(M31),IF(TODAY()>N31,"BREACHED","PENDING"),IF(M31<=N31,"Within SLA","BREACHED")) -> BREACHED
A32: VR-0024 | B32: ROP-0082 | C32: Shortage | D32: MOS100180 | E32: =IFERROR(INDEX(M_User!$A$12:$J$67,MATCH(D32,M_User!$D$12:$D$67,0),3),"UNMAPPED") -> Deodat Francis Materu | F32: FG003 | G32: =IFERROR(INDEX(M_SKU!$A$18:$J$57,MATCH(F32,M_SKU!$B$18:$B$57,0),1),"UNKNOWN SKU") -> Fanta Passion RGB 350ml | H32: CK3-33356 | I32: 0.0030781441 | N32: 46180 | O32: =IF(ISBLANK(M32),IF(TODAY()>N32,"BREACHED","PENDING"),IF(M32<=N32,"Within SLA","BREACHED")) -> BREACHED
A33: VR-0025 | B33: ROP-0083 | C33: Shortage | D33: MOS100180 | E33: =IFERROR(INDEX(M_User!$A$12:$J$67,MATCH(D33,M_User!$D$12:$D$67,0),3),"UNMAPPED") -> Deodat Francis Materu | F33: FG004 | G33: =IFERROR(INDEX(M_SKU!$A$18:$J$57,MATCH(F33,M_SKU!$B$18:$B$57,0),1),"UNKNOWN SKU") -> Fanta Pineapple RGB 350ml | H33: CK3-33385 | I33: 0.0020751648 | J33: Mobile App Entry Error | K33: Mobile app crashed mid-entry; sales not fully captured | L33: BBL_SUP_028 | M33: 46179 | N33: 46180 | O33: =IF(ISBLANK(M33),IF(TODAY()>N33,"BREACHED","PENDING"),IF(M33<=N33,"Within SLA","BREACHED")) -> Within SLA
A34: VR-0026 | B34: ROP-0084 | C34: Excess | D34: MOS100180 | E34: =IFERROR(INDEX(M_User!$A$12:$J$67,MATCH(D34,M_User!$D$12:$D$67,0),3),"UNMAPPED") -> Deodat Francis Materu | F34: FG005 | G34: =IFERROR(INDEX(M_SKU!$A$18:$J$57,MATCH(F34,M_SKU!$B$18:$B$57,0),1),"UNKNOWN SKU") -> Fanta Fruit Blast RGB 350 ml | H34: CK3-33402 | I34: 0.0045121631 | N34: 46180 | O34: =IF(ISBLANK(M34),IF(TODAY()>N34,"BREACHED","PENDING"),IF(M34<=N34,"Within SLA","BREACHED")) -> BREACHED
A35: VR-0027 | B35: ROP-0085 | C35: Shortage | D35: MOS100180 | E35: =IFERROR(INDEX(M_User!$A$12:$J$67,MATCH(D35,M_User!$D$12:$D$67,0),3),"UNMAPPED") -> Deodat Francis Materu | F35: FG006 | G35: =IFERROR(INDEX(M_SKU!$A$18:$J$57,MATCH(F35,M_SKU!$B$18:$B$57,0),1),"UNKNOWN SKU") -> Sprite 350ml | H35: CK3-33414 | I35: 0.0013350872 | N35: 46180 | O35: =IF(ISBLANK(M35),IF(TODAY()>N35,"BREACHED","PENDING"),IF(M35<=N35,"Within SLA","BREACHED")) -> BREACHED
A36: VR-0028 | B36: ROP-0086 | C36: Excess | D36: MOS100180 | E36: =IFERROR(INDEX(M_User!$A$12:$J$67,MATCH(D36,M_User!$D$12:$D$67,0),3),"UNMAPPED") -> Deodat Francis Materu | F36: FG007 | G36: =IFERROR(INDEX(M_SKU!$A$18:$J$57,MATCH(F36,M_SKU!$B$18:$B$57,0),1),"UNKNOWN SKU") -> Stoney Tangawizi RGB 350ml | H36: CK3-33404 | I36: 0.0014881311 | N36: 46180 | O36: =IF(ISBLANK(M36),IF(TODAY()>N36,"BREACHED","PENDING"),IF(M36<=N36,"Within SLA","BREACHED")) -> BREACHED
A37: VR-0029 | B37: ROP-0087 | C37: Shortage | D37: MOS100180 | E37: =IFERROR(INDEX(M_User!$A$12:$J$67,MATCH(D37,M_User!$D$12:$D$67,0),3),"UNMAPPED") -> Deodat Francis Materu | F37: FG008 | G37: =IFERROR(INDEX(M_SKU!$A$18:$J$57,MATCH(F37,M_SKU!$B$18:$B$57,0),1),"UNKNOWN SKU") -> Sparletta Pinenut RGB 350ml | H37: CK3-33365 | I37: 0.0032481749 | N37: 46180 | O37: =IF(ISBLANK(M37),IF(TODAY()>N37,"BREACHED","PENDING"),IF(M37<=N37,"Within SLA","BREACHED")) -> BREACHED
A38: VR-0030 | B38: ROP-0088 | C38: Excess | D38: MOS100180 | E38: =IFERROR(INDEX(M_User!$A$12:$J$67,MATCH(D38,M_User!$D$12:$D$67,0),3),"UNMAPPED") -> Deodat Francis Materu | F38: FG009 | G38: =IFERROR(INDEX(M_SKU!$A$18:$J$57,MATCH(F38,M_SKU!$B$18:$B$57,0),1),"UNKNOWN SKU") -> Krest Bitter Lemon RGB 300ml | H38: CK3-33348 | I38: 0.0025480312 | N38: 46180 | O38: =IF(ISBLANK(M38),IF(TODAY()>N38,"BREACHED","PENDING"),IF(M38<=N38,"Within SLA","BREACHED")) -> BREACHED
A39: VR-0031 | B39: ROP-0089 | C39: Shortage | D39: MOS100180 | E39: =IFERROR(INDEX(M_User!$A$12:$J$67,MATCH(D39,M_User!$D$12:$D$67,0),3),"UNMAPPED") -> Deodat Francis Materu | F39: FG010 | G39: =IFERROR(INDEX(M_SKU!$A$18:$J$57,MATCH(F39,M_SKU!$B$18:$B$57,0),1),"UNKNOWN SKU") -> Krest Club Soda RGB 300ml | H39: CK3-33301 | I39: 0.0013011742 | J39: Mobile App Entry Error | K39: Mobile app crashed mid-entry; sales not fully captured | L39: BBL_SUP_086 | M39: 46179 | N39: 46180 | O39: =IF(ISBLANK(M39),IF(TODAY()>N39,"BREACHED","PENDING"),IF(M39<=N39,"Within SLA","BREACHED")) -> Within SLA
A40: VR-0032 | B40: ROP-0090 | C40: Shortage | D40: MOS100180 | E40: =IFERROR(INDEX(M_User!$A$12:$J$67,MATCH(D40,M_User!$D$12:$D$67,0),3),"UNMAPPED") -> Deodat Francis Materu | F40: FG011 | G40: =IFERROR(INDEX(M_SKU!$A$18:$J$57,MATCH(F40,M_SKU!$B$18:$B$57,0),1),"UNKNOWN SKU") -> Krest Tonic Water RGB 300ml | H40: CK3-33347 | I40: 0.00082252986 | N40: 46180 | O40: =IF(ISBLANK(M40),IF(TODAY()>N40,"BREACHED","PENDING"),IF(M40<=N40,"Within SLA","BREACHED")) -> BREACHED
A41: VR-0033 | B41: ROP-0091 | C41: Shortage | D41: MOS100180 | E41: =IFERROR(INDEX(M_User!$A$12:$J$67,MATCH(D41,M_User!$D$12:$D$67,0),3),"UNMAPPED") -> Deodat Francis Materu | F41: FG012 | G41: =IFERROR(INDEX(M_SKU!$A$18:$J$57,MATCH(F41,M_SKU!$B$18:$B$57,0),1),"UNKNOWN SKU") -> Krest Ginger Ale RGB 300ml | H41: CK3-33126 | I41: 0.0011533976 | J41: Counting Error | K41: Initial van loading count mismatched warehouse issue | L41: BBL_SUP_047 | M41: 46179 | N41: 46180 | O41: =IF(ISBLANK(M41),IF(TODAY()>N41,"BREACHED","PENDING"),IF(M41<=N41,"Within SLA","BREACHED")) -> Within SLA
A42: VR-0034 | B42: ROP-0092 | C42: Shortage | D42: MOS100180 | E42: =IFERROR(INDEX(M_User!$A$12:$J$67,MATCH(D42,M_User!$D$12:$D$67,0),3),"UNMAPPED") -> Deodat Francis Materu | F42: FG024 | G42: =IFERROR(INDEX(M_SKU!$A$18:$J$57,MATCH(F42,M_SKU!$B$18:$B$57,0),1),"UNKNOWN SKU") -> Sparletta Red Apple RGB 350ml | H42: CK3-32758 | I42: 0.0027640084 | J42: Mobile App Entry Error | K42: Mobile app crashed mid-entry; sales not fully captured | L42: BBL_SUP_057 | M42: 46180 | N42: 46180 | O42: =IF(ISBLANK(M42),IF(TODAY()>N42,"BREACHED","PENDING"),IF(M42<=N42,"Within SLA","BREACHED")) -> Within SLA
A43: VR-0035 | B43: ROP-0108 | C43: Excess | D43: MOS100200 | E43: =IFERROR(INDEX(M_User!$A$12:$J$67,MATCH(D43,M_User!$D$12:$D$67,0),3),"UNMAPPED") -> George Gibson Mmary | F43: FG001 | G43: =IFERROR(INDEX(M_SKU!$A$18:$J$57,MATCH(F43,M_SKU!$B$18:$B$57,0),1),"UNKNOWN SKU") -> Coke RGB 350ml | H43: CK3-33410 | I43: 0.0042863993 | N43: 46180 | O43: =IF(ISBLANK(M43),IF(TODAY()>N43,"BREACHED","PENDING"),IF(M43<=N43,"Within SLA","BREACHED")) -> BREACHED
A44: VR-0036 | B44: ROP-0109 | C44: Excess | D44: MOS100200 | E44: =IFERROR(INDEX(M_User!$A$12:$J$67,MATCH(D44,M_User!$D$12:$D$67,0),3),"UNMAPPED") -> George Gibson Mmary | F44: FG002 | G44: =IFERROR(INDEX(M_SKU!$A$18:$J$57,MATCH(F44,M_SKU!$B$18:$B$57,0),1),"UNKNOWN SKU") -> Fanta Orange RGB 350ml | H44: CK3-33407 | I44: 0.003106758 | N44: 46180 | O44: =IF(ISBLANK(M44),IF(TODAY()>N44,"BREACHED","PENDING"),IF(M44<=N44,"Within SLA","BREACHED")) -> BREACHED
A45: VR-0037 | B45: ROP-0110 | C45: Shortage | D45: MOS100200 | E45: =IFERROR(INDEX(M_User!$A$12:$J$67,MATCH(D45,M_User!$D$12:$D$67,0),3),"UNMAPPED") -> George Gibson Mmary | F45: FG003 | G45: =IFERROR(INDEX(M_SKU!$A$18:$J$57,MATCH(F45,M_SKU!$B$18:$B$57,0),1),"UNKNOWN SKU") -> Fanta Passion RGB 350ml | H45: CK3-33356 | I45: 0.0042364434 | J45: Theft / Loss | K45: Van left unattended briefly; quantity reported missing | L45: BBL_SUP_056 | M45: 46179 | N45: 46180 | O45: =IF(ISBLANK(M45),IF(TODAY()>N45,"BREACHED","PENDING"),IF(M45<=N45,"Within SLA","BREACHED")) -> Within SLA
A46: VR-0038 | B46: ROP-0111 | C46: Shortage | D46: MOS100200 | E46: =IFERROR(INDEX(M_User!$A$12:$J$67,MATCH(D46,M_User!$D$12:$D$67,0),3),"UNMAPPED") -> George Gibson Mmary | F46: FG004 | G46: =IFERROR(INDEX(M_SKU!$A$18:$J$57,MATCH(F46,M_SKU!$B$18:$B$57,0),1),"UNKNOWN SKU") -> Fanta Pineapple RGB 350ml | H46: CK3-33385 | I46: 0.00047636439 | N46: 46180 | O46: =IF(ISBLANK(M46),IF(TODAY()>N46,"BREACHED","PENDING"),IF(M46<=N46,"Within SLA","BREACHED")) -> BREACHED
A47: VR-0039 | B47: ROP-0112 | C47: Shortage | D47: MOS100200 | E47: =IFERROR(INDEX(M_User!$A$12:$J$67,MATCH(D47,M_User!$D$12:$D$67,0),3),"UNMAPPED") -> George Gibson Mmary | F47: FG005 | G47: =IFERROR(INDEX(M_SKU!$A$18:$J$57,MATCH(F47,M_SKU!$B$18:$B$57,0),1),"UNKNOWN SKU") -> Fanta Fruit Blast RGB 350 ml | H47: CK3-33402 | I47: 0.0022880739 | J47: Damage / Breakage | K47: Broken bottles found in van during physical count | L47: BBL_SUP_057 | M47: 46179 | N47: 46180 | O47: =IF(ISBLANK(M47),IF(TODAY()>N47,"BREACHED","PENDING"),IF(M47<=N47,"Within SLA","BREACHED")) -> Within SLA
A48: VR-0040 | B48: ROP-0113 | C48: Excess | D48: MOS100200 | E48: =IFERROR(INDEX(M_User!$A$12:$J$67,MATCH(D48,M_User!$D$12:$D$67,0),3),"UNMAPPED") -> George Gibson Mmary | F48: FG006 | G48: =IFERROR(INDEX(M_SKU!$A$18:$J$57,MATCH(F48,M_SKU!$B$18:$B$57,0),1),"UNKNOWN SKU") -> Sprite 350ml | H48: CK3-33414 | I48: 0.0049151848 | J48: Mobile App Entry Error | K48: Outlet code mistake led to over-recording on mobile | L48: BBL_SUP_046 | M48: 46179 | N48: 46180 | O48: =IF(ISBLANK(M48),IF(TODAY()>N48,"BREACHED","PENDING"),IF(M48<=N48,"Within SLA","BREACHED")) -> Within SLA
A49: VR-0041 | B49: ROP-0114 | C49: Shortage | D49: MOS100200 | E49: =IFERROR(INDEX(M_User!$A$12:$J$67,MATCH(D49,M_User!$D$12:$D$67,0),3),"UNMAPPED") -> George Gibson Mmary | F49: FG007 | G49: =IFERROR(INDEX(M_SKU!$A$18:$J$57,MATCH(F49,M_SKU!$B$18:$B$57,0),1),"UNKNOWN SKU") -> Stoney Tangawizi RGB 350ml | H49: CK3-33404 | I49: 0.0017259118 | N49: 46180 | O49: =IF(ISBLANK(M49),IF(TODAY()>N49,"BREACHED","PENDING"),IF(M49<=N49,"Within SLA","BREACHED")) -> BREACHED
A50: VR-0042 | B50: ROP-0115 | C50: Shortage | D50: MOS100200 | E50: =IFERROR(INDEX(M_User!$A$12:$J$67,MATCH(D50,M_User!$D$12:$D$67,0),3),"UNMAPPED") -> George Gibson Mmary | F50: FG008 | G50: =IFERROR(INDEX(M_SKU!$A$18:$J$57,MATCH(F50,M_SKU!$B$18:$B$57,0),1),"UNKNOWN SKU") -> Sparletta Pinenut RGB 350ml | H50: CK3-33365 | I50: 0.0011483328 | J50: Damage / Breakage | K50: Crate fell during loading; multiple breakages | L50: BBL_SUP_086 | M50: 46179 | N50: 46180 | O50: =IF(ISBLANK(M50),IF(TODAY()>N50,"BREACHED","PENDING"),IF(M50<=N50,"Within SLA","BREACHED")) -> Within SLA
A51: VR-0043 | B51: ROP-0116 | C51: Shortage | D51: MOS100200 | E51: =IFERROR(INDEX(M_User!$A$12:$J$67,MATCH(D51,M_User!$D$12:$D$67,0),3),"UNMAPPED") -> George Gibson Mmary | F51: FG009 | G51: =IFERROR(INDEX(M_SKU!$A$18:$J$57,MATCH(F51,M_SKU!$B$18:$B$57,0),1),"UNKNOWN SKU") -> Krest Bitter Lemon RGB 300ml | H51: CK3-33348 | I51: 0.00049887161 | N51: 46180 | O51: =IF(ISBLANK(M51),IF(TODAY()>N51,"BREACHED","PENDING"),IF(M51<=N51,"Within SLA","BREACHED")) -> BREACHED
A52: VR-0044 | B52: ROP-0118 | C52: Excess | D52: MOS100200 | E52: =IFERROR(INDEX(M_User!$A$12:$J$67,MATCH(D52,M_User!$D$12:$D$67,0),3),"UNMAPPED") -> George Gibson Mmary | F52: FG011 | G52: =IFERROR(INDEX(M_SKU!$A$18:$J$57,MATCH(F52,M_SKU!$B$18:$B$57,0),1),"UNKNOWN SKU") -> Krest Tonic Water RGB 300ml | H52: CK3-33347 | I52: 0.0019498115 | J52: Mobile App Entry Error | K52: Double-entry mistake: same sale recorded twice on mobile | L52: BBL_SUP_079 | M52: 46179 | N52: 46180 | O52: =IF(ISBLANK(M52),IF(TODAY()>N52,"BREACHED","PENDING"),IF(M52<=N52,"Within SLA","BREACHED")) -> Within SLA
A53: VR-0045 | B53: ROP-0119 | C53: Excess | D53: MOS100200 | E53: =IFERROR(INDEX(M_User!$A$12:$J$67,MATCH(D53,M_User!$D$12:$D$67,0),3),"UNMAPPED") -> George Gibson Mmary | F53: FG012 | G53: =IFERROR(INDEX(M_SKU!$A$18:$J$57,MATCH(F53,M_SKU!$B$18:$B$57,0),1),"UNKNOWN SKU") -> Krest Ginger Ale RGB 300ml | H53: CK3-33126 | I53: 0.00060045979 | N53: 46180 | O53: =IF(ISBLANK(M53),IF(TODAY()>N53,"BREACHED","PENDING"),IF(M53<=N53,"Within SLA","BREACHED")) -> BREACHED
A54: VR-0046 | B54: ROP-0120 | C54: Shortage | D54: MOS100200 | E54: =IFERROR(INDEX(M_User!$A$12:$J$67,MATCH(D54,M_User!$D$12:$D$67,0),3),"UNMAPPED") -> George Gibson Mmary | F54: FG024 | G54: =IFERROR(INDEX(M_SKU!$A$18:$J$57,MATCH(F54,M_SKU!$B$18:$B$57,0),1),"UNKNOWN SKU") -> Sparletta Red Apple RGB 350ml | H54: CK3-32758 | I54: 0.00187585 | J54: Counting Error | K54: Stock layered incorrectly; missed during count | L54: BBL_SUP_086 | M54: 46179 | N54: 46180 | O54: =IF(ISBLANK(M54),IF(TODAY()>N54,"BREACHED","PENDING"),IF(M54<=N54,"Within SLA","BREACHED")) -> Within SLA
A55: VR-0047 | B55: ROP-0131 | C55: Excess | D55: MOS100209 | E55: =IFERROR(INDEX(M_User!$A$12:$J$67,MATCH(D55,M_User!$D$12:$D$67,0),3),"UNMAPPED") -> Erick K. Mkama | F55: FG001 | G55: =IFERROR(INDEX(M_SKU!$A$18:$J$57,MATCH(F55,M_SKU!$B$18:$B$57,0),1),"UNKNOWN SKU") -> Coke RGB 350ml | H55: CK3-33409 | I55: 0.00014803382 | N55: 46180 | O55: =IF(ISBLANK(M55),IF(TODAY()>N55,"BREACHED","PENDING"),IF(M55<=N55,"Within SLA","BREACHED")) -> BREACHED
A56: VR-0048 | B56: ROP-0132 | C56: Shortage | D56: MOS100209 | E56: =IFERROR(INDEX(M_User!$A$12:$J$67,MATCH(D56,M_User!$D$12:$D$67,0),3),"UNMAPPED") -> Erick K. Mkama | F56: FG002 | G56: =IFERROR(INDEX(M_SKU!$A$18:$J$57,MATCH(F56,M_SKU!$B$18:$B$57,0),1),"UNKNOWN SKU") -> Fanta Orange RGB 350ml | H56: CK3-33407 | I56: 0.0010213285 | N56: 46180 | O56: =IF(ISBLANK(M56),IF(TODAY()>N56,"BREACHED","PENDING"),IF(M56<=N56,"Within SLA","BREACHED")) -> BREACHED
A57: VR-0049 | B57: ROP-0133 | C57: Shortage | D57: MOS100209 | E57: =IFERROR(INDEX(M_User!$A$12:$J$67,MATCH(D57,M_User!$D$12:$D$67,0),3),"UNMAPPED") -> Erick K. Mkama | F57: FG003 | G57: =IFERROR(INDEX(M_SKU!$A$18:$J$57,MATCH(F57,M_SKU!$B$18:$B$57,0),1),"UNKNOWN SKU") -> Fanta Passion RGB 350ml | H57: CK3-33356 | I57: 0.00019391515 | N57: 46180 | O57: =IF(ISBLANK(M57),IF(TODAY()>N57,"BREACHED","PENDING"),IF(M57<=N57,"Within SLA","BREACHED")) -> BREACHED
A58: VR-0050 | B58: ROP-0134 | C58: Excess | D58: MOS100209 | E58: =IFERROR(INDEX(M_User!$A$12:$J$67,MATCH(D58,M_User!$D$12:$D$67,0),3),"UNMAPPED") -> Erick K. Mkama | F58: FG004 | G58: =IFERROR(INDEX(M_SKU!$A$18:$J$57,MATCH(F58,M_SKU!$B$18:$B$57,0),1),"UNKNOWN SKU") -> Fanta Pineapple RGB 350ml | H58: CK3-33385 | I58: 0.0032745249 | N58: 46180 | O58: =IF(ISBLANK(M58),IF(TODAY()>N58,"BREACHED","PENDING"),IF(M58<=N58,"Within SLA","BREACHED")) -> BREACHED
A59: VR-0051 | B59: ROP-0135 | C59: Excess | D59: MOS100209 | E59: =IFERROR(INDEX(M_User!$A$12:$J$67,MATCH(D59,M_User!$D$12:$D$67,0),3),"UNMAPPED") -> Erick K. Mkama | F59: FG005 | G59: =IFERROR(INDEX(M_SKU!$A$18:$J$57,MATCH(F59,M_SKU!$B$18:$B$57,0),1),"UNKNOWN SKU") -> Fanta Fruit Blast RGB 350 ml | H59: CK3-33402 | I59: 0.00092843222 | J59: Counting Error | K59: Salesman included anticipated return as a sale | L59: BBL_SUP_079 | M59: 46179 | N59: 46180 | O59: =IF(ISBLANK(M59),IF(TODAY()>N59,"BREACHED","PENDING"),IF(M59<=N59,"Within SLA","BREACHED")) -> Within SLA
A60: VR-0052 | B60: ROP-0136 | C60: Shortage | D60: MOS100209 | E60: =IFERROR(INDEX(M_User!$A$12:$J$67,MATCH(D60,M_User!$D$12:$D$67,0),3),"UNMAPPED") -> Erick K. Mkama | F60: FG006 | G60: =IFERROR(INDEX(M_SKU!$A$18:$J$57,MATCH(F60,M_SKU!$B$18:$B$57,0),1),"UNKNOWN SKU") -> Sprite 350ml | H60: CK3-33414 | I60: 0.0017093329 | N60: 46180 | O60: =IF(ISBLANK(M60),IF(TODAY()>N60,"BREACHED","PENDING"),IF(M60<=N60,"Within SLA","BREACHED")) -> BREACHED
A61: VR-0053 | B61: ROP-0137 | C61: Excess | D61: MOS100209 | E61: =IFERROR(INDEX(M_User!$A$12:$J$67,MATCH(D61,M_User!$D$12:$D$67,0),3),"UNMAPPED") -> Erick K. Mkama | F61: FG007 | G61: =IFERROR(INDEX(M_SKU!$A$18:$J$57,MATCH(F61,M_SKU!$B$18:$B$57,0),1),"UNKNOWN SKU") -> Stoney Tangawizi RGB 350ml | H61: CK3-33404 | I61: 0.0023825643 | J61: Mobile App Entry Error | K61: Outlet code mistake led to over-recording on mobile | L61: BBL_SUP_057 | M61: 46179 | N61: 46180 | O61: =IF(ISBLANK(M61),IF(TODAY()>N61,"BREACHED","PENDING"),IF(M61<=N61,"Within SLA","BREACHED")) -> Within SLA
A62: VR-0054 | B62: ROP-0138 | C62: Excess | D62: MOS100209 | E62: =IFERROR(INDEX(M_User!$A$12:$J$67,MATCH(D62,M_User!$D$12:$D$67,0),3),"UNMAPPED") -> Erick K. Mkama | F62: FG008 | G62: =IFERROR(INDEX(M_SKU!$A$18:$J$57,MATCH(F62,M_SKU!$B$18:$B$57,0),1),"UNKNOWN SKU") -> Sparletta Pinenut RGB 350ml | H62: CK3-33367 | I62: 0.0024788416 | N62: 46180 | O62: =IF(ISBLANK(M62),IF(TODAY()>N62,"BREACHED","PENDING"),IF(M62<=N62,"Within SLA","BREACHED")) -> BREACHED
A63: VR-0055 | B63: ROP-0139 | C63: Shortage | D63: MOS100209 | E63: =IFERROR(INDEX(M_User!$A$12:$J$67,MATCH(D63,M_User!$D$12:$D$67,0),3),"UNMAPPED") -> Erick K. Mkama | F63: FG009 | G63: =IFERROR(INDEX(M_SKU!$A$18:$J$57,MATCH(F63,M_SKU!$B$18:$B$57,0),1),"UNKNOWN SKU") -> Krest Bitter Lemon RGB 300ml | H63: CK3-33348 | I63: 0.0026164212 | N63: 46180 | O63: =IF(ISBLANK(M63),IF(TODAY()>N63,"BREACHED","PENDING"),IF(M63<=N63,"Within SLA","BREACHED")) -> BREACHED
A64: VR-0056 | B64: ROP-0140 | C64: Shortage | D64: MOS100209 | E64: =IFERROR(INDEX(M_User!$A$12:$J$67,MATCH(D64,M_User!$D$12:$D$67,0),3),"UNMAPPED") -> Erick K. Mkama | F64: FG010 | G64: =IFERROR(INDEX(M_SKU!$A$18:$J$57,MATCH(F64,M_SKU!$B$18:$B$57,0),1),"UNKNOWN SKU") -> Krest Club Soda RGB 300ml | H64: CK3-33301 | I64: 0.0032692604 | N64: 46180 | O64: =IF(ISBLANK(M64),IF(TODAY()>N64,"BREACHED","PENDING"),IF(M64<=N64,"Within SLA","BREACHED")) -> BREACHED
A65: VR-0057 | B65: ROP-0141 | C65: Shortage | D65: MOS100209 | E65: =IFERROR(INDEX(M_User!$A$12:$J$67,MATCH(D65,M_User!$D$12:$D$67,0),3),"UNMAPPED") -> Erick K. Mkama | F65: FG011 | G65: =IFERROR(INDEX(M_SKU!$A$18:$J$57,MATCH(F65,M_SKU!$B$18:$B$57,0),1),"UNKNOWN SKU") -> Krest Tonic Water RGB 300ml | H65: CK3-33347 | I65: 0.001379163 | J65: Mobile App Entry Error | K65: Salesman entered sales but missed an outlet visit on mobile | L65: BBL_SUP_046 | M65: 46179 | N65: 46180 | O65: =IF(ISBLANK(M65),IF(TODAY()>N65,"BREACHED","PENDING"),IF(M65<=N65,"Within SLA","BREACHED")) -> Within SLA
A66: VR-0058 | B66: ROP-0142 | C66: Excess | D66: MOS100209 | E66: =IFERROR(INDEX(M_User!$A$12:$J$67,MATCH(D66,M_User!$D$12:$D$67,0),3),"UNMAPPED") -> Erick K. Mkama | F66: FG012 | G66: =IFERROR(INDEX(M_SKU!$A$18:$J$57,MATCH(F66,M_SKU!$B$18:$B$57,0),1),"UNKNOWN SKU") -> Krest Ginger Ale RGB 300ml | H66: CK3-33126 | I66: 0.0011238368 | J66: Mobile App Entry Error | K66: Wrong quantity multiplier applied (e.g. selected dozen instead of singles) | L66: BBL_SUP_057 | M66: 46179 | N66: 46180 | O66: =IF(ISBLANK(M66),IF(TODAY()>N66,"BREACHED","PENDING"),IF(M66<=N66,"Within SLA","BREACHED")) -> Within SLA
A67: VR-0059 | B67: ROP-0143 | C67: Excess | D67: MOS100209 | E67: =IFERROR(INDEX(M_User!$A$12:$J$67,MATCH(D67,M_User!$D$12:$D$67,0),3),"UNMAPPED") -> Erick K. Mkama | F67: FG024 | G67: =IFERROR(INDEX(M_SKU!$A$18:$J$57,MATCH(F67,M_SKU!$B$18:$B$57,0),1),"UNKNOWN SKU") -> Sparletta Red Apple RGB 350ml | H67: CK3-32758 | I67: 0.0018840495 | N67: 46180 | O67: =IF(ISBLANK(M67),IF(TODAY()>N67,"BREACHED","PENDING"),IF(M67<=N67,"Within SLA","BREACHED")) -> BREACHED
A68: VR-0060 | B68: ROP-0157 | C68: Excess | D68: MOS100501 | E68: =IFERROR(INDEX(M_User!$A$12:$J$67,MATCH(D68,M_User!$D$12:$D$67,0),3),"UNMAPPED") -> Jonas Steven Michael | F68: FG001 | G68: =IFERROR(INDEX(M_SKU!$A$18:$J$57,MATCH(F68,M_SKU!$B$18:$B$57,0),1),"UNKNOWN SKU") -> Coke RGB 350ml | H68: CK3-33409 | I68: 0.004464825 | N68: 46180 | O68: =IF(ISBLANK(M68),IF(TODAY()>N68,"BREACHED","PENDING"),IF(M68<=N68,"Within SLA","BREACHED")) -> BREACHED
A69: VR-0061 | B69: ROP-0158 | C69: Excess | D69: MOS100501 | E69: =IFERROR(INDEX(M_User!$A$12:$J$67,MATCH(D69,M_User!$D$12:$D$67,0),3),"UNMAPPED") -> Jonas Steven Michael | F69: FG002 | G69: =IFERROR(INDEX(M_SKU!$A$18:$J$57,MATCH(F69,M_SKU!$B$18:$B$57,0),1),"UNKNOWN SKU") -> Fanta Orange RGB 350ml | H69: CK3-33407 | I69: 0.0009264551 | J69: Mobile App Entry Error | K69: Salesman entered sale quantity higher than actually delivered | L69: BBL_SUP_086 | M69: 46180 | N69: 46180 | O69: =IF(ISBLANK(M69),IF(TODAY()>N69,"BREACHED","PENDING"),IF(M69<=N69,"Within SLA","BREACHED")) -> Within SLA
A70: VR-0062 | B70: ROP-0159 | C70: Excess | D70: MOS100501 | E70: =IFERROR(INDEX(M_User!$A$12:$J$67,MATCH(D70,M_User!$D$12:$D$67,0),3),"UNMAPPED") -> Jonas Steven Michael | F70: FG003 | G70: =IFERROR(INDEX(M_SKU!$A$18:$J$57,MATCH(F70,M_SKU!$B$18:$B$57,0),1),"UNKNOWN SKU") -> Fanta Passion RGB 350ml | H70: CK3-33356 | I70: 0.004769584 | N70: 46180 | O70: =IF(ISBLANK(M70),IF(TODAY()>N70,"BREACHED","PENDING"),IF(M70<=N70,"Within SLA","BREACHED")) -> BREACHED
A71: VR-0063 | B71: ROP-0160 | C71: Excess | D71: MOS100501 | E71: =IFERROR(INDEX(M_User!$A$12:$J$67,MATCH(D71,M_User!$D$12:$D$67,0),3),"UNMAPPED") -> Jonas Steven Michael | F71: FG004 | G71: =IFERROR(INDEX(M_SKU!$A$18:$J$57,MATCH(F71,M_SKU!$B$18:$B$57,0),1),"UNKNOWN SKU") -> Fanta Pineapple RGB 350ml | H71: CK3-33385 | I71: 0.0036840183 | J71: Mobile App Entry Error | K71: Double-entry mistake: same sale recorded twice on mobile | L71: BBL_SUP_047 | M71: 46180 | N71: 46180 | O71: =IF(ISBLANK(M71),IF(TODAY()>N71,"BREACHED","PENDING"),IF(M71<=N71,"Within SLA","BREACHED")) -> Within SLA
A72: VR-0064 | B72: ROP-0161 | C72: Excess | D72: MOS100501 | E72: =IFERROR(INDEX(M_User!$A$12:$J$67,MATCH(D72,M_User!$D$12:$D$67,0),3),"UNMAPPED") -> Jonas Steven Michael | F72: FG005 | G72: =IFERROR(INDEX(M_SKU!$A$18:$J$57,MATCH(F72,M_SKU!$B$18:$B$57,0),1),"UNKNOWN SKU") -> Fanta Fruit Blast RGB 350 ml | H72: CK3-33402 | I72: 0.0044481596 | N72: 46180 | O72: =IF(ISBLANK(M72),IF(TODAY()>N72,"BREACHED","PENDING"),IF(M72<=N72,"Within SLA","BREACHED")) -> BREACHED
A73: VR-0065 | B73: ROP-0162 | C73: Excess | D73: MOS100501 | E73: =IFERROR(INDEX(M_User!$A$12:$J$67,MATCH(D73,M_User!$D$12:$D$67,0),3),"UNMAPPED") -> Jonas Steven Michael | F73: FG006 | G73: =IFERROR(INDEX(M_SKU!$A$18:$J$57,MATCH(F73,M_SKU!$B$18:$B$57,0),1),"UNKNOWN SKU") -> Sprite 350ml | H73: CK3-33414 | I73: 0.003706288 | N73: 46180 | O73: =IF(ISBLANK(M73),IF(TODAY()>N73,"BREACHED","PENDING"),IF(M73<=N73,"Within SLA","BREACHED")) -> BREACHED
A74: VR-0066 | B74: ROP-0163 | C74: Excess | D74: MOS100501 | E74: =IFERROR(INDEX(M_User!$A$12:$J$67,MATCH(D74,M_User!$D$12:$D$67,0),3),"UNMAPPED") -> Jonas Steven Michael | F74: FG007 | G74: =IFERROR(INDEX(M_SKU!$A$18:$J$57,MATCH(F74,M_SKU!$B$18:$B$57,0),1),"UNKNOWN SKU") -> Stoney Tangawizi RGB 350ml | H74: CK3-33404 | I74: 0.0022508577 | J74: Counting Error | K74: Mobile entry over-stated; actual physical stock higher than recorded | L74: BBL_SUP_057 | M74: 46179 | N74: 46180 | O74: =IF(ISBLANK(M74),IF(TODAY()>N74,"BREACHED","PENDING"),IF(M74<=N74,"Within SLA","BREACHED")) -> Within SLA
A75: VR-0067 | B75: ROP-0164 | C75: Shortage | D75: MOS100501 | E75: =IFERROR(INDEX(M_User!$A$12:$J$67,MATCH(D75,M_User!$D$12:$D$67,0),3),"UNMAPPED") -> Jonas Steven Michael | F75: FG008 | G75: =IFERROR(INDEX(M_SKU!$A$18:$J$57,MATCH(F75,M_SKU!$B$18:$B$57,0),1),"UNKNOWN SKU") -> Sparletta Pinenut RGB 350ml | H75: CK3-33365 | I75: 0.0042466684 | N75: 46180 | O75: =IF(ISBLANK(M75),IF(TODAY()>N75,"BREACHED","PENDING"),IF(M75<=N75,"Within SLA","BREACHED")) -> BREACHED
A76: VR-0068 | B76: ROP-0165 | C76: Excess | D76: MOS100501 | E76: =IFERROR(INDEX(M_User!$A$12:$J$67,MATCH(D76,M_User!$D$12:$D$67,0),3),"UNMAPPED") -> Jonas Steven Michael | F76: FG009 | G76: =IFERROR(INDEX(M_SKU!$A$18:$J$57,MATCH(F76,M_SKU!$B$18:$B$57,0),1),"UNKNOWN SKU") -> Krest Bitter Lemon RGB 300ml | H76: CK3-33348 | I76: 0.0025009864 | N76: 46180 | O76: =IF(ISBLANK(M76),IF(TODAY()>N76,"BREACHED","PENDING"),IF(M76<=N76,"Within SLA","BREACHED")) -> BREACHED
A77: VR-0069 | B77: ROP-0166 | C77: Excess | D77: MOS100501 | E77: =IFERROR(INDEX(M_User!$A$12:$J$67,MATCH(D77,M_User!$D$12:$D$67,0),3),"UNMAPPED") -> Jonas Steven Michael | F77: FG010 | G77: =IFERROR(INDEX(M_SKU!$A$18:$J$57,MATCH(F77,M_SKU!$B$18:$B$57,0),1),"UNKNOWN SKU") -> Krest Club Soda RGB 300ml | H77: CK3-33301 | I77: 0.0027717467 | N77: 46180 | O77: =IF(ISBLANK(M77),IF(TODAY()>N77,"BREACHED","PENDING"),IF(M77<=N77,"Within SLA","BREACHED")) -> BREACHED
A78: VR-0070 | B78: ROP-0167 | C78: Excess | D78: MOS100501 | E78: =IFERROR(INDEX(M_User!$A$12:$J$67,MATCH(D78,M_User!$D$12:$D$67,0),3),"UNMAPPED") -> Jonas Steven Michael | F78: FG011 | G78: =IFERROR(INDEX(M_SKU!$A$18:$J$57,MATCH(F78,M_SKU!$B$18:$B$57,0),1),"UNKNOWN SKU") -> Krest Tonic Water RGB 300ml | H78: CK3-33347 | I78: 0.0018918214 | N78: 46180 | O78: =IF(ISBLANK(M78),IF(TODAY()>N78,"BREACHED","PENDING"),IF(M78<=N78,"Within SLA","BREACHED")) -> BREACHED
A79: VR-0071 | B79: ROP-0168 | C79: Excess | D79: MOS100501 | E79: =IFERROR(INDEX(M_User!$A$12:$J$67,MATCH(D79,M_User!$D$12:$D$67,0),3),"UNMAPPED") -> Jonas Steven Michael | F79: FG012 | G79: =IFERROR(INDEX(M_SKU!$A$18:$J$57,MATCH(F79,M_SKU!$B$18:$B$57,0),1),"UNKNOWN SKU") -> Krest Ginger Ale RGB 300ml | H79: CK3-33126 | I79: 0.0010228768 | N79: 46180 | O79: =IF(ISBLANK(M79),IF(TODAY()>N79,"BREACHED","PENDING"),IF(M79<=N79,"Within SLA","BREACHED")) -> BREACHED
A80: VR-0072 | B80: ROP-0169 | C80: Excess | D80: MOS100501 | E80: =IFERROR(INDEX(M_User!$A$12:$J$67,MATCH(D80,M_User!$D$12:$D$67,0),3),"UNMAPPED") -> Jonas Steven Michael | F80: FG024 | G80: =IFERROR(INDEX(M_SKU!$A$18:$J$57,MATCH(F80,M_SKU!$B$18:$B$57,0),1),"UNKNOWN SKU") -> Sparletta Red Apple RGB 350ml | H80: CK3-32758 | I80: 0.0011873634 | N80: 46180 | O80: =IF(ISBLANK(M80),IF(TODAY()>N80,"BREACHED","PENDING"),IF(M80<=N80,"Within SLA","BREACHED")) -> BREACHED
A81: VR-0073 | B81: ROP-0182 | C81: Shortage | D81: MOS100624 | E81: =IFERROR(INDEX(M_User!$A$12:$J$67,MATCH(D81,M_User!$D$12:$D$67,0),3),"UNMAPPED") -> Gastory S Msaki | F81: FG001 | G81: =IFERROR(INDEX(M_SKU!$A$18:$J$57,MATCH(F81,M_SKU!$B$18:$B$57,0),1),"UNKNOWN SKU") -> Coke RGB 350ml | H81: CK3-33409 | I81: 0.0035482308 | N81: 46180 | O81: =IF(ISBLANK(M81),IF(TODAY()>N81,"BREACHED","PENDING"),IF(M81<=N81,"Within SLA","BREACHED")) -> BREACHED
A82: VR-0074 | B82: ROP-0183 | C82: Excess | D82: MOS100624 | E82: =IFERROR(INDEX(M_User!$A$12:$J$67,MATCH(D82,M_User!$D$12:$D$67,0),3),"UNMAPPED") -> Gastory S Msaki | F82: FG002 | G82: =IFERROR(INDEX(M_SKU!$A$18:$J$57,MATCH(F82,M_SKU!$B$18:$B$57,0),1),"UNKNOWN SKU") -> Fanta Orange RGB 350ml | H82: CK3-33407 | I82: 0.0002482518 | J82: Counting Error | K82: Salesman included anticipated return as a sale | L82: BBL_SUP_028 | M82: 46179 | N82: 46180 | O82: =IF(ISBLANK(M82),IF(TODAY()>N82,"BREACHED","PENDING"),IF(M82<=N82,"Within SLA","BREACHED")) -> Within SLA
A83: VR-0075 | B83: ROP-0184 | C83: Excess | D83: MOS100624 | E83: =IFERROR(INDEX(M_User!$A$12:$J$67,MATCH(D83,M_User!$D$12:$D$67,0),3),"UNMAPPED") -> Gastory S Msaki | F83: FG003 | G83: =IFERROR(INDEX(M_SKU!$A$18:$J$57,MATCH(F83,M_SKU!$B$18:$B$57,0),1),"UNKNOWN SKU") -> Fanta Passion RGB 350ml | H83: CK3-33356 | I83: 0.0012658412 | N83: 46180 | O83: =IF(ISBLANK(M83),IF(TODAY()>N83,"BREACHED","PENDING"),IF(M83<=N83,"Within SLA","BREACHED")) -> BREACHED
A84: VR-0076 | B84: ROP-0185 | C84: Shortage | D84: MOS100624 | E84: =IFERROR(INDEX(M_User!$A$12:$J$67,MATCH(D84,M_User!$D$12:$D$67,0),3),"UNMAPPED") -> Gastory S Msaki | F84: FG004 | G84: =IFERROR(INDEX(M_SKU!$A$18:$J$57,MATCH(F84,M_SKU!$B$18:$B$57,0),1),"UNKNOWN SKU") -> Fanta Pineapple RGB 350ml | H84: CK3-33385 | I84: 0.00084137365 | N84: 46180 | O84: =IF(ISBLANK(M84),IF(TODAY()>N84,"BREACHED","PENDING"),IF(M84<=N84,"Within SLA","BREACHED")) -> BREACHED
A85: VR-0077 | B85: ROP-0186 | C85: Excess | D85: MOS100624 | E85: =IFERROR(INDEX(M_User!$A$12:$J$67,MATCH(D85,M_User!$D$12:$D$67,0),3),"UNMAPPED") -> Gastory S Msaki | F85: FG005 | G85: =IFERROR(INDEX(M_SKU!$A$18:$J$57,MATCH(F85,M_SKU!$B$18:$B$57,0),1),"UNKNOWN SKU") -> Fanta Fruit Blast RGB 350 ml | H85: CK3-33402 | I85: 0.0013428957 | N85: 46180 | O85: =IF(ISBLANK(M85),IF(TODAY()>N85,"BREACHED","PENDING"),IF(M85<=N85,"Within SLA","BREACHED")) -> BREACHED
A86: VR-0078 | B86: ROP-0187 | C86: Shortage | D86: MOS100624 | E86: =IFERROR(INDEX(M_User!$A$12:$J$67,MATCH(D86,M_User!$D$12:$D$67,0),3),"UNMAPPED") -> Gastory S Msaki | F86: FG006 | G86: =IFERROR(INDEX(M_SKU!$A$18:$J$57,MATCH(F86,M_SKU!$B$18:$B$57,0),1),"UNKNOWN SKU") -> Sprite 350ml | H86: CK3-33414 | I86: 0.002642793 | N86: 46180 | O86: =IF(ISBLANK(M86),IF(TODAY()>N86,"BREACHED","PENDING"),IF(M86<=N86,"Within SLA","BREACHED")) -> BREACHED
A87: VR-0079 | B87: ROP-0188 | C87: Shortage | D87: MOS100624 | E87: =IFERROR(INDEX(M_User!$A$12:$J$67,MATCH(D87,M_User!$D$12:$D$67,0),3),"UNMAPPED") -> Gastory S Msaki | F87: FG007 | G87: =IFERROR(INDEX(M_SKU!$A$18:$J$57,MATCH(F87,M_SKU!$B$18:$B$57,0),1),"UNKNOWN SKU") -> Stoney Tangawizi RGB 350ml | H87: CK3-33404 | I87: 0.0019028097 | J87: Damage / Breakage | K87: Crate fell during loading; multiple breakages | L87: BBL_SUP_086 | M87: 46179 | N87: 46180 | O87: =IF(ISBLANK(M87),IF(TODAY()>N87,"BREACHED","PENDING"),IF(M87<=N87,"Within SLA","BREACHED")) -> Within SLA
A88: VR-0080 | B88: ROP-0189 | C88: Excess | D88: MOS100624 | E88: =IFERROR(INDEX(M_User!$A$12:$J$67,MATCH(D88,M_User!$D$12:$D$67,0),3),"UNMAPPED") -> Gastory S Msaki | F88: FG008 | G88: =IFERROR(INDEX(M_SKU!$A$18:$J$57,MATCH(F88,M_SKU!$B$18:$B$57,0),1),"UNKNOWN SKU") -> Sparletta Pinenut RGB 350ml | H88: CK3-33365 | I88: 0.0035906543 | N88: 46180 | O88: =IF(ISBLANK(M88),IF(TODAY()>N88,"BREACHED","PENDING"),IF(M88<=N88,"Within SLA","BREACHED")) -> BREACHED
A89: VR-0081 | B89: ROP-0190 | C89: Excess | D89: MOS100624 | E89: =IFERROR(INDEX(M_User!$A$12:$J$67,MATCH(D89,M_User!$D$12:$D$67,0),3),"UNMAPPED") -> Gastory S Msaki | F89: FG009 | G89: =IFERROR(INDEX(M_SKU!$A$18:$J$57,MATCH(F89,M_SKU!$B$18:$B$57,0),1),"UNKNOWN SKU") -> Krest Bitter Lemon RGB 300ml | H89: CK3-33348 | I89: 0.0018784128 | N89: 46180 | O89: =IF(ISBLANK(M89),IF(TODAY()>N89,"BREACHED","PENDING"),IF(M89<=N89,"Within SLA","BREACHED")) -> BREACHED
A90: VR-0082 | B90: ROP-0191 | C90: Shortage | D90: MOS100624 | E90: =IFERROR(INDEX(M_User!$A$12:$J$67,MATCH(D90,M_User!$D$12:$D$67,0),3),"UNMAPPED") -> Gastory S Msaki | F90: FG010 | G90: =IFERROR(INDEX(M_SKU!$A$18:$J$57,MATCH(F90,M_SKU!$B$18:$B$57,0),1),"UNKNOWN SKU") -> Krest Club Soda RGB 300ml | H90: CK3-33301 | I90: 0.0015700727 | J90: Counting Error | K90: Initial van loading count mismatched warehouse issue | L90: BBL_SUP_079 | M90: 46180 | N90: 46180 | O90: =IF(ISBLANK(M90),IF(TODAY()>N90,"BREACHED","PENDING"),IF(M90<=N90,"Within SLA","BREACHED")) -> Within SLA
A91: VR-0083 | B91: ROP-0192 | C91: Shortage | D91: MOS100624 | E91: =IFERROR(INDEX(M_User!$A$12:$J$67,MATCH(D91,M_User!$D$12:$D$67,0),3),"UNMAPPED") -> Gastory S Msaki | F91: FG011 | G91: =IFERROR(INDEX(M_SKU!$A$18:$J$57,MATCH(F91,M_SKU!$B$18:$B$57,0),1),"UNKNOWN SKU") -> Krest Tonic Water RGB 300ml | H91: CK3-33347 | I91: 0.0029364631 | N91: 46180 | O91: =IF(ISBLANK(M91),IF(TODAY()>N91,"BREACHED","PENDING"),IF(M91<=N91,"Within SLA","BREACHED")) -> BREACHED
A92: VR-0084 | B92: ROP-0193 | C92: Shortage | D92: MOS100624 | E92: =IFERROR(INDEX(M_User!$A$12:$J$67,MATCH(D92,M_User!$D$12:$D$67,0),3),"UNMAPPED") -> Gastory S Msaki | F92: FG012 | G92: =IFERROR(INDEX(M_SKU!$A$18:$J$57,MATCH(F92,M_SKU!$B$18:$B$57,0),1),"UNKNOWN SKU") -> Krest Ginger Ale RGB 300ml | H92: CK3-33126 | I92: 0.001774716 | N92: 46180 | O92: =IF(ISBLANK(M92),IF(TODAY()>N92,"BREACHED","PENDING"),IF(M92<=N92,"Within SLA","BREACHED")) -> BREACHED
A93: VR-0085 | B93: ROP-0194 | C93: Excess | D93: MOS100624 | E93: =IFERROR(INDEX(M_User!$A$12:$J$67,MATCH(D93,M_User!$D$12:$D$67,0),3),"UNMAPPED") -> Gastory S Msaki | F93: FG024 | G93: =IFERROR(INDEX(M_SKU!$A$18:$J$57,MATCH(F93,M_SKU!$B$18:$B$57,0),1),"UNKNOWN SKU") -> Sparletta Red Apple RGB 350ml | H93: CK3-32758 | I93: 0.0039545935 | N93: 46180 | O93: =IF(ISBLANK(M93),IF(TODAY()>N93,"BREACHED","PENDING"),IF(M93<=N93,"Within SLA","BREACHED")) -> BREACHED
A94: VR-0086 | B94: ROP-0208 | C94: Shortage | D94: MOS100645 | E94: =IFERROR(INDEX(M_User!$A$12:$J$67,MATCH(D94,M_User!$D$12:$D$67,0),3),"UNMAPPED") -> Riziki Rajabu Mghamba | F94: FG001 | G94: =IFERROR(INDEX(M_SKU!$A$18:$J$57,MATCH(F94,M_SKU!$B$18:$B$57,0),1),"UNKNOWN SKU") -> Coke RGB 350ml | H94: CK3-33408 | I94: 0.63772198 | J94: Damage / Breakage | K94: Bottles damaged due to rough road conditions | L94: BBL_SUP_046 | M94: 46179 | N94: 46180 | O94: =IF(ISBLANK(M94),IF(TODAY()>N94,"BREACHED","PENDING"),IF(M94<=N94,"Within SLA","BREACHED")) -> Within SLA
A95: VR-0087 | B95: ROP-0209 | C95: Shortage | D95: MOS100645 | E95: =IFERROR(INDEX(M_User!$A$12:$J$67,MATCH(D95,M_User!$D$12:$D$67,0),3),"UNMAPPED") -> Riziki Rajabu Mghamba | F95: FG001 | G95: =IFERROR(INDEX(M_SKU!$A$18:$J$57,MATCH(F95,M_SKU!$B$18:$B$57,0),1),"UNKNOWN SKU") -> Coke RGB 350ml | H95: CK3-33409 | I95: 2.753791 | N95: 46180 | O95: =IF(ISBLANK(M95),IF(TODAY()>N95,"BREACHED","PENDING"),IF(M95<=N95,"Within SLA","BREACHED")) -> BREACHED
A96: VR-0088 | B96: ROP-0210 | C96: Shortage | D96: MOS100645 | E96: =IFERROR(INDEX(M_User!$A$12:$J$67,MATCH(D96,M_User!$D$12:$D$67,0),3),"UNMAPPED") -> Riziki Rajabu Mghamba | F96: FG002 | G96: =IFERROR(INDEX(M_SKU!$A$18:$J$57,MATCH(F96,M_SKU!$B$18:$B$57,0),1),"UNKNOWN SKU") -> Fanta Orange RGB 350ml | H96: CK3-33407 | I96: 0.73517495 | J96: Damage / Breakage | K96: Pallet damaged during transit; mixed breakage | L96: BBL_SUP_047 | M96: 46179 | N96: 46180 | O96: =IF(ISBLANK(M96),IF(TODAY()>N96,"BREACHED","PENDING"),IF(M96<=N96,"Within SLA","BREACHED")) -> Within SLA
A97: VR-0089 | B97: ROP-0211 | C97: Shortage | D97: MOS100645 | E97: =IFERROR(INDEX(M_User!$A$12:$J$67,MATCH(D97,M_User!$D$12:$D$67,0),3),"UNMAPPED") -> Riziki Rajabu Mghamba | F97: FG003 | G97: =IFERROR(INDEX(M_SKU!$A$18:$J$57,MATCH(F97,M_SKU!$B$18:$B$57,0),1),"UNKNOWN SKU") -> Fanta Passion RGB 350ml | H97: CK3-33387 | I97: 0.45220468 | N97: 46180 | O97: =IF(ISBLANK(M97),IF(TODAY()>N97,"BREACHED","PENDING"),IF(M97<=N97,"Within SLA","BREACHED")) -> BREACHED
A98: VR-0090 | B98: ROP-0212 | C98: Shortage | D98: MOS100645 | E98: =IFERROR(INDEX(M_User!$A$12:$J$67,MATCH(D98,M_User!$D$12:$D$67,0),3),"UNMAPPED") -> Riziki Rajabu Mghamba | F98: FG004 | G98: =IFERROR(INDEX(M_SKU!$A$18:$J$57,MATCH(F98,M_SKU!$B$18:$B$57,0),1),"UNKNOWN SKU") -> Fanta Pineapple RGB 350ml | H98: CK3-33385 | I98: 0.63430047 | N98: 46180 | O98: =IF(ISBLANK(M98),IF(TODAY()>N98,"BREACHED","PENDING"),IF(M98<=N98,"Within SLA","BREACHED")) -> BREACHED
A99: VR-0091 | B99: ROP-0213 | C99: Shortage | D99: MOS100645 | E99: =IFERROR(INDEX(M_User!$A$12:$J$67,MATCH(D99,M_User!$D$12:$D$67,0),3),"UNMAPPED") -> Riziki Rajabu Mghamba | F99: FG005 | G99: =IFERROR(INDEX(M_SKU!$A$18:$J$57,MATCH(F99,M_SKU!$B$18:$B$57,0),1),"UNKNOWN SKU") -> Fanta Fruit Blast RGB 350 ml | H99: CK3-33402 | I99: 0.69433082 | N99: 46180 | O99: =IF(ISBLANK(M99),IF(TODAY()>N99,"BREACHED","PENDING"),IF(M99<=N99,"Within SLA","BREACHED")) -> BREACHED
A100: VR-0092 | B100: ROP-0214 | C100: Shortage | D100: MOS100645 | E100: =IFERROR(INDEX(M_User!$A$12:$J$67,MATCH(D100,M_User!$D$12:$D$67,0),3),"UNMAPPED") -> Riziki Rajabu Mghamba | F100: FG006 | G100: =IFERROR(INDEX(M_SKU!$A$18:$J$57,MATCH(F100,M_SKU!$B$18:$B$57,0),1),"UNKNOWN SKU") -> Sprite 350ml | H100: CK3-33414 | I100: 0.48680122 | J100: Theft / Loss | K100: Suspected pilferage at outlet; under investigation | L100: BBL_SUP_047 | M100: 46179 | N100: 46180 | O100: =IF(ISBLANK(M100),IF(TODAY()>N100,"BREACHED","PENDING"),IF(M100<=N100,"Within SLA","BREACHED")) -> Within SLA
A101: VR-0093 | B101: ROP-0215 | C101: Shortage | D101: MOS100645 | E101: =IFERROR(INDEX(M_User!$A$12:$J$67,MATCH(D101,M_User!$D$12:$D$67,0),3),"UNMAPPED") -> Riziki Rajabu Mghamba | F101: FG007 | G101: =IFERROR(INDEX(M_SKU!$A$18:$J$57,MATCH(F101,M_SKU!$B$18:$B$57,0),1),"UNKNOWN SKU") -> Stoney Tangawizi RGB 350ml | H101: CK3-33404 | I101: 0.1612089 | J101: Damage / Breakage | K101: Crate fell during loading; multiple breakages | L101: BBL_SUP_046 | M101: 46180 | N101: 46180 | O101: =IF(ISBLANK(M101),IF(TODAY()>N101,"BREACHED","PENDING"),IF(M101<=N101,"Within SLA","BREACHED")) -> Within SLA
A102: VR-0094 | B102: ROP-0216 | C102: Shortage | D102: MOS100645 | E102: =IFERROR(INDEX(M_User!$A$12:$J$67,MATCH(D102,M_User!$D$12:$D$67,0),3),"UNMAPPED") -> Riziki Rajabu Mghamba | F102: FG008 | G102: =IFERROR(INDEX(M_SKU!$A$18:$J$57,MATCH(F102,M_SKU!$B$18:$B$57,0),1),"UNKNOWN SKU") -> Sparletta Pinenut RGB 350ml | H102: CK3-33365 | I102: 0.12274557 | N102: 46180 | O102: =IF(ISBLANK(M102),IF(TODAY()>N102,"BREACHED","PENDING"),IF(M102<=N102,"Within SLA","BREACHED")) -> BREACHED
A103: VR-0095 | B103: ROP-0217 | C103: Shortage | D103: MOS100645 | E103: =IFERROR(INDEX(M_User!$A$12:$J$67,MATCH(D103,M_User!$D$12:$D$67,0),3),"UNMAPPED") -> Riziki Rajabu Mghamba | F103: FG009 | G103: =IFERROR(INDEX(M_SKU!$A$18:$J$57,MATCH(F103,M_SKU!$B$18:$B$57,0),1),"UNKNOWN SKU") -> Krest Bitter Lemon RGB 300ml | H103: CK3-33348 | I103: 0.081844973 | N103: 46180 | O103: =IF(ISBLANK(M103),IF(TODAY()>N103,"BREACHED","PENDING"),IF(M103<=N103,"Within SLA","BREACHED")) -> BREACHED
...

Sheet R_IntegrationPage
A1: R_IntegrationPage — Clerk Command Center
A2: Live view of all items requiring Clerk action. Refresh by recalculating the workbook (F9).
A3: Today's Date: | B3: =TODAY() -> 46206
A5: KEY ACTION SUMMARY
A6: Pending Load Confirmation | C6: Force-Push Required | E6: Pending ROP Verification
A7: =COUNTIF(T_Load!$P$9:$P$439,"Pending Confirmation")-COUNTIF(T_Load!$F$9:$F$439,"UNMAPPED") -> 407 | C7: =COUNTIF(T_Load!$F$9:$F$439,"UNMAPPED") -> 24 | E7: =COUNTIF(T_ROP!$O$13:$O$436,"Pending Verification") -> 400
A8: Loads awaiting Clerk's confirmation | C8: SAP codes not in User Master | E8: Actual ROP not yet verified by Clerk
A10: Shortage Postings to Push | C10: Variance Reasons Pending | E10: SLA Breaches
A11: =COUNTIF(T_DefaultOutletPosting!$P$9:$P$111,"Pending Push") -> 103 | C11: =COUNTIF(T_VarianceReasons!$O$9:$O$240,"PENDING")+COUNTIF(T_VarianceReasons!$O$9:$O$240,"BREACHED") -> 163 | E11: =COUNTIF(T_VarianceReasons!$O$9:$O$240,"BREACHED") -> 163
A12: Default Outlet sales pending SAP push | C12: Reasons not yet logged by Supervisor | E12: Reason log past 24h deadline
A14: FORCE-PUSH REQUIRED (Unmapped SAP Codes — Clerk Decision Needed)
A15: SAP Doc | B15: SAP Code | C15: SAP Dest Name | D15: SKU Code | E15: SKU Name | F15: Batch | G15: Qty | H15: Status
A16: =T_Load!B116 -> 166152 | B16: =T_Load!D116 -> MOS100801 | C16: =T_Load!E116 -> James Tegemea Ndosi | D16: =T_Load!J116 -> FG001 | E16: =T_Load!K116 -> Coke RGB 350ml | F16: =T_Load!L116 -> CK3-33409 | G16: =T_Load!O116 -> 40 | H16: =T_Load!P116 -> Pending Confirmation
A17: =T_Load!B117 -> 166152 | B17: =T_Load!D117 -> MOS100801 | C17: =T_Load!E117 -> James Tegemea Ndosi | D17: =T_Load!J117 -> FG002 | E17: =T_Load!K117 -> Fanta Orange RGB 350ml | F17: =T_Load!L117 -> CK3-33407 | G17: =T_Load!O117 -> 15 | H17: =T_Load!P117 -> Pending Confirmation
A18: =T_Load!B118 -> 166152 | B18: =T_Load!D118 -> MOS100801 | C18: =T_Load!E118 -> James Tegemea Ndosi | D18: =T_Load!J118 -> FG003 | E18: =T_Load!K118 -> Fanta Passion RGB 350ml | F18: =T_Load!L118 -> CK3-33356 | G18: =T_Load!O118 -> 7 | H18: =T_Load!P118 -> Pending Confirmation
A19: =T_Load!B119 -> 166152 | B19: =T_Load!D119 -> MOS100801 | C19: =T_Load!E119 -> James Tegemea Ndosi | D19: =T_Load!J119 -> FG004 | E19: =T_Load!K119 -> Fanta Pineapple RGB 350ml | F19: =T_Load!L119 -> CK3-33385 | G19: =T_Load!O119 -> 7 | H19: =T_Load!P119 -> Pending Confirmation
A20: =T_Load!B120 -> 166152 | B20: =T_Load!D120 -> MOS100801 | C20: =T_Load!E120 -> James Tegemea Ndosi | D20: =T_Load!J120 -> FG005 | E20: =T_Load!K120 -> Fanta Fruit Blast RGB 350 ml | F20: =T_Load!L120 -> CK3-33402 | G20: =T_Load!O120 -> 5 | H20: =T_Load!P120 -> Pending Confirmation
A21: =T_Load!B121 -> 166152 | B21: =T_Load!D121 -> MOS100801 | C21: =T_Load!E121 -> James Tegemea Ndosi | D21: =T_Load!J121 -> FG006 | E21: =T_Load!K121 -> Sprite 350ml | F21: =T_Load!L121 -> CK3-33414 | G21: =T_Load!O121 -> 7 | H21: =T_Load!P121 -> Pending Confirmation
A22: =T_Load!B122 -> 166152 | B22: =T_Load!D122 -> MOS100801 | C22: =T_Load!E122 -> James Tegemea Ndosi | D22: =T_Load!J122 -> FG007 | E22: =T_Load!K122 -> Stoney Tangawizi RGB 350ml | F22: =T_Load!L122 -> CK3-33404 | G22: =T_Load!O122 -> 5 | H22: =T_Load!P122 -> Pending Confirmation
A23: =T_Load!B123 -> 166152 | B23: =T_Load!D123 -> MOS100801 | C23: =T_Load!E123 -> James Tegemea Ndosi | D23: =T_Load!J123 -> FG008 | E23: =T_Load!K123 -> Sparletta Pinenut RGB 350ml | F23: =T_Load!L123 -> CK3-33365 | G23: =T_Load!O123 -> 5 | H23: =T_Load!P123 -> Pending Confirmation
A24: =T_Load!B124 -> 166152 | B24: =T_Load!D124 -> MOS100801 | C24: =T_Load!E124 -> James Tegemea Ndosi | D24: =T_Load!J124 -> FG009 | E24: =T_Load!K124 -> Krest Bitter Lemon RGB 300ml | F24: =T_Load!L124 -> CK3-33348 | G24: =T_Load!O124 -> 3 | H24: =T_Load!P124 -> Pending Confirmation
A25: =T_Load!B125 -> 166152 | B25: =T_Load!D125 -> MOS100801 | C25: =T_Load!E125 -> James Tegemea Ndosi | D25: =T_Load!J125 -> FG010 | E25: =T_Load!K125 -> Krest Club Soda RGB 300ml | F25: =T_Load!L125 -> CK3-33301 | G25: =T_Load!O125 -> 3 | H25: =T_Load!P125 -> Pending Confirmation
A26: =T_Load!B126 -> 166152 | B26: =T_Load!D126 -> MOS100801 | C26: =T_Load!E126 -> James Tegemea Ndosi | D26: =T_Load!J126 -> FG011 | E26: =T_Load!K126 -> Krest Tonic Water RGB 300ml | F26: =T_Load!L126 -> CK3-33347 | G26: =T_Load!O126 -> 3 | H26: =T_Load!P126 -> Pending Confirmation
A27: =T_Load!B127 -> 166152 | B27: =T_Load!D127 -> MOS100801 | C27: =T_Load!E127 -> James Tegemea Ndosi | D27: =T_Load!J127 -> FG012 | E27: =T_Load!K127 -> Krest Ginger Ale RGB 300ml | F27: =T_Load!L127 -> CK3-33126 | G27: =T_Load!O127 -> 3 | H27: =T_Load!P127 -> Pending Confirmation
... A39: =T_Load!B139 -> 166152 | B39: =T_Load!D139 -> MOS100801 | C39: =T_Load!E139 -> James Tegemea Ndosi | D39: =T_Load!J139 -> PO015 | E39: =T_Load!K139 -> Sparletta Pine Apple Pet 300ML (x 12) | F39: =T_Load!L139 -> CK5-33366 | G39: =T_Load!O139 -> 5 | H39: =T_Load!P139 -> Pending Confirmation
A41: Clerk Action: Use Force-Push to assign these rows to a valid M_User salesman, or Reject the load.
A44: AGING — Open Loads by Days Outstanding (Threshold: 7 days from M_Config)
A45: Age Bucket | B45: Pending Loads | C45: Total Qty | D45: % of Total
A46: Same day (0 days) | B46: =SUMPRODUCT((T_Load!$P$9:$P$439="Pending Confirmation")*((TODAY()-T_Load!$C$9:$C$439)=0)) -> 0 | C46: =SUMPRODUCT((T_Load!$P$9:$P$439="Pending Confirmation")*((TODAY()-T_Load!$C$9:$C$439)=0)*T_Load!$O$9:$O$439) -> 0 | D46: =IFERROR(B46/SUM(B46:B49),0) -> 0
A47: 1-2 days | B47: =SUMPRODUCT((T_Load!$P$9:$P$439="Pending Confirmation")*((TODAY()-T_Load!$C$9:$C$439)>=1)*((TODAY()-T_Load!$C$9:$C$439)<=2)) -> 0 | C47: =SUMPRODUCT((T_Load!$P$9:$P$439="Pending Confirmation")*((TODAY()-T_Load!$C$9:$C$439)>=1)*((TODAY()-T_Load!$C$9:$C$439)<=2)*T_Load!$O$9:$O$439) -> 0 | D47: =IFERROR(B47/SUM(B46:B49),0) -> 0
A48: 3-6 days | B48: =SUMPRODUCT((T_Load!$P$9:$P$439="Pending Confirmation")*((TODAY()-T_Load!$C$9:$C$439)>=3)*((TODAY()-T_Load!$C$9:$C$439)<=6)) -> 0 | C48: =SUMPRODUCT((T_Load!$P$9:$P$439="Pending Confirmation")*((TODAY()-T_Load!$C$9:$C$439)>=3)*((TODAY()-T_Load!$C$9:$C$439)<=6)*T_Load!$O$9:$O$439) -> 0 | D48: =IFERROR(B48/SUM(B46:B49),0) -> 0
A49: 7+ days (ALERT) | B49: =SUMPRODUCT((T_Load!$P$9:$P$439="Pending Confirmation")*((TODAY()-T_Load!$C$9:$C$439)>=7)) -> 431 | C49: =SUMPRODUCT((T_Load!$P$9:$P$439="Pending Confirmation")*((TODAY()-T_Load!$C$9:$C$439)>=7)*T_Load!$O$9:$O$439) -> 8286 | D49: =IFERROR(B49/SUM(B46:B49),0) -> 1
A52: VARIANCE REASON SLA — Quick Overview
A53: SLA Status | B53: Count | C53: Notes
A54: Within SLA | B54: =COUNTIF(T_VarianceReasons!$O$9:$O$240,"Within SLA") -> 69 | C54: Reason logged within 24 hours
A55: Pending | B55: =COUNTIF(T_VarianceReasons!$O$9:$O$240,"PENDING") -> 0 | C55: Not yet logged; still within deadline
A56: BREACHED | B56: =COUNTIF(T_VarianceReasons!$O$9:$O$240,"BREACHED") -> 163 | C56: Past 24h deadline — escalation needed
A59: This report aggregates live data from T_Load, T_ROP, T_DefaultOutletPosting, and T_VarianceReasons. Press F9 to recalculate.

Sheet R_SettlementSheet
A1: R_SettlementSheet — Daily Salesman Settlement | N1: Salesman Display (helper) | O1: SAP Code (helper) | AA1: Helper: Match Rank
A2: Dynamic template: select a salesman from the dropdown to populate all figures. Printable per day, per salesman. | N2: Alice Jonathan Mfuru (MOS100823) | O2: MOS100823 | AA2: =IF(AND(T_ROP!$C$13=$I$4,T_ROP!$L$13<>"CLEAN",T_ROP!$L$13<>""),COUNTIFS(T_ROP!$C$13:$C$13,$I$4,T_ROP!$L$13:$L$13,"<>CLEAN",T_ROP!$L$13:$L$13,"<>"),"")
N3: Deodat Francis Materu (MOS100180) | O3: MOS100180 | AA3: =IF(AND(T_ROP!$C$14=$I$4,T_ROP!$L$14<>"CLEAN",T_ROP!$L$14<>""),COUNTIFS(T_ROP!$C$13:$C$14,$I$4,T_ROP!$L$13:$L$14,"<>CLEAN",T_ROP!$L$13:$L$14,"<>"),"")
A4: SELECT SALESMAN: | B4: Erick K. Mkama (MOS100209) | H4: Selected SAP: | I4: =INDEX($O$2:$O$19,MATCH($B$4,$N$2:$N$19,0)) -> MOS100209 | N4: Doglas E. Shirima (ARS000069) | O4: ARS000069 | AA4: =IF(AND(T_ROP!$C$15=$I$4,T_ROP!$L$15<>"CLEAN",T_ROP!$L$15<>""),COUNTIFS(T_ROP!$C$13:$C$15,$I$4,T_ROP!$L$13:$L$15,"<>CLEAN",T_ROP!$L$13:$L$15,"<>"),"")
N5: Erick K. Mkama (MOS100209) | O5: MOS100209 | AA5: =IF(AND(T_ROP!$C$16=$I$4,T_ROP!$L$16<>"CLEAN",T_ROP!$L$16<>""),COUNTIFS(T_ROP!$C$13:$C$16,$I$4,T_ROP!$L$13:$L$16,"<>CLEAN",T_ROP!$L$13:$L$16,"<>"),"")
A6: Salesman Name: | B6: =IFERROR(INDEX(M_User!$A$12:$J$67,MATCH($I$4,M_User!$D$12:$D$67,0),3),"NOT FOUND") -> Erick K. Mkama | F6: Depot: | G6: =IFERROR(INDEX(M_User!$A$12:$J$67,MATCH($I$4,M_User!$D$12:$D$67,0),5),"N/A") -> MOS | N6: Gastory S Msaki (MOS100624) | O6: MOS100624 | AA6: =IF(AND(T_ROP!$C$17=$I$4,T_ROP!$L$17<>"CLEAN",T_ROP!$L$17<>""),COUNTIFS(T_ROP!$C$13:$C$17,$I$4,T_ROP!$L$13:$L$17,"<>CLEAN",T_ROP!$L$13:$L$17,"<>"),"")
A7: SAP Code: | B7: =$I$4 -> MOS100209 | F7: Reporting Officer: | G7: =IFERROR(INDEX(M_User!$A$12:$J$67,MATCH($I$4,M_User!$D$12:$D$67,0),7),"N/A") -> Rachel Emanuel Kissota | N7: George Gibson Mmary (MOS100200) | O7: MOS100200 | AA7: =IF(AND(T_ROP!$C$18=$I$4,T_ROP!$L$18<>"CLEAN",T_ROP!$L$18<>""),COUNTIFS(T_ROP!$C$13:$C$18,$I$4,T_ROP!$L$13:$L$18,"<>CLEAN",T_ROP!$L$13:$L$18,"<>"),"")
A8: Settlement Date: | B8: =IF($I$4="DSM300140",DATE(2026,6,11),DATE(2026,6,6)) -> 46179 | F8: Generated On: | G8: =TODAY() -> 46206 | N8: James Tegemea Ndosi (UNMAPPED) (MOS100801) | O8: MOS100801 | AA8: =IF(AND(T_ROP!$C$19=$I$4,T_ROP!$L$19<>"CLEAN",T_ROP!$L$19<>""),COUNTIFS(T_ROP!$C$13:$C$19,$I$4,T_ROP!$L$13:$L$19,"<>CLEAN",T_ROP!$L$13:$L$19,"<>"),"")
N9: Jonas Steven Michael (MOS100501) | O9: MOS100501 | AA9: =IF(AND(T_ROP!$C$20=$I$4,T_ROP!$L$20<>"CLEAN",T_ROP!$L$20<>""),COUNTIFS(T_ROP!$C$13:$C$20,$I$4,T_ROP!$L$13:$L$20,"<>CLEAN",T_ROP!$L$13:$L$20,"<>"),"")
N10: Joyline J Lyimo (MOS100802) | O10: MOS100802 | AA10: =IF(AND(T_ROP!$C$21=$I$4,T_ROP!$L$21<>"CLEAN",T_ROP!$L$21<>""),COUNTIFS(T_ROP!$C$13:$C$21,$I$4,T_ROP!$L$13:$L$21,"<>CLEAN",T_ROP!$L$13:$L$21,"<>"),"")
A11: PAGE 1 — SETTLEMENT BY SKU (40 SKUs in Canonical Category Order) | N11: Masunga Mwala Ramadhani (MOS100788) | O11: MOS100788 | AA11: =IF(AND(T_ROP!$C$22=$I$4,T_ROP!$L$22<>"CLEAN",T_ROP!$L$22<>""),COUNTIFS(T_ROP!$C$13:$C$22,$I$4,T_ROP!$L$13:$L$22,"<>CLEAN",T_ROP!$L$13:$L$22,"<>"),"")
A12: SKU Code | B12: SKU Name | C12: Load Qty | D12: Sales Qty | E12: Expected ROP | F12: Actual ROP | G12: Variance | H12: Unit Price (TZS) | I12: Sale Value (TZS) | J12: Action | N12: Meshack Jeremiah (MOS100079) | O12: MOS100079 | AA12: =IF(AND(T_ROP!$C$23=$I$4,T_ROP!$L$23<>"CLEAN",T_ROP!$L$23<>""),COUNTIFS(T_ROP!$C$13:$C$23,$I$4,T_ROP!$L$13:$L$23,"<>CLEAN",T_ROP!$L$13:$L$23,"<>"),"")
A13: RGB | N13: Omary O. Seif (DSM300140) | O13: DSM300140 | AA13: =IF(AND(T_ROP!$C$24=$I$4,T_ROP!$L$24<>"CLEAN",T_ROP!$L$24<>""),COUNTIFS(T_ROP!$C$13:$C$24,$I$4,T_ROP!$L$13:$L$24,"<>CLEAN",T_ROP!$L$13:$L$24,"<>"),"")
A14: FG001 | B14: Coke RGB 350ml | C14: =SUMIFS(T_Load!$O$9:$O$439,T_Load!$D$9:$D$439,$I$4,T_Load!$J$9:$J$439,"FG001") -> 34 | D14: =SUMIFS(T_Sales!$L$9:$L$1164,T_Sales!$D$9:$D$1164,$I$4,T_Sales!$I$9:$I$1164,"FG001") -> 30.760148 | E14: =C14-D14 -> 3.239852 | F14: =SUMIFS(T_ROP!$J$13:$J$436,T_ROP!$C$13:$C$436,$I$4,T_ROP!$F$13:$F$436,"FG001") -> 3.24 | G14: =E14-F14 -> -0.00014803382 | H14: {=IFERROR(INDEX(M_DepotPrice!$C$10:$C$52,MATCH(1,(M_DepotPrice!$A$10:$A$52=A14)*(M_DepotPrice!$H$10:$H$52=IFERROR(INDEX(M_Depot!$A$7:$A$24,MATCH($G$6,M_Depot!$B$7:$B$24,0)),""))*(M_DepotPrice!$G$10:$G$52="Special"),0)),INDEX(M_DepotPrice!$C$10:$C$52,MATCH(1,(M_DepotPrice!$A$10:$A$52=A14)*(M_DepotPrice!$G$10:$G$52="Default"),0)))*1.18} -> 13900.4 | I14: =SUMIFS(T_Sales!$N$9:$N$1164,T_Sales!$D$9:$D$1164,$I$4,T_Sales!$I$9:$I$1164,"FG001") -> 427578.36 | J14: =IF(C14=0,"-",IF(ABS(G14)<0.0001,"CLEAN",IF(G14>0,"Default Outlet Posting","Unload Adjustment"))) -> Unload Adjustment | N14: Piniel Julius Singo (MOS100654) | O14: MOS100654 | AA14: =IF(AND(T_ROP!$C$25=$I$4,T_ROP!$L$25<>"CLEAN",T_ROP!$L$25<>""),COUNTIFS(T_ROP!$C$13:$C$25,$I$4,T_ROP!$L$13:$L$25,"<>CLEAN",T_ROP!$L$13:$L$25,"<>"),"")
A15: FG002 | B15: Fanta Orange RGB 350ml | C15: =SUMIFS(T_Load!$O$9:$O$439,T_Load!$D$9:$D$439,$I$4,T_Load!$J$9:$J$439,"FG002") -> 15 | D15: =SUMIFS(T_Sales!$L$9:$L$1164,T_Sales!$D$9:$D$1164,$I$4,T_Sales!$I$9:$I$1164,"FG002") -> 11.398979 | E15: =C15-D15 -> 3.6010213 | F15: =SUMIFS(T_ROP!$J$13:$J$436,T_ROP!$C$13:$C$436,$I$4,T_ROP!$F$13:$F$436,"FG002") -> 3.6 | G15: =E15-F15 -> 0.0010213285 | H15: {=IFERROR(INDEX(M_DepotPrice!$C$10:$C$52,MATCH(1,(M_DepotPrice!$A$10:$A$52=A15)*(M_DepotPrice!$H$10:$H$52=IFERROR(INDEX(M_Depot!$A$7:$A$24,MATCH($G$6,M_Depot!$B$7:$B$24,0)),""))*(M_DepotPrice!$G$10:$G$52="Special"),0)),INDEX(M_DepotPrice!$C$10:$C$52,MATCH(1,(M_DepotPrice!$A$10:$A$52=A15)*(M_DepotPrice!$G$10:$G$52="Default"),0)))*1.18} -> 13900.4 | I15: =SUMIFS(T_Sales!$N$9:$N$1164,T_Sales!$D$9:$D$1164,$I$4,T_Sales!$I$9:$I$1164,"FG002") -> 158450.36 | J15: =IF(C15=0,"-",IF(ABS(G15)<0.0001,"CLEAN",IF(G15>0,"Default Outlet Posting","Unload Adjustment"))) -> Default Outlet Posting | N15: Raymond P Sangawe (MOS100716) | O15: MOS100716 | AA15: =IF(AND(T_ROP!$C$26=$I$4,T_ROP!$L$26<>"CLEAN",T_ROP!$L$26<>""),COUNTIFS(T_ROP!$C$13:$C$26,$I$4,T_ROP!$L$13:$L$26,"<>CLEAN",T_ROP!$L$13:$L$26,"<>"),"")
A16: FG003 | B16: Fanta Passion RGB 350ml | C16: =SUMIFS(T_Load!$O$9:$O$439,T_Load!$D$9:$D$439,$I$4,T_Load!$J$9:$J$439,"FG003") -> 8 | D16: =SUMIFS(T_Sales!$L$9:$L$1164,T_Sales!$D$9:$D$1164,$I$4,T_Sales!$I$9:$I$1164,"FG003") -> 6.8298061 | E16: =C16-D16 -> 1.1701939 | F16: =SUMIFS(T_ROP!$J$13:$J$436,T_ROP!$C$13:$C$436,$I$4,T_ROP!$F$13:$F$436,"FG003") -> 1.17 | G16: =E16-F16 -> 0.00019391515 | H16: {=IFERROR(INDEX(M_DepotPrice!$C$10:$C$52,MATCH(1,(M_DepotPrice!$A$10:$A$52=A16)*(M_DepotPrice!$H$10:$H$52=IFERROR(INDEX(M_Depot!$A$7:$A$24,MATCH($G$6,M_Depot!$B$7:$B$24,0)),""))*(M_DepotPrice!$G$10:$G$52="Special"),0)),INDEX(M_DepotPrice!$C$10:$C$52,MATCH(1,(M_DepotPrice!$A$10:$A$52=A16)*(M_DepotPrice!$G$10:$G$52="Default"),0)))*1.18} -> 13900.4 | I16: =SUMIFS(T_Sales!$N$9:$N$1164,T_Sales!$D$9:$D$1164,$I$4,T_Sales!$I$9:$I$1164,"FG003") -> 94937.037 | J16: =IF(C16=0,"-",IF(ABS(G16)<0.0001,"CLEAN",IF(G16>0,"Default Outlet Posting","Unload Adjustment"))) -> Default Outlet Posting | N16: Riziki Rajabu Mghamba (MOS100645) | O16: MOS100645 | AA16: =IF(AND(T_ROP!$C$27=$I$4,T_ROP!$L$27<>"CLEAN",T_ROP!$L$27<>""),COUNTIFS(T_ROP!$C$13:$C$27,$I$4,T_ROP!$L$13:$L$27,"<>CLEAN",T_ROP!$L$13:$L$27,"<>"),"")
A17: FG004 | B17: Fanta Pineapple RGB 350ml | C17: =SUMIFS(T_Load!$O$9:$O$439,T_Load!$D$9:$D$439,$I$4,T_Load!$J$9:$J$439,"FG004") -> 8 | D17: =SUMIFS(T_Sales!$L$9:$L$1164,T_Sales!$D$9:$D$1164,$I$4,T_Sales!$I$9:$I$1164,"FG004") -> 6.4732745 | E17: =C17-D17 -> 1.5267255 | F17: =SUMIFS(T_ROP!$J$13:$J$436,T_ROP!$C$13:$C$436,$I$4,T_ROP!$F$13:$F$436,"FG004") -> 1.53 | G17: =E17-F17 -> -0.0032745249 | H17: {=IFERROR(INDEX(M_DepotPrice!$C$10:$C$52,MATCH(1,(M_DepotPrice!$A$10:$A$52=A17)*(M_DepotPrice!$H$10:$H$52=IFERROR(INDEX(M_Depot!$A$7:$A$24,MATCH($G$6,M_Depot!$B$7:$B$24,0)),""))*(M_DepotPrice!$G$10:$G$52="Special"),0)),INDEX(M_DepotPrice!$C$10:$C$52,MATCH(1,(M_DepotPrice!$A$10:$A$52=A17)*(M_DepotPrice!$G$10:$G$52="Default"),0)))*1.18} -> 13900.4 | I17: =SUMIFS(T_Sales!$N$9:$N$1164,T_Sales!$D$9:$D$1164,$I$4,T_Sales!$I$9:$I$1164,"FG004") -> 89981.105 | J17: =IF(C17=0,"-",IF(ABS(G17)<0.0001,"CLEAN",IF(G17>0,"Default Outlet Posting","Unload Adjustment"))) -> Unload Adjustment | N17: Samson Felix Ngowi (MOS100842) | O17: MOS100842 | AA17: =IF(AND(T_ROP!$C$28=$I$4,T_ROP!$L$28<>"CLEAN",T_ROP!$L$28<>""),COUNTIFS(T_ROP!$C$13:$C$28,$I$4,T_ROP!$L$13:$L$28,"<>CLEAN",T_ROP!$L$13:$L$28,"<>"),"")
A18: FG005 | B18: Fanta Fruit Blast RGB 350 ml | C18: =SUMIFS(T_Load!$O$9:$O$439,T_Load!$D$9:$D$439,$I$4,T_Load!$J$9:$J$439,"FG005") -> 5 | D18: =SUMIFS(T_Sales!$L$9:$L$1164,T_Sales!$D$9:$D$1164,$I$4,T_Sales!$I$9:$I$1164,"FG005") -> 4.2709284 | E18: =C18-D18 -> 0.72907157 | F18: =SUMIFS(T_ROP!$J$13:$J$436,T_ROP!$C$13:$C$436,$I$4,T_ROP!$F$13:$F$436,"FG005") -> 0.73 | G18: =E18-F18 -> -0.00092843222 | H18: {=IFERROR(INDEX(M_DepotPrice!$C$10:$C$52,MATCH(1,(M_DepotPrice!$A$10:$A$52=A18)*(M_DepotPrice!$H$10:$H$52=IFERROR(INDEX(M_Depot!$A$7:$A$24,MATCH($G$6,M_Depot!$B$7:$B$24,0)),""))*(M_DepotPrice!$G$10:$G$52="Special"),0)),INDEX(M_DepotPrice!$C$10:$C$52,MATCH(1,(M_DepotPrice!$A$10:$A$52=A18)*(M_DepotPrice!$G$10:$G$52="Default"),0)))*1.18} -> 13900.4 | I18: =SUMIFS(T_Sales!$N$9:$N$1164,T_Sales!$D$9:$D$1164,$I$4,T_Sales!$I$9:$I$1164,"FG005") -> 59367.614 | J18: =IF(C18=0,"-",IF(ABS(G18)<0.0001,"CLEAN",IF(G18>0,"Default Outlet Posting","Unload Adjustment"))) -> Unload Adjustment | N18: Zawadi Jastin Laizer (MOS100744) | O18: MOS100744 | AA18: =IF(AND(T_ROP!$C$29=$I$4,T_ROP!$L$29<>"CLEAN",T_ROP!$L$29<>""),COUNTIFS(T_ROP!$C$13:$C$29,$I$4,T_ROP!$L$13:$L$29,"<>CLEAN",T_ROP!$L$13:$L$29,"<>"),"")
A19: FG006 | B19: Sprite 350ml | C19: =SUMIFS(T_Load!$O$9:$O$439,T_Load!$D$9:$D$439,$I$4,T_Load!$J$9:$J$439,"FG006") -> 10 | D19: =SUMIFS(T_Sales!$L$9:$L$1164,T_Sales!$D$9:$D$1164,$I$4,T_Sales!$I$9:$I$1164,"FG006") -> 8.4082907 | E19: =C19-D19 -> 1.5917093 | F19: =SUMIFS(T_ROP!$J$13:$J$436,T_ROP!$C$13:$C$436,$I$4,T_ROP!$F$13:$F$436,"FG006") -> 1.59 | G19: =E19-F19 -> 0.0017093329 | H19: {=IFERROR(INDEX(M_DepotPrice!$C$10:$C$52,MATCH(1,(M_DepotPrice!$A$10:$A$52=A19)*(M_DepotPrice!$H$10:$H$52=IFERROR(INDEX(M_Depot!$A$7:$A$24,MATCH($G$6,M_Depot!$B$7:$B$24,0)),""))*(M_DepotPrice!$G$10:$G$52="Special"),0)),INDEX(M_DepotPrice!$C$10:$C$52,MATCH(1,(M_DepotPrice!$A$10:$A$52=A19)*(M_DepotPrice!$G$10:$G$52="Default"),0)))*1.18} -> 13900.4 | I19: =SUMIFS(T_Sales!$N$9:$N$1164,T_Sales!$D$9:$D$1164,$I$4,T_Sales!$I$9:$I$1164,"FG006") -> 116878.6 | J19: =IF(C19=0,"-",IF(ABS(G19)<0.0001,"CLEAN",IF(G19>0,"Default Outlet Posting","Unload Adjustment"))) -> Default Outlet Posting | N19: Zefania Julius Ngoma (MOS100144) | O19: MOS100144 | AA19: =IF(AND(T_ROP!$C$30=$I$4,T_ROP!$L$30<>"CLEAN",T_ROP!$L$30<>""),COUNTIFS(T_ROP!$C$13:$C$30,$I$4,T_ROP!$L$13:$L$30,"<>CLEAN",T_ROP!$L$13:$L$30,"<>"),"")
A20: FG007 | B20: Stoney Tangawizi RGB 350ml | C20: =SUMIFS(T_Load!$O$9:$O$439,T_Load!$D$9:$D$439,$I$4,T_Load!$J$9:$J$439,"FG007") -> 3 | D20: =SUMIFS(T_Sales!$L$9:$L$1164,T_Sales!$D$9:$D$1164,$I$4,T_Sales!$I$9:$I$1164,"FG007") -> 2.2923826 | E20: =C20-D20 -> 0.70761744 | F20: =SUMIFS(T_ROP!$J$13:$J$436,T_ROP!$C$13:$C$436,$I$4,T_ROP!$F$13:$F$436,"FG007") -> 0.71 | G20: =E20-F20 -> -0.0023825643 | H20: {=IFERROR(INDEX(M_DepotPrice!$C$10:$C$52,MATCH(1,(M_DepotPrice!$A$10:$A$52=A20)*(M_DepotPrice!$H$10:$H$52=IFERROR(INDEX(M_Depot!$A$7:$A$24,MATCH($G$6,M_Depot!$B$7:$B$24,0)),""))*(M_DepotPrice!$G$10:$G$52="Special"),0)),INDEX(M_DepotPrice!$C$10:$C$52,MATCH(1,(M_DepotPrice!$A$10:$A$52=A20)*(M_DepotPrice!$G$10:$G$52="Default"),0)))*1.18} -> 13900.4 | I20: =SUMIFS(T_Sales!$N$9:$N$1164,T_Sales!$D$9:$D$1164,$I$4,T_Sales!$I$9:$I$1164,"FG007") -> 31865.035 | J20: =IF(C20=0,"-",IF(ABS(G20)<0.0001,"CLEAN",IF(G20>0,"Default Outlet Posting","Unload Adjustment"))) -> Unload Adjustment | AA20: =IF(AND(T_ROP!$C$31=$I$4,T_ROP!$L$31<>"CLEAN",T_ROP!$L$31<>""),COUNTIFS(T_ROP!$C$13:$C$31,$I$4,T_ROP!$L$13:$L$31,"<>CLEAN",T_ROP!$L$13:$L$31,"<>"),"")
A21: FG008 | B21: Sparletta Pinenut RGB 350ml | C21: =SUMIFS(T_Load!$O$9:$O$439,T_Load!$D$9:$D$439,$I$4,T_Load!$J$9:$J$439,"FG008") -> 3 | D21: =SUMIFS(T_Sales!$L$9:$L$1164,T_Sales!$D$9:$D$1164,$I$4,T_Sales!$I$9:$I$1164,"FG008") -> 2.2724788 | E21: =C21-D21 -> 0.72752116 | F21: =SUMIFS(T_ROP!$J$13:$J$436,T_ROP!$C$13:$C$436,$I$4,T_ROP!$F$13:$F$436,"FG008") -> 0.73 | G21: =E21-F21 -> -0.0024788416 | H21: {=IFERROR(INDEX(M_DepotPrice!$C$10:$C$52,MATCH(1,(M_DepotPrice!$A$10:$A$52=A21)*(M_DepotPrice!$H$10:$H$52=IFERROR(INDEX(M_Depot!$A$7:$A$24,MATCH($G$6,M_Depot!$B$7:$B$24,0)),""))*(M_DepotPrice!$G$10:$G$52="Special"),0)),INDEX(M_DepotPrice!$C$10:$C$52,MATCH(1,(M_DepotPrice!$A$10:$A$52=A21)*(M_DepotPrice!$G$10:$G$52="Default"),0)))*1.18} -> 13900.4 | I21: =SUMIFS(T_Sales!$N$9:$N$1164,T_Sales!$D$9:$D$1164,$I$4,T_Sales!$I$9:$I$1164,"FG008") -> 31588.365 | J21: =IF(C21=0,"-",IF(ABS(G21)<0.0001,"CLEAN",IF(G21>0,"Default Outlet Posting","Unload Adjustment"))) -> Unload Adjustment | AA21: =IF(AND(T_ROP!$C$32=$I$4,T_ROP!$L$32<>"CLEAN",T_ROP!$L$32<>""),COUNTIFS(T_ROP!$C$13:$C$32,$I$4,T_ROP!$L$13:$L$32,"<>CLEAN",T_ROP!$L$13:$L$32,"<>"),"")
A22: FG009 | B22: Krest Bitter Lemon RGB 300ml | C22: =SUMIFS(T_Load!$O$9:$O$439,T_Load!$D$9:$D$439,$I$4,T_Load!$J$9:$J$439,"FG009") -> 3 | D22: =SUMIFS(T_Sales!$L$9:$L$1164,T_Sales!$D$9:$D$1164,$I$4,T_Sales!$I$9:$I$1164,"FG009") -> 2.3873836 | E22: =C22-D22 -> 0.61261642 | F22: =SUMIFS(T_ROP!$J$13:$J$436,T_ROP!$C$13:$C$436,$I$4,T_ROP!$F$13:$F$436,"FG009") -> 0.61 | G22: =E22-F22 -> 0.0026164212 | H22: {=IFERROR(INDEX(M_DepotPrice!$C$10:$C$52,MATCH(1,(M_DepotPrice!$A$10:$A$52=A22)*(M_DepotPrice!$H$10:$H$52=IFERROR(INDEX(M_Depot!$A$7:$A$24,MATCH($G$6,M_Depot!$B$7:$B$24,0)),""))*(M_DepotPrice!$G$10:$G$52="Special"),0)),INDEX(M_DepotPrice!$C$10:$C$52,MATCH(1,(M_DepotPrice!$A$10:$A$52=A22)*(M_DepotPrice!$G$10:$G$52="Default"),0)))*1.18} -> 13900.4 | I22: =SUMIFS(T_Sales!$N$9:$N$1164,T_Sales!$D$9:$D$1164,$I$4,T_Sales!$I$9:$I$1164,"FG009") -> 33185.587 | J22: =IF(C22=0,"-",IF(ABS(G22)<0.0001,"CLEAN",IF(G22>0,"Default Outlet Posting","Unload Adjustment"))) -> Default Outlet Posting | AA22: =IF(AND(T_ROP!$C$33=$I$4,T_ROP!$L$33<>"CLEAN",T_ROP!$L$33<>""),COUNTIFS(T_ROP!$C$13:$C$33,$I$4,T_ROP!$L$13:$L$33,"<>CLEAN",T_ROP!$L$13:$L$33,"<>"),"")
A23: FG010 | B23: Krest Club Soda RGB 300ml | C23: =SUMIFS(T_Load!$O$9:$O$439,T_Load!$D$9:$D$439,$I$4,T_Load!$J$9:$J$439,"FG010") -> 2 | D23: =SUMIFS(T_Sales!$L$9:$L$1164,T_Sales!$D$9:$D$1164,$I$4,T_Sales!$I$9:$I$1164,"FG010") -> 1.7067307 | E23: =C23-D23 -> 0.29326926 | F23: =SUMIFS(T_ROP!$J$13:$J$436,T_ROP!$C$13:$C$436,$I$4,T_ROP!$F$13:$F$436,"FG010") -> 0.29 | G23: =E23-F23 -> 0.0032692604 | H23: {=IFERROR(INDEX(M_DepotPrice!$C$10:$C$52,MATCH(1,(M_DepotPrice!$A$10:$A$52=A23)*(M_DepotPrice!$H$10:$H$52=IFERROR(INDEX(M_Depot!$A$7:$A$24,MATCH($G$6,M_Depot!$B$7:$B$24,0)),""))*(M_DepotPrice!$G$10:$G$52="Special"),0)),INDEX(M_DepotPrice!$C$10:$C$52,MATCH(1,(M_DepotPrice!$A$10:$A$52=A23)*(M_DepotPrice!$G$10:$G$52="Default"),0)))*1.18} -> 13900.4 | I23: =SUMIFS(T_Sales!$N$9:$N$1164,T_Sales!$D$9:$D$1164,$I$4,T_Sales!$I$9:$I$1164,"FG010") -> 23724.24 | J23: =IF(C23=0,"-",IF(ABS(G23)<0.0001,"CLEAN",IF(G23>0,"Default Outlet Posting","Unload Adjustment"))) -> Default Outlet Posting | AA23: =IF(AND(T_ROP!$C$34=$I$4,T_ROP!$L$34<>"CLEAN",T_ROP!$L$34<>""),COUNTIFS(T_ROP!$C$13:$C$34,$I$4,T_ROP!$L$13:$L$34,"<>CLEAN",T_ROP!$L$13:$L$34,"<>"),"")
A24: FG011 | B24: Krest Tonic Water RGB 300ml | C24: =SUMIFS(T_Load!$O$9:$O$439,T_Load!$D$9:$D$439,$I$4,T_Load!$J$9:$J$439,"FG011") -> 3 | D24: =SUMIFS(T_Sales!$L$9:$L$1164,T_Sales!$D$9:$D$1164,$I$4,T_Sales!$I$9:$I$1164,"FG011") -> 2.3986208 | E24: =C24-D24 -> 0.60137916 | F24: =SUMIFS(T_ROP!$J$13:$J$436,T_ROP!$C$13:$C$436,$I$4,T_ROP!$F$13:$F$436,"FG011") -> 0.6 | G24: =E24-F24 -> 0.001379163 | H24: {=IFERROR(INDEX(M_DepotPrice!$C$10:$C$52,MATCH(1,(M_DepotPrice!$A$10:$A$52=A24)*(M_DepotPrice!$H$10:$H$52=IFERROR(INDEX(M_Depot!$A$7:$A$24,MATCH($G$6,M_Depot!$B$7:$B$24,0)),""))*(M_DepotPrice!$G$10:$G$52="Special"),0)),INDEX(M_DepotPrice!$C$10:$C$52,MATCH(1,(M_DepotPrice!$A$10:$A$52=A24)*(M_DepotPrice!$G$10:$G$52="Default"),0)))*1.18} -> 13900.4 | I24: =SUMIFS(T_Sales!$N$9:$N$1164,T_Sales!$D$9:$D$1164,$I$4,T_Sales!$I$9:$I$1164,"FG011") -> 33341.789 | J24: =IF(C24=0,"-",IF(ABS(G24)<0.0001,"CLEAN",IF(G24>0,"Default Outlet Posting","Unload Adjustment"))) -> Default Outlet Posting | AA24: =IF(AND(T_ROP!$C$35=$I$4,T_ROP!$L$35<>"CLEAN",T_ROP!$L$35<>""),COUNTIFS(T_ROP!$C$13:$C$35,$I$4,T_ROP!$L$13:$L$35,"<>CLEAN",T_ROP!$L$13:$L$35,"<>"),"")
A25: FG012 | B25: Krest Ginger Ale RGB 300ml | C25: =SUMIFS(T_Load!$O$9:$O$439,T_Load!$D$9:$D$439,$I$4,T_Load!$J$9:$J$439,"FG012") -> 2 | D25: =SUMIFS(T_Sales!$L$9:$L$1164,T_Sales!$D$9:$D$1164,$I$4,T_Sales!$I$9:$I$1164,"FG012") -> 1.7311238 | E25: =C25-D25 -> 0.26887616 | F25: =SUMIFS(T_ROP!$J$13:$J$436,T_ROP!$C$13:$C$436,$I$4,T_ROP!$F$13:$F$436,"FG012") -> 0.27 | G25: =E25-F25 -> -0.0011238368 | H25: {=IFERROR(INDEX(M_DepotPrice!$C$10:$C$52,MATCH(1,(M_DepotPrice!$A$10:$A$52=A25)*(M_DepotPrice!$H$10:$H$52=IFERROR(INDEX(M_Depot!$A$7:$A$24,MATCH($G$6,M_Depot!$B$7:$B$24,0)),""))*(M_DepotPrice!$G$10:$G$52="Special"),0)),INDEX(M_DepotPrice!$C$10:$C$52,MATCH(1,(M_DepotPrice!$A$10:$A$52=A25)*(M_DepotPrice!$G$10:$G$52="Default"),0)))*1.18} -> 13900.4 | I25: =SUMIFS(T_Sales!$N$9:$N$1164,T_Sales!$D$9:$D$1164,$I$4,T_Sales!$I$9:$I$1164,"FG012") -> 24063.314 | J25: =IF(C25=0,"-",IF(ABS(G25)<0.0001,"CLEAN",IF(G25>0,"Default Outlet Posting","Unload Adjustment"))) -> Unload Adjustment | AA25: =IF(AND(T_ROP!$C$36=$I$4,T_ROP!$L$36<>"CLEAN",T_ROP!$L$36<>""),COUNTIFS(T_ROP!$C$13:$C$36,$I$4,T_ROP!$L$13:$L$36,"<>CLEAN",T_ROP!$L$13:$L$36,"<>"),"")
A26: FG013 | B26: Coke RGB 250ml | C26: =SUMIFS(T_Load!$O$9:$O$439,T_Load!$D$9:$D$439,$I$4,T_Load!$J$9:$J$439,"FG013") -> 0 | D26: =SUMIFS(T_Sales!$L$9:$L$1164,T_Sales!$D$9:$D$1164,$I$4,T_Sales!$I$9:$I$1164,"FG013") -> 0 | E26: =C26-D26 -> 0 | F26: =SUMIFS(T_ROP!$J$13:$J$436,T_ROP!$C$13:$C$436,$I$4,T_ROP!$F$13:$F$436,"FG013") -> 0 | G26: =E26-F26 -> 0 | H26: {=IFERROR(INDEX(M_DepotPrice!$C$10:$C$52,MATCH(1,(M_DepotPrice!$A$10:$A$52=A26)*(M_DepotPrice!$H$10:$H$52=IFERROR(INDEX(M_Depot!$A$7:$A$24,MATCH($G$6,M_Depot!$B$7:$B$24,0)),""))*(M_DepotPrice!$G$10:$G$52="Special"),0)),INDEX(M_DepotPrice!$C$10:$C$52,MATCH(1,(M_DepotPrice!$A$10:$A$52=A26)*(M_DepotPrice!$G$10:$G$52="Default"),0)))*1.18} -> 10000.5 | I26: =SUMIFS(T_Sales!$N$9:$N$1164,T_Sales!$D$9:$D$1164,$I$4,T_Sales!$I$9:$I$1164,"FG013") -> 0 | J26: =IF(C26=0,"-",IF(ABS(G26)<0.0001,"CLEAN",IF(G26>0,"Default Outlet Posting","Unload Adjustment"))) -> - | AA26: =IF(AND(T_ROP!$C$37=$I$4,T_ROP!$L$37<>"CLEAN",T_ROP!$L$37<>""),COUNTIFS(T_ROP!$C$13:$C$37,$I$4,T_ROP!$L$13:$L$37,"<>CLEAN",T_ROP!$L$13:$L$37,"<>"),"")
A27: FG014 | B27: Fanta Orange RGB 250ml | C27: =SUMIFS(T_Load!$O$9:$O$439,T_Load!$D$9:$D$439,$I$4,T_Load!$J$9:$J$439,"FG014") -> 0 | D27: =SUMIFS(T_Sales!$L$9:$L$1164,T_Sales!$D$9:$D$1164,$I$4,T_Sales!$I$9:$I$1164,"FG014") -> 0 | E27: =C27-D27 -> 0 | F27: =SUMIFS(T_ROP!$J$13:$J$436,T_ROP!$C$13:$C$436,$I$4,T_ROP!$F$13:$F$436,"FG014") -> 0 | G27: =E27-F27 -> 0 | H27: {=IFERROR(INDEX(M_DepotPrice!$C$10:$C$52,MATCH(1,(M_DepotPrice!$A$10:$A$52=A27)*(M_DepotPrice!$H$10:$H$52=IFERROR(INDEX(M_Depot!$A$7:$A$24,MATCH($G$6,M_Depot!$B$7:$B$24,0)),""))*(M_DepotPrice!$G$10:$G$52="Special"),0)),INDEX(M_DepotPrice!$C$10:$C$52,MATCH(1,(M_DepotPrice!$A$10:$A$52=A27)*(M_DepotPrice!$G$10:$G$52="Default"),0)))*1.18} -> 10000.5 | I27: =SUMIFS(T_Sales!$N$9:$N$1164,T_Sales!$D$9:$D$1164,$I$4,T_Sales!$I$9:$I$1164,"FG014") -> 0 | J27: =IF(C27=0,"-",IF(ABS(G27)<0.0001,"CLEAN",IF(G27>0,"Default Outlet Posting","Unload Adjustment"))) -> - | AA27: =IF(AND(T_ROP!$C$38=$I$4,T_ROP!$L$38<>"CLEAN",T_ROP!$L$38<>""),COUNTIFS(T_ROP!$C$13:$C$38,$I$4,T_ROP!$L$13:$L$38,"<>CLEAN",T_ROP!$L$13:$L$38,"<>"),"")
A28: FG024 | B28: Sparletta Red Apple RGB 350ml | C28: =SUMIFS(T_Load!$O$9:$O$439,T_Load!$D$9:$D$439,$I$4,T_Load!$J$9:$J$439,"FG024") -> 2 | D28: =SUMIFS(T_Sales!$L$9:$L$1164,T_Sales!$D$9:$D$1164,$I$4,T_Sales!$I$9:$I$1164,"FG024") -> 1.771884 | E28: =C28-D28 -> 0.22811595 | F28: =SUMIFS(T_ROP!$J$13:$J$436,T_ROP!$C$13:$C$436,$I$4,T_ROP!$F$13:$F$436,"FG024") -> 0.23 | G28: =E28-F28 -> -0.0018840495 | H28: {=IFERROR(INDEX(M_DepotPrice!$C$10:$C$52,MATCH(1,(M_DepotPrice!$A$10:$A$52=A28)*(M_DepotPrice!$H$10:$H$52=IFERROR(INDEX(M_Depot!$A$7:$A$24,MATCH($G$6,M_Depot!$B$7:$B$24,0)),""))*(M_DepotPrice!$G$10:$G$52="Special"),0)),INDEX(M_DepotPrice!$C$10:$C$52,MATCH(1,(M_DepotPrice!$A$10:$A$52=A28)*(M_DepotPrice!$G$10:$G$52="Default"),0)))*1.18} -> 13900.4 | I28: =SUMIFS(T_Sales!$N$9:$N$1164,T_Sales!$D$9:$D$1164,$I$4,T_Sales!$I$9:$I$1164,"FG024") -> 24629.897 | J28: =IF(C28=0,"-",IF(ABS(G28)<0.0001,"CLEAN",IF(G28>0,"Default Outlet Posting","Unload Adjustment"))) -> Unload Adjustment | AA28: =IF(AND(T_ROP!$C$39=$I$4,T_ROP!$L$39<>"CLEAN",T_ROP!$L$39<>""),COUNTIFS(T_ROP!$C$13:$C$39,$I$4,T_ROP!$L$13:$L$39,"<>CLEAN",T_ROP!$L$13:$L$39,"<>"),"")
A29: PET 500 | AA29: =IF(AND(T_ROP!$C$40=$I$4,T_ROP!$L$40<>"CLEAN",T_ROP!$L$40<>""),COUNTIFS(T_ROP!$C$13:$C$40,$I$4,T_ROP!$L$13:$L$40,"<>CLEAN",T_ROP!$L$13:$L$40,"<>"),"")
A30: PH001 | B30: Coke Pet 500ML ( x12) | C30: =SUMIFS(T_Load!$O$9:$O$439,T_Load!$D$9:$D$439,$I$4,T_Load!$J$9:$J$439,"PH001") -> 50 | D30: =SUMIFS(T_Sales!$L$9:$L$1164,T_Sales!$D$9:$D$1164,$I$4,T_Sales!$I$9:$I$1164,"PH001") -> 45 | E30: =C30-D30 -> 5 | F30: =SUMIFS(T_ROP!$J$13:$J$436,T_ROP!$C$13:$C$436,$I$4,T_ROP!$F$13:$F$436,"PH001") -> 5 | G30: =E30-F30 -> 0 | H30: {=IFERROR(INDEX(M_DepotPrice!$C$10:$C$52,MATCH(1,(M_DepotPrice!$A$10:$A$52=A30)*(M_DepotPrice!$H$10:$H$52=IFERROR(INDEX(M_Depot!$A$7:$A$24,MATCH($G$6,M_Depot!$B$7:$B$24,0)),""))*(M_DepotPrice!$G$10:$G$52="Special"),0)),INDEX(M_DepotPrice!$C$10:$C$52,MATCH(1,(M_DepotPrice!$A$10:$A$52=A30)*(M_DepotPrice!$G$10:$G$52="Default"),0)))*1.18} -> 10499.64 | I30: =SUMIFS(T_Sales!$N$9:$N$1164,T_Sales!$D$9:$D$1164,$I$4,T_Sales!$I$9:$I$1164,"PH001") -> 472483.8 | J30: =IF(C30=0,"-",IF(ABS(G30)<0.0001,"CLEAN",IF(G30>0,"Default Outlet Posting","Unload Adjustment"))) -> CLEAN | AA30: =IF(AND(T_ROP!$C$41=$I$4,T_ROP!$L$41<>"CLEAN",T_ROP!$L$41<>""),COUNTIFS(T_ROP!$C$13:$C$41,$I$4,T_ROP!$L$13:$L$41,"<>CLEAN",T_ROP!$L$13:$L$41,"<>"),"")
A31: PH002 | B31: Sprite Pet 500ML (x 12) | C31: =SUMIFS(T_Load!$O$9:$O$439,T_Load!$D$9:$D$439,$I$4,T_Load!$J$9:$J$439,"PH002") -> 10 | D31: =SUMIFS(T_Sales!$L$9:$L$1164,T_Sales!$D$9:$D$1164,$I$4,T_Sales!$I$9:$I$1164,"PH002") -> 8 | E31: =C31-D31 -> 2 | F31: =SUMIFS(T_ROP!$J$13:$J$436,T_ROP!$C$13:$C$436,$I$4,T_ROP!$F$13:$F$436,"PH002") -> 2 | G31: =E31-F31 -> 0 | H31: {=IFERROR(INDEX(M_DepotPrice!$C$10:$C$52,MATCH(1,(M_DepotPrice!$A$10:$A$52=A31)*(M_DepotPrice!$H$10:$H$52=IFERROR(INDEX(M_Depot!$A$7:$A$24,MATCH($G$6,M_Depot!$B$7:$B$24,0)),""))*(M_DepotPrice!$G$10:$G$52="Special"),0)),INDEX(M_DepotPrice!$C$10:$C$52,MATCH(1,(M_DepotPrice!$A$10:$A$52=A31)*(M_DepotPrice!$G$10:$G$52="Default"),0)))*1.18} -> 10499.64 | I31: =SUMIFS(T_Sales!$N$9:$N$1164,T_Sales!$D$9:$D$1164,$I$4,T_Sales!$I$9:$I$1164,"PH002") -> 83997.12 | J31: =IF(C31=0,"-",IF(ABS(G31)<0.0001,"CLEAN",IF(G31>0,"Default Outlet Posting","Unload Adjustment"))) -> CLEAN | AA31: =IF(AND(T_ROP!$C$42=$I$4,T_ROP!$L$42<>"CLEAN",T_ROP!$L$42<>""),COUNTIFS(T_ROP!$C$13:$C$42,$I$4,T_ROP!$L$13:$L$42,"<>CLEAN",T_ROP!$L$13:$L$42,"<>"),"")
A32: PH003 | B32: Fanta Orange Pet 500ML ( x 12) | C32: =SUMIFS(T_Load!$O$9:$O$439,T_Load!$D$9:$D$439,$I$4,T_Load!$J$9:$J$439,"PH003") -> 30 | D32: =SUMIFS(T_Sales!$L$9:$L$1164,T_Sales!$D$9:$D$1164,$I$4,T_Sales!$I$9:$I$1164,"PH003") -> 24 | E32: =C32-D32 -> 6 | F32: =SUMIFS(T_ROP!$J$13:$J$436,T_ROP!$C$13:$C$436,$I$4,T_ROP!$F$13:$F$436,"PH003") -> 6 | G32: =E32-F32 -> 0 | H32: {=IFERROR(INDEX(M_DepotPrice!$C$10:$C$52,MATCH(1,(M_DepotPrice!$A$10:$A$52=A32)*(M_DepotPrice!$H$10:$H$52=IFERROR(INDEX(M_Depot!$A$7:$A$24,MATCH($G$6,M_Depot!$B$7:$B$24,0)),""))*(M_DepotPrice!$G$10:$G$52="Special"),0)),INDEX(M_DepotPrice!$C$10:$C$52,MATCH(1,(M_DepotPrice!$A$10:$A$52=A32)*(M_DepotPrice!$G$10:$G$52="Default"),0)))*1.18} -> 10499.64 | I32: =SUMIFS(T_Sales!$N$9:$N$1164,T_Sales!$D$9:$D$1164,$I$4,T_Sales!$I$9:$I$1164,"PH003") -> 251991.36 | J32: =IF(C32=0,"-",IF(ABS(G32)<0.0001,"CLEAN",IF(G32>0,"Default Outlet Posting","Unload Adjustment"))) -> CLEAN | AA32: =IF(AND(T_ROP!$C$43=$I$4,T_ROP!$L$43<>"CLEAN",T_ROP!$L$43<>""),COUNTIFS(T_ROP!$C$13:$C$43,$I$4,T_ROP!$L$13:$L$43,"<>CLEAN",T_ROP!$L$13:$L$43,"<>"),"")
A33: PH004 | B33: Fanta Passion Pet 500ML ( x12) | C33: =SUMIFS(T_Load!$O$9:$O$439,T_Load!$D$9:$D$439,$I$4,T_Load!$J$9:$J$439,"PH004") -> 8 | D33: =SUMIFS(T_Sales!$L$9:$L$1164,T_Sales!$D$9:$D$1164,$I$4,T_Sales!$I$9:$I$1164,"PH004") -> 7 | E33: =C33-D33 -> 1 | F33: =SUMIFS(T_ROP!$J$13:$J$436,T_ROP!$C$13:$C$436,$I$4,T_ROP!$F$13:$F$436,"PH004") -> 1 | G33: =E33-F33 -> 0 | H33: {=IFERROR(INDEX(M_DepotPrice!$C$10:$C$52,MATCH(1,(M_DepotPrice!$A$10:$A$52=A33)*(M_DepotPrice!$H$10:$H$52=IFERROR(INDEX(M_Depot!$A$7:$A$24,MATCH($G$6,M_Depot!$B$7:$B$24,0)),""))*(M_DepotPrice!$G$10:$G$52="Special"),0)),INDEX(M_DepotPrice!$C$10:$C$52,MATCH(1,(M_DepotPrice!$A$10:$A$52=A33)*(M_DepotPrice!$G$10:$G$52="Default"),0)))*1.18} -> 10499.64 | I33: =SUMIFS(T_Sales!$N$9:$N$1164,T_Sales!$D$9:$D$1164,$I$4,T_Sales!$I$9:$I$1164,"PH004") -> 73497.48 | J33: =IF(C33=0,"-",IF(ABS(G33)<0.0001,"CLEAN",IF(G33>0,"Default Outlet Posting","Unload Adjustment"))) -> CLEAN | AA33: =IF(AND(T_ROP!$C$44=$I$4,T_ROP!$L$44<>"CLEAN",T_ROP!$L$44<>""),COUNTIFS(T_ROP!$C$13:$C$44,$I$4,T_ROP!$L$13:$L$44,"<>CLEAN",T_ROP!$L$13:$L$44,"<>"),"")
A34: PH005 | B34: Fanta Pineapple Pet 500ml ( x12) | C34: =SUMIFS(T_Load!$O$9:$O$439,T_Load!$D$9:$D$439,$I$4,T_Load!$J$9:$J$439,"PH005") -> 0 | D34: =SUMIFS(T_Sales!$L$9:$L$1164,T_Sales!$D$9:$D$1164,$I$4,T_Sales!$I$9:$I$1164,"PH005") -> 0 | E34: =C34-D34 -> 0 | F34: =SUMIFS(T_ROP!$J$13:$J$436,T_ROP!$C$13:$C$436,$I$4,T_ROP!$F$13:$F$436,"PH005") -> 0 | G34: =E34-F34 -> 0 | H34: {=IFERROR(INDEX(M_DepotPrice!$C$10:$C$52,MATCH(1,(M_DepotPrice!$A$10:$A$52=A34)*(M_DepotPrice!$H$10:$H$52=IFERROR(INDEX(M_Depot!$A$7:$A$24,MATCH($G$6,M_Depot!$B$7:$B$24,0)),""))*(M_DepotPrice!$G$10:$G$52="Special"),0)),INDEX(M_DepotPrice!$C$10:$C$52,MATCH(1,(M_DepotPrice!$A$10:$A$52=A34)*(M_DepotPrice!$G$10:$G$52="Default"),0)))*1.18} -> 10499.64 | I34: =SUMIFS(T_Sales!$N$9:$N$1164,T_Sales!$D$9:$D$1164,$I$4,T_Sales!$I$9:$I$1164,"PH005") -> 0 | J34: =IF(C34=0,"-",IF(ABS(G34)<0.0001,"CLEAN",IF(G34>0,"Default Outlet Posting","Unload Adjustment"))) -> - | AA34: =IF(AND(T_ROP!$C$45=$I$4,T_ROP!$L$45<>"CLEAN",T_ROP!$L$45<>""),COUNTIFS(T_ROP!$C$13:$C$45,$I$4,T_ROP!$L$13:$L$45,"<>CLEAN",T_ROP!$L$13:$L$45,"<>"),"")
A35: PH006 | B35: Fanta Fruit Blast Pet 500ML (x12) | C35: =SUMIFS(T_Load!$O$9:$O$439,T_Load!$D$9:$D$439,$I$4,T_Load!$J$9:$J$439,"PH006") -> 5 | D35: =SUMIFS(T_Sales!$L$9:$L$1164,T_Sales!$D$9:$D$1164,$I$4,T_Sales!$I$9:$I$1164,"PH006") -> 4 | E35: =C35-D35 -> 1 | F35: =SUMIFS(T_ROP!$J$13:$J$436,T_ROP!$C$13:$C$436,$I$4,T_ROP!$F$13:$F$436,"PH006") -> 1 | G35: =E35-F35 -> 0 | H35: {=IFERROR(INDEX(M_DepotPrice!$C$10:$C$52,MATCH(1,(M_DepotPrice!$A$10:$A$52=A35)*(M_DepotPrice!$H$10:$H$52=IFERROR(INDEX(M_Depot!$A$7:$A$24,MATCH($G$6,M_Depot!$B$7:$B$24,0)),""))*(M_DepotPrice!$G$10:$G$52="Special"),0)),INDEX(M_DepotPrice!$C$10:$C$52,MATCH(1,(M_DepotPrice!$A$10:$A$52=A35)*(M_DepotPrice!$G$10:$G$52="Default"),0)))*1.18} -> 10499.64 | I35: =SUMIFS(T_Sales!$N$9:$N$1164,T_Sales!$D$9:$D$1164,$I$4,T_Sales!$I$9:$I$1164,"PH006") -> 41998.56 | J35: =IF(C35=0,"-",IF(ABS(G35)<0.0001,"CLEAN",IF(G35>0,"Default Outlet Posting","Unload Adjustment"))) -> CLEAN | AA35: =IF(AND(T_ROP!$C$46=$I$4,T_ROP!$L$46<>"CLEAN",T_ROP!$L$46<>""),COUNTIFS(T_ROP!$C$13:$C$46,$I$4,T_ROP!$L$13:$L$46,"<>CLEAN",T_ROP!$L$13:$L$46,"<>"),"")
A36: PH007 | B36: Stoney Tangawizi Pet 500 ml ( x12) | C36: =SUMIFS(T_Load!$O$9:$O$439,T_Load!$D$9:$D$439,$I$4,T_Load!$J$9:$J$439,"PH007") -> 3 | D36: =SUMIFS(T_Sales!$L$9:$L$1164,T_Sales!$D$9:$D$1164,$I$4,T_Sales!$I$9:$I$1164,"PH007") -> 2 | E36: =C36-D36 -> 1 | F36: =SUMIFS(T_ROP!$J$13:$J$436,T_ROP!$C$13:$C$436,$I$4,T_ROP!$F$13:$F$436,"PH007") -> 1 | G36: =E36-F36 -> 0 | H36: {=IFERROR(INDEX(M_DepotPrice!$C$10:$C$52,MATCH(1,(M_DepotPrice!$A$10:$A$52=A36)*(M_DepotPrice!$H$10:$H$52=IFERROR(INDEX(M_Depot!$A$7:$A$24,MATCH($G$6,M_Depot!$B$7:$B$24,0)),""))*(M_DepotPrice!$G$10:$G$52="Special"),0)),INDEX(M_DepotPrice!$C$10:$C$52,MATCH(1,(M_DepotPrice!$A$10:$A$52=A36)*(M_DepotPrice!$G$10:$G$52="Default"),0)))*1.18} -> 10499.64 | I36: =SUMIFS(T_Sales!$N$9:$N$1164,T_Sales!$D$9:$D$1164,$I$4,T_Sales!$I$9:$I$1164,"PH007") -> 20999.28 | J36: =IF(C36=0,"-",IF(ABS(G36)<0.0001,"CLEAN",IF(G36>0,"Default Outlet Posting","Unload Adjustment"))) -> CLEAN | AA36: =IF(AND(T_ROP!$C$47=$I$4,T_ROP!$L$47<>"CLEAN",T_ROP!$L$47<>""),COUNTIFS(T_ROP!$C$13:$C$47,$I$4,T_ROP!$L$13:$L$47,"<>CLEAN",T_ROP!$L$13:$L$47,"<>"),"")
A37: PH008 | B37: Sparletta Pinenut Pet 500 ml ( x12) | C37: =SUMIFS(T_Load!$O$9:$O$439,T_Load!$D$9:$D$439,$I$4,T_Load!$J$9:$J$439,"PH008") -> 3 | D37: =SUMIFS(T_Sales!$L$9:$L$1164,T_Sales!$D$9:$D$1164,$I$4,T_Sales!$I$9:$I$1164,"PH008") -> 3 | E37: =C37-D37 -> 0 | F37: =SUMIFS(T_ROP!$J$13:$J$436,T_ROP!$C$13:$C$436,$I$4,T_ROP!$F$13:$F$436,"PH008") -> 0 | G37: =E37-F37 -> 0 | H37: {=IFERROR(INDEX(M_DepotPrice!$C$10:$C$52,MATCH(1,(M_DepotPrice!$A$10:$A$52=A37)*(M_DepotPrice!$H$10:$H$52=IFERROR(INDEX(M_Depot!$A$7:$A$24,MATCH($G$6,M_Depot!$B$7:$B$24,0)),""))*(M_DepotPrice!$G$10:$G$52="Special"),0)),INDEX(M_DepotPrice!$C$10:$C$52,MATCH(1,(M_DepotPrice!$A$10:$A$52=A37)*(M_DepotPrice!$G$10:$G$52="Default"),0)))*1.18} -> 10499.64 | I37: =SUMIFS(T_Sales!$N$9:$N$1164,T_Sales!$D$9:$D$1164,$I$4,T_Sales!$I$9:$I$1164,"PH008") -> 31498.92 | J37: =IF(C37=0,"-",IF(ABS(G37)<0.0001,"CLEAN",IF(G37>0,"Default Outlet Posting","Unload Adjustment"))) -> CLEAN | AA37: =IF(AND(T_ROP!$C$48=$I$4,T_ROP!$L$48<>"CLEAN",T_ROP!$L$48<>""),COUNTIFS(T_ROP!$C$13:$C$48,$I$4,T_ROP!$L$13:$L$48,"<>CLEAN",T_ROP!$L$13:$L$48,"<>"),"")
A38: PH009 | B38: Coke Zero Pet 500ML ( X 12) | C38: =SUMIFS(T_Load!$O$9:$O$439,T_Load!$D$9:$D$439,$I$4,T_Load!$J$9:$J$439,"PH009") -> 5 | D38: =SUMIFS(T_Sales!$L$9:$L$1164,T_Sales!$D$9:$D$1164,$I$4,T_Sales!$I$9:$I$1164,"PH009") -> 4 | E38: =C38-D38 -> 1 | F38: =SUMIFS(T_ROP!$J$13:$J$436,T_ROP!$C$13:$C$436,$I$4,T_ROP!$F$13:$F$436,"PH009") -> 1 | G38: =E38-F38 -> 0 | H38: {=IFERROR(INDEX(M_DepotPrice!$C$10:$C$52,MATCH(1,(M_DepotPrice!$A$10:$A$52=A38)*(M_DepotPrice!$H$10:$H$52=IFERROR(INDEX(M_Depot!$A$7:$A$24,MATCH($G$6,M_Depot!$B$7:$B$24,0)),""))*(M_DepotPrice!$G$10:$G$52="Special"),0)),INDEX(M_DepotPrice!$C$10:$C$52,MATCH(1,(M_DepotPrice!$A$10:$A$52=A38)*(M_DepotPrice!$G$10:$G$52="Default"),0)))*1.18} -> 10499.64 | I38: =SUMIFS(T_Sales!$N$9:$N$1164,T_Sales!$D$9:$D$1164,$I$4,T_Sales!$I$9:$I$1164,"PH009") -> 41998.56 | J38: =IF(C38=0,"-",IF(ABS(G38)<0.0001,"CLEAN",IF(G38>0,"Default Outlet Posting","Unload Adjustment"))) -> CLEAN | AA38: =IF(AND(T_ROP!$C$49=$I$4,T_ROP!$L$49<>"CLEAN",T_ROP!$L$49<>""),COUNTIFS(T_ROP!$C$13:$C$49,$I$4,T_ROP!$L$13:$L$49,"<>CLEAN",T_ROP!$L$13:$L$49,"<>"),"")
A39: PET 300 | AA39: =IF(AND(T_ROP!$C$50=$I$4,T_ROP!$L$50<>"CLEAN",T_ROP!$L$50<>""),COUNTIFS(T_ROP!$C$13:$C$50,$I$4,T_ROP!$L$13:$L$50,"<>CLEAN",T_ROP!$L$13:$L$50,"<>"),"")
A40: PO008 | B40: Coke Pet 300ML(x 12) | C40: =SUMIFS(T_Load!$O$9:$O$439,T_Load!$D$9:$D$439,$I$4,T_Load!$J$9:$J$439,"PO008") -> 0 | D40: =SUMIFS(T_Sales!$L$9:$L$1164,T_Sales!$D$9:$D$1164,$I$4,T_Sales!$I$9:$I$1164,"PO008") -> 0 | E40: =C40-D40 -> 0 | F40: =SUMIFS(T_ROP!$J$13:$J$436,T_ROP!$C$13:$C$436,$I$4,T_ROP!$F$13:$F$436,"PO008") -> 0 | G40: =E40-F40 -> 0 | H40: {=IFERROR(INDEX(M_DepotPrice!$C$10:$C$52,MATCH(1,(M_DepotPrice!$A$10:$A$52=A40)*(M_DepotPrice!$H$10:$H$52=IFERROR(INDEX(M_Depot!$A$7:$A$24,MATCH($G$6,M_Depot!$B$7:$B$24,0)),""))*(M_DepotPrice!$G$10:$G$52="Special"),0)),INDEX(M_DepotPrice!$C$10:$C$52,MATCH(1,(M_DepotPrice!$A$10:$A$52=A40)*(M_DepotPrice!$G$10:$G$52="Default"),0)))*1.18} -> 6000.3 | I40: =SUMIFS(T_Sales!$N$9:$N$1164,T_Sales!$D$9:$D$1164,$I$4,T_Sales!$I$9:$I$1164,"PO008") -> 0 | J40: =IF(C40=0,"-",IF(ABS(G40)<0.0001,"CLEAN",IF(G40>0,"Default Outlet Posting","Unload Adjustment"))) -> - | AA40: =IF(AND(T_ROP!$C$51=$I$4,T_ROP!$L$51<>"CLEAN",T_ROP!$L$51<>""),COUNTIFS(T_ROP!$C$13:$C$51,$I$4,T_ROP!$L$13:$L$51,"<>CLEAN",T_ROP!$L$13:$L$51,"<>"),"")
A41: PO009 | B41: Coke Zero Pet 300ML (x 12) | C41: =SUMIFS(T_Load!$O$9:$O$439,T_Load!$D$9:$D$439,$I$4,T_Load!$J$9:$J$439,"PO009") -> 0 | D41: =SUMIFS(T_Sales!$L$9:$L$1164,T_Sales!$D$9:$D$1164,$I$4,T_Sales!$I$9:$I$1164,"PO009") -> 0 | E41: =C41-D41 -> 0 | F41: =SUMIFS(T_ROP!$J$13:$J$436,T_ROP!$C$13:$C$436,$I$4,T_ROP!$F$13:$F$436,"PO009") -> 0 | G41: =E41-F41 -> 0 | H41: {=IFERROR(INDEX(M_DepotPrice!$C$10:$C$52,MATCH(1,(M_DepotPrice!$A$10:$A$52=A41)*(M_DepotPrice!$H$10:$H$52=IFERROR(INDEX(M_Depot!$A$7:$A$24,MATCH($G$6,M_Depot!$B$7:$B$24,0)),""))*(M_DepotPrice!$G$10:$G$52="Special"),0)),INDEX(M_DepotPrice!$C$10:$C$52,MATCH(1,(M_DepotPrice!$A$10:$A$52=A41)*(M_DepotPrice!$G$10:$G$52="Default"),0)))*1.18} -> 6000.3 | I41: =SUMIFS(T_Sales!$N$9:$N$1164,T_Sales!$D$9:$D$1164,$I$4,T_Sales!$I$9:$I$1164,"PO009") -> 0 | J41: =IF(C41=0,"-",IF(ABS(G41)<0.0001,"CLEAN",IF(G41>0,"Default Outlet Posting","Unload Adjustment"))) -> - | AA41: =IF(AND(T_ROP!$C$52=$I$4,T_ROP!$L$52<>"CLEAN",T_ROP!$L$52<>""),COUNTIFS(T_ROP!$C$13:$C$52,$I$4,T_ROP!$L$13:$L$52,"<>CLEAN",T_ROP!$L$13:$L$52,"<>"),"")
A42: PO010 | B42: Sprite Zero Pet 300ML (x 12) | C42: =SUMIFS(T_Load!$O$9:$O$439,T_Load!$D$9:$D$439,$I$4,T_Load!$J$9:$J$439,"PO010") -> 10 | D42: =SUMIFS(T_Sales!$L$9:$L$1164,T_Sales!$D$9:$D$1164,$I$4,T_Sales!$I$9:$I$1164,"PO010") -> 8 | E42: =C42-D42 -> 2 | F42: =SUMIFS(T_ROP!$J$13:$J$436,T_ROP!$C$13:$C$436,$I$4,T_ROP!$F$13:$F$436,"PO010") -> 2 | G42: =E42-F42 -> 0 | H42: {=IFERROR(INDEX(M_DepotPrice!$C$10:$C$52,MATCH(1,(M_DepotPrice!$A$10:$A$52=A42)*(M_DepotPrice!$H$10:$H$52=IFERROR(INDEX(M_Depot!$A$7:$A$24,MATCH($G$6,M_Depot!$B$7:$B$24,0)),""))*(M_DepotPrice!$G$10:$G$52="Special"),0)),INDEX(M_DepotPrice!$C$10:$C$52,MATCH(1,(M_DepotPrice!$A$10:$A$52=A42)*(M_DepotPrice!$G$10:$G$52="Default"),0)))*1.18} -> 6000.3 | I42: =SUMIFS(T_Sales!$N$9:$N$1164,T_Sales!$D$9:$D$1164,$I$4,T_Sales!$I$9:$I$1164,"PO010") -> 48002.4 | J42: =IF(C42=0,"-",IF(ABS(G42)<0.0001,"CLEAN",IF(G42>0,"Default Outlet Posting","Unload Adjustment"))) -> CLEAN | AA42: =IF(AND(T_ROP!$C$53=$I$4,T_ROP!$L$53<>"CLEAN",T_ROP!$L$53<>""),COUNTIFS(T_ROP!$C$13:$C$53,$I$4,T_ROP!$L$13:$L$53,"<>CLEAN",T_ROP!$L$13:$L$53,"<>"),"")
A43: PO012 | B43: Fanta Zero Pet 300ML (x 12) | C43: =SUMIFS(T_Load!$O$9:$O$439,T_Load!$D$9:$D$439,$I$4,T_Load!$J$9:$J$439,"PO012") -> 10 | D43: =SUMIFS(T_Sales!$L$9:$L$1164,T_Sales!$D$9:$D$1164,$I$4,T_Sales!$I$9:$I$1164,"PO012") -> 8 | E43: =C43-D43 -> 2 | F43: =SUMIFS(T_ROP!$J$13:$J$436,T_ROP!$C$13:$C$436,$I$4,T_ROP!$F$13:$F$436,"PO012") -> 2 | G43: =E43-F43 -> 0 | H43: {=IFERROR(INDEX(M_DepotPrice!$C$10:$C$52,MATCH(1,(M_DepotPrice!$A$10:$A$52=A43)*(M_DepotPrice!$H$10:$H$52=IFERROR(INDEX(M_Depot!$A$7:$A$24,MATCH($G$6,M_Depot!$B$7:$B$24,0)),""))*(M_DepotPrice!$G$10:$G$52="Special"),0)),INDEX(M_DepotPrice!$C$10:$C$52,MATCH(1,(M_DepotPrice!$A$10:$A$52=A43)*(M_DepotPrice!$G$10:$G$52="Default"),0)))*1.18} -> 6000.3 | I43: =SUMIFS(T_Sales!$N$9:$N$1164,T_Sales!$D$9:$D$1164,$I$4,T_Sales!$I$9:$I$1164,"PO012") -> 48002.4 | J43: =IF(C43=0,"-",IF(ABS(G43)<0.0001,"CLEAN",IF(G43>0,"Default Outlet Posting","Unload Adjustment"))) -> CLEAN | AA43: =IF(AND(T_ROP!$C$54=$I$4,T_ROP!$L$54<>"CLEAN",T_ROP!$L$54<>""),COUNTIFS(T_ROP!$C$13:$C$54,$I$4,T_ROP!$L$13:$L$54,"<>CLEAN",T_ROP!$L$13:$L$54,"<>"),"")
A44: PO013 | B44: Sparletta Red Apple Pet 300ML(x 12) | C44: =SUMIFS(T_Load!$O$9:$O$439,T_Load!$D$9:$D$439,$I$4,T_Load!$J$9:$J$439,"PO013") -> 0 | D44: =SUMIFS(T_Sales!$L$9:$L$1164,T_Sales!$D$9:$D$1164,$I$4,T_Sales!$I$9:$I$1164,"PO013") -> 0 | E44: =C44-D44 -> 0 | F44: =SUMIFS(T_ROP!$J$13:$J$436,T_ROP!$C$13:$C$436,$I$4,T_ROP!$F$13:$F$436,"PO013") -> 0 | G44: =E44-F44 -> 0 | H44: {=IFERROR(INDEX(M_DepotPrice!$C$10:$C$52,MATCH(1,(M_DepotPrice!$A$10:$A$52=A44)*(M_DepotPrice!$H$10:$H$52=IFERROR(INDEX(M_Depot!$A$7:$A$24,MATCH($G$6,M_Depot!$B$7:$B$24,0)),""))*(M_DepotPrice!$G$10:$G$52="Special"),0)),INDEX(M_DepotPrice!$C$10:$C$52,MATCH(1,(M_DepotPrice!$A$10:$A$52=A44)*(M_DepotPrice!$G$10:$G$52="Default"),0)))*1.18} -> 6000.3 | I44: =SUMIFS(T_Sales!$N$9:$N$1164,T_Sales!$D$9:$D$1164,$I$4,T_Sales!$I$9:$I$1164,"PO013") -> 0 | J44: =IF(C44=0,"-",IF(ABS(G44)<0.0001,"CLEAN",IF(G44>0,"Default Outlet Posting","Unload Adjustment"))) -> - | AA44: =IF(AND(T_ROP!$C$55=$I$4,T_ROP!$L$55<>"CLEAN",T_ROP!$L$55<>""),COUNTIFS(T_ROP!$C$13:$C$55,$I$4,T_ROP!$L$13:$L$55,"<>CLEAN",T_ROP!$L$13:$L$55,"<>"),"")
A45: PO014 | B45: Novida Pineapple 300ML (x 12) | C45: =SUMIFS(T_Load!$O$9:$O$439,T_Load!$D$9:$D$439,$I$4,T_Load!$J$9:$J$439,"PO014") -> 0 | D45: =SUMIFS(T_Sales!$L$9:$L$1164,T_Sales!$D$9:$D$1164,$I$4,T_Sales!$I$9:$I$1164,"PO014") -> 0 | E45: =C45-D45 -> 0 | F45: =SUMIFS(T_ROP!$J$13:$J$436,T_ROP!$C$13:$C$436,$I$4,T_ROP!$F$13:$F$436,"PO014") -> 0 | G45: =E45-F45 -> 0 | H45: {=IFERROR(INDEX(M_DepotPrice!$C$10:$C$52,MATCH(1,(M_DepotPrice!$A$10:$A$52=A45)*(M_DepotPrice!$H$10:$H$52=IFERROR(INDEX(M_Depot!$A$7:$A$24,MATCH($G$6,M_Depot!$B$7:$B$24,0)),""))*(M_DepotPrice!$G$10:$G$52="Special"),0)),INDEX(M_DepotPrice!$C$10:$C$52,MATCH(1,(M_DepotPrice!$A$10:$A$52=A45)*(M_DepotPrice!$G$10:$G$52="Default"),0)))*1.18} -> 6000.3 | I45: =SUMIFS(T_Sales!$N$9:$N$1164,T_Sales!$D$9:$D$1164,$I$4,T_Sales!$I$9:$I$1164,"PO014") -> 0 | J45: =IF(C45=0,"-",IF(ABS(G45)<0.0001,"CLEAN",IF(G45>0,"Default Outlet Posting","Unload Adjustment"))) -> - | AA45: =IF(AND(T_ROP!$C$56=$I$4,T_ROP!$L$56<>"CLEAN",T_ROP!$L$56<>""),COUNTIFS(T_ROP!$C$13:$C$56,$I$4,T_ROP!$L$13:$L$56,"<>CLEAN",T_ROP!$L$13:$L$56,"<>"),"")
A46: PO015 | B46: Sparletta Pine Apple Pet 300ML (x 12) | C46: =SUMIFS(T_Load!$O$9:$O$439,T_Load!$D$9:$D$439,$I$4,T_Load!$J$9:$J$439,"PO015") -> 15 | D46: =SUMIFS(T_Sales!$L$9:$L$1164,T_Sales!$D$9:$D$1164,$I$4,T_Sales!$I$9:$I$1164,"PO015") -> 11 | E46: =C46-D46 -> 4 | F46: =SUMIFS(T_ROP!$J$13:$J$436,T_ROP!$C$13:$C$436,$I$4,T_ROP!$F$13:$F$436,"PO015") -> 4 | G46: =E46-F46 -> 0 | H46: {=IFERROR(INDEX(M_DepotPrice!$C$10:$C$52,MATCH(1,(M_DepotPrice!$A$10:$A$52=A46)*(M_DepotPrice!$H$10:$H$52=IFERROR(INDEX(M_Depot!$A$7:$A$24,MATCH($G$6,M_Depot!$B$7:$B$24,0)),""))*(M_DepotPrice!$G$10:$G$52="Special"),0)),INDEX(M_DepotPrice!$C$10:$C$52,MATCH(1,(M_DepotPrice!$A$10:$A$52=A46)*(M_DepotPrice!$G$10:$G$52="Default"),0)))*1.18} -> 6000.3 | I46: =SUMIFS(T_Sales!$N$9:$N$1164,T_Sales!$D$9:$D$1164,$I$4,T_Sales!$I$9:$I$1164,"PO015") -> 66003.3 | J46: =IF(C46=0,"-",IF(ABS(G46)<0.0001,"CLEAN",IF(G46>0,"Default Outlet Posting","Unload Adjustment"))) -> CLEAN | AA46: =IF(AND(T_ROP!$C$57=$I$4,T_ROP!$L$57<>"CLEAN",T_ROP!$L$57<>""),COUNTIFS(T_ROP!$C$13:$C$57,$I$4,T_ROP!$L$13:$L$57,"<>CLEAN",T_ROP!$L$13:$L$57,"<>"),"")
A47: PET 1250 | AA47: =IF(AND(T_ROP!$C$58=$I$4,T_ROP!$L$58<>"CLEAN",T_ROP!$L$58<>""),COUNTIFS(T_ROP!$C$13:$C$58,$I$4,T_ROP!$L$13:$L$58,"<>CLEAN",T_ROP!$L$13:$L$58,"<>"),"")
A48: PT005 | B48: Coke 1250 Pet ML | C48: =SUMIFS(T_Load!$O$9:$O$439,T_Load!$D$9:$D$439,$I$4,T_Load!$J$9:$J$439,"PT005") -> 0 | D48: =SUMIFS(T_Sales!$L$9:$L$1164,T_Sales!$D$9:$D$1164,$I$4,T_Sales!$I$9:$I$1164,"PT005") -> 0 | E48: =C48-D48 -> 0 | F48: =SUMIFS(T_ROP!$J$13:$J$436,T_ROP!$C$13:$C$436,$I$4,T_ROP!$F$13:$F$436,"PT005") -> 0 | G48: =E48-F48 -> 0 | H48: {=IFERROR(INDEX(M_DepotPrice!$C$10:$C$52,MATCH(1,(M_DepotPrice!$A$10:$A$52=A48)*(M_DepotPrice!$H$10:$H$52=IFERROR(INDEX(M_Depot!$A$7:$A$24,MATCH($G$6,M_Depot!$B$7:$B$24,0)),""))*(M_DepotPrice!$G$10:$G$52="Special"),0)),INDEX(M_DepotPrice!$C$10:$C$52,MATCH(1,(M_DepotPrice!$A$10:$A$52=A48)*(M_DepotPrice!$G$10:$G$52="Default"),0)))*1.18} -> 9799.9 | I48: =SUMIFS(T_Sales!$N$9:$N$1164,T_Sales!$D$9:$D$1164,$I$4,T_Sales!$I$9:$I$1164,"PT005") -> 0 | J48: =IF(C48=0,"-",IF(ABS(G48)<0.0001,"CLEAN",IF(G48>0,"Default Outlet Posting","Unload Adjustment"))) -> - | AA48: =IF(AND(T_ROP!$C$59=$I$4,T_ROP!$L$59<>"CLEAN",T_ROP!$L$59<>""),COUNTIFS(T_ROP!$C$13:$C$59,$I$4,T_ROP!$L$13:$L$59,"<>CLEAN",T_ROP!$L$13:$L$59,"<>"),"")
A49: PT006 | B49: Sprite Pet 1250 ML | C49: =SUMIFS(T_Load!$O$9:$O$439,T_Load!$D$9:$D$439,$I$4,T_Load!$J$9:$J$439,"PT006") -> 0 | D49: =SUMIFS(T_Sales!$L$9:$L$1164,T_Sales!$D$9:$D$1164,$I$4,T_Sales!$I$9:$I$1164,"PT006") -> 0 | E49: =C49-D49 -> 0 | F49: =SUMIFS(T_ROP!$J$13:$J$436,T_ROP!$C$13:$C$436,$I$4,T_ROP!$F$13:$F$436,"PT006") -> 0 | G49: =E49-F49 -> 0 | H49: {=IFERROR(INDEX(M_DepotPrice!$C$10:$C$52,MATCH(1,(M_DepotPrice!$A$10:$A$52=A49)*(M_DepotPrice!$H$10:$H$52=IFERROR(INDEX(M_Depot!$A$7:$A$24,MATCH($G$6,M_Depot!$B$7:$B$24,0)),""))*(M_DepotPrice!$G$10:$G$52="Special"),0)),INDEX(M_DepotPrice!$C$10:$C$52,MATCH(1,(M_DepotPrice!$A$10:$A$52=A49)*(M_DepotPrice!$G$10:$G$52="Default"),0)))*1.18} -> 9799.9 | I49: =SUMIFS(T_Sales!$N$9:$N$1164,T_Sales!$D$9:$D$1164,$I$4,T_Sales!$I$9:$I$1164,"PT006") -> 0 | J49: =IF(C49=0,"-",IF(ABS(G49)<0.0001,"CLEAN",IF(G49>0,"Default Outlet Posting","Unload Adjustment"))) -> - | AA49: =IF(AND(T_ROP!$C$60=$I$4,T_ROP!$L$60<>"CLEAN",T_ROP!$L$60<>""),COUNTIFS(T_ROP!$C$13:$C$60,$I$4,T_ROP!$L$13:$L$60,"<>CLEAN",T_ROP!$L$13:$L$60,"<>"),"")
A50: PT007 | B50: Fanta Orange Pet 1250 ML | C50: =SUMIFS(T_Load!$O$9:$O$439,T_Load!$D$9:$D$439,$I$4,T_Load!$J$9:$J$439,"PT007") -> 0 | D50: =SUMIFS(T_Sales!$L$9:$L$1164,T_Sales!$D$9:$D$1164,$I$4,T_Sales!$I$9:$I$1164,"PT007") -> 0 | E50: =C50-D50 -> 0 | F50: =SUMIFS(T_ROP!$J$13:$J$436,T_ROP!$C$13:$C$436,$I$4,T_ROP!$F$13:$F$436,"PT007") -> 0 | G50: =E50-F50 -> 0 | H50: {=IFERROR(INDEX(M_DepotPrice!$C$10:$C$52,MATCH(1,(M_DepotPrice!$A$10:$A$52=A50)*(M_DepotPrice!$H$10:$H$52=IFERROR(INDEX(M_Depot!$A$7:$A$24,MATCH($G$6,M_Depot!$B$7:$B$24,0)),""))*(M_DepotPrice!$G$10:$G$52="Special"),0)),INDEX(M_DepotPrice!$C$10:$C$52,MATCH(1,(M_DepotPrice!$A$10:$A$52=A50)*(M_DepotPrice!$G$10:$G$52="Default"),0)))*1.18} -> 9799.9 | I50: =SUMIFS(T_Sales!$N$9:$N$1164,T_Sales!$D$9:$D$1164,$I$4,T_Sales!$I$9:$I$1164,"PT007") -> 0 | J50: =IF(C50=0,"-",IF(ABS(G50)<0.0001,"CLEAN",IF(G50>0,"Default Outlet Posting","Unload Adjustment"))) -> - | AA50: =IF(AND(T_ROP!$C$61=$I$4,T_ROP!$L$61<>"CLEAN",T_ROP!$L$61<>""),COUNTIFS(T_ROP!$C$13:$C$61,$I$4,T_ROP!$L$13:$L$61,"<>CLEAN",T_ROP!$L$13:$L$61,"<>"),"")
A51: KNMW | AA51: =IF(AND(T_ROP!$C$62=$I$4,T_ROP!$L$62<>"CLEAN",T_ROP!$L$62<>""),COUNTIFS(T_ROP!$C$13:$C$62,$I$4,T_ROP!$L$13:$L$62,"<>CLEAN",T_ROP!$L$13:$L$62,"<>"),"")
A52: KD001 | B52: KNMW 500ml | C52: =SUMIFS(T_Load!$O$9:$O$439,T_Load!$D$9:$D$439,$I$4,T_Load!$J$9:$J$439,"KD001") -> 50 | D52: =SUMIFS(T_Sales!$L$9:$L$1164,T_Sales!$D$9:$D$1164,$I$4,T_Sales!$I$9:$I$1164,"KD001") -> 39 | E52: =C52-D52 -> 11 | F52: =SUMIFS(T_ROP!$J$13:$J$436,T_ROP!$C$13:$C$436,$I$4,T_ROP!$F$13:$F$436,"KD001") -> 11 | G52: =E52-F52 -> 0 | H52: {=IFERROR(INDEX(M_DepotPrice!$C$10:$C$52,MATCH(1,(M_DepotPrice!$A$10:$A$52=A52)*(M_DepotPrice!$H$10:$H$52=IFERROR(INDEX(M_Depot!$A$7:$A$24,MATCH($G$6,M_Depot!$B$7:$B$24,0)),""))*(M_DepotPrice!$G$10:$G$52="Special"),0)),INDEX(M_DepotPrice!$C$10:$C$52,MATCH(1,(M_DepotPrice!$A$10:$A$52=A52)*(M_DepotPrice!$G$10:$G$52="Default"),0)))*1.18} -> 4199.62 | I52: =SUMIFS(T_Sales!$N$9:$N$1164,T_Sales!$D$9:$D$1164,$I$4,T_Sales!$I$9:$I$1164,"KD001") -> 163785.18 | J52: =IF(C52=0,"-",IF(ABS(G52)<0.0001,"CLEAN",IF(G52>0,"Default Outlet Posting","Unload Adjustment"))) -> CLEAN | AA52: =IF(AND(T_ROP!$C$63=$I$4,T_ROP!$L$63<>"CLEAN",T_ROP!$L$63<>""),COUNTIFS(T_ROP!$C$13:$C$63,$I$4,T_ROP!$L$13:$L$63,"<>CLEAN",T_ROP!$L$13:$L$63,"<>"),"")
